Workbook
Name ANNEE: #REF!
Name Budget: [1]Budget!$B$5:$O$28
Name Budget: #REF!
Name BudgetCum: [1]Budget!$B$31:$O$54
Name BudgetCum: #REF!
Name CA: [2]TDB!$B$4:$O$15
Name CA: [2]TDB!$B$4:$O$15
Name CA: [2]TDB!$B$4:$O$15
Name CA: [2]TDB!$B$4:$O$15
Name CA: [2]TDB!$B$4:$O$15
Name CA: [3]TDB!$B$4:$O$15
Name cge: #REF!
Name cge: #REF!
Name CH: [2]TDB!$A$20:$O$42
Name CH: [2]TDB!$A$20:$O$42
Name CH: [2]TDB!$A$20:$O$42
Name CH: [2]TDB!$A$20:$O$42
Name CH: [2]TDB!$A$20:$O$42
Name CH: [3]TDB!$A$20:$O$42
Name data1: '[4]Cal. 1'!$AQ$4:$AQ$23
Name data1: '[5]Cal. 1'!$AQ$4:$AQ$23
Name data1: '[4]Cal. 1'!$AQ$4:$AQ$23
Name data1: '[4]Cal. 1'!$AQ$4:$AQ$23
Name data1: '[4]Cal. 1'!$AQ$4:$AQ$23
Name data1: '[4]Cal. 1'!$AQ$4:$AQ$23
Name data1: '[5]Cal. 1'!$AQ$4:$AQ$23
Name data2: '[4]Cal. 1'!$AT$4:$AT$23
Name data2: '[5]Cal. 1'!$AT$4:$AT$23
Name data2: '[4]Cal. 1'!$AT$4:$AT$23
Name data2: '[4]Cal. 1'!$AT$4:$AT$23
Name data2: '[4]Cal. 1'!$AT$4:$AT$23
Name data2: '[4]Cal. 1'!$AT$4:$AT$23
Name data2: '[5]Cal. 1'!$AT$4:$AT$23
Name Entrée: #REF!
Name f: #REF!
Name f: #REF!
Name Feries: [4]BDD!$A$2:$A$18
Name Feries: [5]BDD!$A$2:$A$18
Name Feries: [4]BDD!$A$2:$A$18
Name Feries: [4]BDD!$A$2:$A$18
Name Feries: [4]BDD!$A$2:$A$18
Name Feries: [4]BDD!$A$2:$A$18
Name Feries: [5]BDD!$A$2:$A$18
Name Fournisseur: #REF!+#REF!
Name Frais: [6]Annexe!$A$4:$A$21
Name nom: #REF!
Name nom: #REF!
Name Obj: '[1]CA Objectif'!$B$3:$O$13
Name Obj: #REF!
Name OCA: '[2]TDB prev'!$B$2:$O$13
Name OCA: '[2]TDB prev'!$B$2:$O$13
Name OCA: '[2]TDB prev'!$B$2:$O$13
Name OCA: '[2]TDB prev'!$B$2:$O$13
Name OCA: '[2]TDB prev'!$B$2:$O$13
Name OCA: '[3]TDB prev'!$B$2:$O$13
Name OCH: '[2]TDB prev'!$B$16:$O$38
Name OCH: '[2]TDB prev'!$B$16:$O$38
Name OCH: '[2]TDB prev'!$B$16:$O$38
Name OCH: '[2]TDB prev'!$B$16:$O$38
Name OCH: '[2]TDB prev'!$B$16:$O$38

Sheet Données
A1: الشركة | B1: صياغة الفتح
A2: السنة التجارية | B2: 2023-2024
A4: تاريخ بداية السنة التجارية | B4: 45142
A6: تاريخ نهاية السنة التجارية | B6: 45583
A8: عدد أيام السنة التجارية | B8: =B6-B4 -> 441
A10: نسبة الزكاة | B10: =ROUNDUP((B8*2.5%)/355,4) -> 0.0311
A12: المكلف بالتصفية: | B12: الواهج عمر
A13: المستلم منه المعلومات: | B13: الواهج عمر
A14: يوم تسليم الميزانية:

Sheet Nv capital
A1: ="حساب رؤوس الأموال الجديدة لسنة "&Données!B2 -> حساب رؤوس الأموال الجديدة لسنة 2023-2024
E3: رأس المال الافتتاحي | F3: مخارج رأس المال | G3: مداخيل رأس المال | H3: رأس المال 2016-2017
D4: صياغة الفتح | E4: =C9-D9 -> 33804739 | F4: =G5+G6 -> 13114674 | G4: =+E9 -> 3100310 | H4: =E4-F4+G4 -> 23790375
D5: الورشة B2 | G5: =8665344.67+1115281 -> 9780625.7 | H5: =E5-F5+G5 -> 9780625.7
D6: الورشة B1 | G6: =3052625+281423.22 -> 3334048.2 | H6: =E6-F6+G6 -> 3334048.2
D7: المجموع | E7: =SUM(E4:E6) -> 33804739 | F7: =SUM(F4:F6) -> 13114674 | G7: =SUM(G4:G6) -> 16214984 | H7: =SUM(H4:H6) -> 36905049
C9: =SUBTOTAL(9,C11:C82) -> 33804739 | D9: =SUBTOTAL(9,D11:D1799) -> 0 | E9: =SUBTOTAL(9,E11:E82) -> 3100310 | H9: =SUBTOTAL(9,H11:H1799) -> 36905049 | I9: =SUBTOTAL(9,I11:I1799) -> 35626133
A10: الرقم | B10: الشركاء | C10: رؤوس الأموال نهاية 2024-2023 | D10: ="سحوبات "&Données!$B$2 -> سحوبات 2023-2024 | E10: ="مداخيل "&Données!$B$2 -> مداخيل 2023-2024 | F10: التاريخ | G10: عدد أيام العمل | H10: ="رؤوس الأموال "&Données!$B$2 -> رؤوس الأموال 2023-2024 | I10: رأس المال النسبي
A11: 1 | B11: الواهج عمر بن يحي | G11: =IF(F11="",Données!$B$6-Données!$B$4,Données!$B$6-F11) -> 441 | H11: =C11-D11+E11 -> 0 | I11: =C11-D11+E11*(G11/Données!$B$8) -> 0
A12: 2 | B12: بن عزوز مبخوتة | C12: 10000000 | G12: =IF(F12="",Données!$B$6-Données!$B$4,Données!$B$6-F12) -> 441 | H12: =C12-D12+E12 -> 10000000 | I12: =C12-D12+E12*(G12/Données!$B$8) -> 10000000
A13: 3 | B13: كروشي الحاج بابهون | C13: =10405921.17-238000 -> 10167921 | G13: =IF(F13="",Données!$B$6-Données!$B$4,Données!$B$6-F13) -> 441 | H13: =C13-D13+E13 -> 10167921 | I13: =C13-D13+E13*(G13/Données!$B$8) -> 10167921
A14: 4 | B14: بوسربة ياسمينة | C14: 607993.9 | G14: =IF(F14="",Données!$B$6-Données!$B$4,Données!$B$6-F14) -> 441 | H14: =C14-D14+E14 -> 607993.9 | I14: =C14-D14+E14*(G14/Données!$B$8) -> 607993.9
A15: 5 | B15: بعوشي رسثم | C15: 1000000 | G15: =IF(F15="",Données!$B$6-Données!$B$4,Données!$B$6-F15) -> 441 | H15: =C15-D15+E15 -> 1000000 | I15: =C15-D15+E15*(G15/Données!$B$8) -> 1000000
A16: 6 | B16: بوسريح نعيمة | C16: 500000 | G16: =IF(F16="",Données!$B$6-Données!$B$4,Données!$B$6-F16) -> 441 | H16: =C16-D16+E16 -> 500000 | I16: =C16-D16+E16*(G16/Données!$B$8) -> 500000
A17: 7 | B17: بكاير حرمية بنت محمد | C17: 719297.09 | G17: =IF(F17="",Données!$B$6-Données!$B$4,Données!$B$6-F17) -> 441 | H17: =C17-D17+E17 -> 719297.09 | I17: =C17-D17+E17*(G17/Données!$B$8) -> 719297.09
A18: 8 | B18: بكاير رابح بن محمد | C18: =2508503.53-325000 -> 2183503.5 | G18: =IF(F18="",Données!$B$6-Données!$B$4,Données!$B$6-F18) -> 441 | H18: =C18-D18+E18 -> 2183503.5 | I18: =C18-D18+E18*(G18/Données!$B$8) -> 2183503.5
A19: 9 | B19: لعساكر عبد الحميد | C19: =1406263.99-31000 -> 1375264 | G19: =IF(F19="",Données!$B$6-Données!$B$4,Données!$B$6-F19) -> 441 | H19: =C19-D19+E19 -> 1375264 | I19: =C19-D19+E19*(G19/Données!$B$8) -> 1375264
A20: 10 | B20: الواهج احمد | C20: 708995.97 | G20: =IF(F20="",Données!$B$6-Données!$B$4,Données!$B$6-F20) -> 441 | H20: =C20-D20+E20 -> 708995.97 | I20: =C20-D20+E20*(G20/Données!$B$8) -> 708995.97
A21: 11 | B21: مبروك مبروك طولقة | C21: 3000000 | G21: =IF(F21="",Données!$B$6-Données!$B$4,Données!$B$6-F21) -> 441 | H21: =C21-D21+E21 -> 3000000 | I21: =C21-D21+E21*(G21/Données!$B$8) -> 3000000
A22: 12 | B22: بن يامي فؤاد بن علي | C22: 340739.85 | G22: =IF(F22="",Données!$B$6-Données!$B$4,Données!$B$6-F22) -> 441 | H22: =C22-D22+E22 -> 340739.85 | I22: =C22-D22+E22*(G22/Données!$B$8) -> 340739.85
A23: 13 | B23: الواهج اسية | C23: 513448.84 | G23: =IF(F23="",Données!$B$6-Données!$B$4,Données!$B$6-F23) -> 441 | H23: =C23-D23+E23 -> 513448.84 | I23: =C23-D23+E23*(G23/Données!$B$8) -> 513448.84
A24: 14 | B24: صالح والحاج خوخة | C24: =22019.02+50104.05 -> 72123.07 | G24: =IF(F24="",Données!$B$6-Données!$B$4,Données!$B$6-F24) -> 441 | H24: =C24-D24+E24 -> 72123.07 | I24: =C24-D24+E24*(G24/Données!$B$8) -> 72123.07
A25: 15 | B25: الواهج مامة | E25: 500000 | F25: 45376 | G25: =IF(F25="",Données!$B$6-Données!$B$4,Données!$B$6-F25) -> 207 | H25: =C25-D25+E25 -> 500000 | I25: =C25-D25+E25*(G25/Données!$B$8) -> 234693.88
A26: 16 | B26: صالح والحاج فاطمة | C26: 22034.67 | G26: =IF(F26="",Données!$B$6-Données!$B$4,Données!$B$6-F26) -> 441 | H26: =C26-D26+E26 -> 22034.67 | I26: =C26-D26+E26*(G26/Données!$B$8) -> 22034.67
A27: 17 | B27: موسى المال سليمان | C27: 642035.45 | G27: =IF(F27="",Données!$B$6-Données!$B$4,Données!$B$6-F27) -> 441 | H27: =C27-D27+E27 -> 642035.45 | I27: =C27-D27+E27*(G27/Données!$B$8) -> 642035.45
A28: 18 | B28: باسليمان محمد بن صالح | C28: 403492.59 | G28: =IF(F28="",Données!$B$6-Données!$B$4,Données!$B$6-F28) -> 441 | H28: =C28-D28+E28 -> 403492.59 | I28: =C28-D28+E28*(G28/Données!$B$8) -> 403492.59
A29: 19 | B29: بن يامي اسلام بن حمزة | E29: 70000 | F29: 45238 | G29: =IF(F29="",Données!$B$6-Données!$B$4,Données!$B$6-F29) -> 345 | H29: =C29-D29+E29 -> 70000 | I29: =C29-D29+E29*(G29/Données!$B$8) -> 54761.905
A30: 20 | B30: بن يامي محمد بن حمزة | E30: 100000 | F30: 45238 | G30: =IF(F30="",Données!$B$6-Données!$B$4,Données!$B$6-F30) -> 345 | H30: =C30-D30+E30 -> 100000 | I30: =C30-D30+E30*(G30/Données!$B$8) -> 78231.293
A31: 21 | B31: خن لقمان | E31: 110310 | F31: 45342 | G31: =IF(F31="",Données!$B$6-Données!$B$4,Données!$B$6-F31) -> 241 | H31: =C31-D31+E31 -> 110310 | I31: =C31-D31+E31*(G31/Données!$B$8) -> 60282.789
A32: 22 | B32: مدرسة فسايل الامل | E32: 1200000 | F32: 45242 | G32: =IF(F32="",Données!$B$6-Données!$B$4,Données!$B$6-F32) -> 341 | H32: =C32-D32+E32 -> 1200000 | I32: =C32-D32+E32*(G32/Données!$B$8) -> 927891.16
A33: 23 | B33: الواهج فاطمة الزهراء | E33: 100000 | F33: 45558 | G33: =IF(F33="",Données!$B$6-Données!$B$4,Données!$B$6-F33) -> 25 | H33: =C33-D33+E33 -> 100000 | I33: =C33-D33+E33*(G33/Données!$B$8) -> 5668.9342
A34: 24 | B34: الواهج لالة | E34: 180000 | F34: 45351 | G34: =IF(F34="",Données!$B$6-Données!$B$4,Données!$B$6-F34) -> 232 | H34: =C34-D34+E34 -> 180000 | I34: =C34-D34+E34*(G34/Données!$B$8) -> 94693.878
A35: 25 | B35: صالح والحاج ادريس بن سليمان | E35: 100000 | F35: 45487 | G35: =IF(F35="",Données!$B$6-Données!$B$4,Données!$B$6-F35) -> 96 | H35: =C35-D35+E35 -> 100000 | I35: =C35-D35+E35*(G35/Données!$B$8) -> 21768.707
A36: 26 | B36: صالح والحاج سليمان بن عمر | E36: 100000 | F36: 45185 | G36: =IF(F36="",Données!$B$6-Données!$B$4,Données!$B$6-F36) -> 398 | H36: =C36-D36+E36 -> 100000 | I36: =C36-D36+E36*(G36/Données!$B$8) -> 90249.433
A37: 27 | B37: صالح والحاج سليمان ين عمر | E37: 500000 | F37: 45444 | G37: =IF(F37="",Données!$B$6-Données!$B$4,Données!$B$6-F37) -> 139 | H37: =C37-D37+E37 -> 500000 | I37: =C37-D37+E37*(G37/Données!$B$8) -> 157596.37
A38: 28 | B38: طالب باحمد نانة | E38: 40000 | F38: 45342 | G38: =IF(F38="",Données!$B$6-Données!$B$4,Données!$B$6-F38) -> 241 | H38: =C38-D38+E38 -> 40000 | I38: =C38-D38+E38*(G38/Données!$B$8) -> 21859.41
A39: 29 | B39: النادي الرياضي فسائل الامل | E39: 100000 | F39: 45258 | G39: =IF(F39="",Données!$B$6-Données!$B$4,Données!$B$6-F39) -> 325 | H39: =C39-D39+E39 -> 100000 | I39: =C39-D39+E39*(G39/Données!$B$8) -> 73696.145
A40: 30 | B40: الواهج عمر بن يحي بن حمو | C40: 1547888.9 | G40: =IF(F40="",Données!$B$6-Données!$B$4,Données!$B$6-F40) -> 441 | H40: =C40-D40+E40 -> 1547888.9 | I40: =C40-D40+E40*(G40/Données!$B$8) -> 1547888.9 | J40: امانة من سنة 2022 ليست في ذمتي 1547888.92

Sheet  Bilan cloture
A1: ="ميزانية مؤسسة "&Données!B1&" في "&DAY(Données!$B$6)&"/"&MONTH(Données!$B$6)&"/"&YEAR(Données!$B$6) -> ميزانية مؤسسة صياغة الفتح في 18/10/2024
A3: Actif / الأصول | F3: Passif / الخصوم
A4: Code | B4: Libéllé de l'Opération | D4: Montant | F4: Code | G4: Libéllé de l'Opération | I4: Montant
A5: Compta | F5: Compta
A6: =D6/D29 -> 0.051069103 | B6: Investissement / الاستثمارات | D6: =SUM(D7:D10) -> 4085540 | F6: =I6/I29 -> 0.29737883 | G6: Fonds Propres / رؤوس الأموال | I6: =SUM(I7:I10) -> 23790375
A7: 2 | B7: Materiels & équipements | C7: التجهيزات | D7: ='Invest Mag'!D8 -> 569310 | F7: 1 | G7: Capiteaux des associés | H7: رؤوس أموال الشركاء | I7: ='Nv capital'!H4 -> 23790375
B8: Matériel Roulant | C8: معدات النقل | D8: 2000000
B9: Materiels & équipements | C9: التجهيزات | D9: ='invest AtB3'!E2 -> 1516230
B10: Materiels & équipements | C10: التجهيزات
A11: =D11/D29 -> 0.49605194 | B11: Stocks / المخزونات | D11: =SUM(D12:D14) -> 39684270 | F11: =I11/I29 -> 0.45281919 | G11: Dettes / الديون | I11: =SUM(I12:I19) -> 36225640
A12: 3 | B12: Stocks Marchandises OR | C12: مخزون السلع | D12: ='stocks or'!I1 -> 36489863 | F12: 4 | G12: Dettes Fournisseurs | H12: ديون الموردين | I12: =Frs!J2 -> 2441869.1
B13: Stocks Marchandises AGR | D13: ='stoks arg'!G1 -> 3044406.9
B14: Stocks Marchandises P/O | D14: ='stok PO'!G1 -> 150000 | G14: Dettes Fournisseurs Casse | H14: ديون الموردين | I14: =Frs!G2 -> 11721510
A15: =D15/D29 -> 0.43948696 | B15: Créances / الحقوق | D15: =SUM(D16:D24) -> 35159059 | G15: Avances clients (versements) | H15: تسبيقات الزبائن | I15: =client!J1 -> 16543749
A16: 4 | B16: Créances Clients | C16: مستحقات لدى الزبائن | D16: =client!I1 -> 5829108 | G16: Avances clients Casse | H16: تسبيقات الزبائن | I16: =client!G1 -> 5106570
B17: Créances Clients Casse | C17: مستحقات لدى الزبائن | D17: =client!F1 -> 9715 | G17: Dettes Personnel | I17: =personnel!I4 -> 411941.5
B18: Avances fournisseurs | C18: تسبيقات للموردين | D18: =Frs!I2 -> 267528.62 | G18: Dettes Inpot Tripinal Berriane
B19: Avances fournisseurs Casse 18 | C19: تسبيقات للموردين | D19: =Frs!F2 -> 1271360
B20: Avances fournisseurs Casse 21 | C20: تسبيقات للموردين | D20: =Frs!E4 -> 964260
B21: Avances associers | C21: تسبيقات للشركاء | D21: ='Avances asso'!C4 -> 20808199 | F21: 1 | G21: Résultat avant déduction des primes | I21: =D6+D11+D15+D25-I6-I11 -> 19984216
B22: Prêt salariés | C22: سلف للعمال | D22: =personnel!H4 -> 43869 | G22: Prime des salaries | H22: منح الموظفين
B23: at b1 | C23: الفائدة | D23: 2630971.2 | G23: ELMACHRI3 ELKHIRIA | H23: المشاريع الخيرية
B24: at b2 | C24: الفائدة | D24: 3334048.2 | G24: Résultat net de l'exercice / النتيجة الصافية للدورة | I24: =I21-SUM(I22:I23) -> 19984216
A25: =D25/D29 -> 0.01339199 | B25: Disponibilités / السيولة | D25: =SUM(D26:D28) -> 1071362.3 | G25: Rentabilité du projet | H25: مردودية المشروع | I25: =I24/I6 -> 0.84001266
A26: 5 | B26: Trésorie | C26: الخزينة | D26: =170000+450000+155910 -> 775910
B27: Compte courant Banque BDL | C27: الحساب الجاري البنكي | D27: =4506.21+10946.07 -> 15452.28
B28: Devise-euro | C28: =370+300+450 -> 1120 | D28: =C28*250 -> 280000
B29: Total Actif | D29: =D6+D11+D15+D25 -> 80000231 | F29: Total Passif | I29: =I11+I6+I21 -> 80000231
B30: 111

Sheet Repartition globale
B6: رأس مال الشركة | D6: =' Bilan cloture'!I6 -> 23790375 | G6: B2 | H6: B1 | I6: المجموع
B7: النتيجة الدورة الصافية | D7: =' Bilan cloture'!I24 -> 19984216 | F7: رأس مال الشركة | G7: ='Nv capital'!H5 -> 9780625.7 | H7: ='Nv capital'!H6 -> 3334048.2 | I7: =D6+G7+H7 -> 36905049 | L7: =F11/D11 -> 0.43452994
B8: نصيب الشركاء بالجهد | C8: 0.5 | D8: =D$7*$C$8 -> 9992108.1 | F8: نصيب الشركاء بالمال | G8: ='[7]Repartition globale'!$E$13 -> 517342.62 | H8: ='[8]Repartition globale'!$D$8 -> 498830.08 | I8: =D9+G8+H8 -> 11008281
B9: نصيب الشركاء بالمال | C9: =100%-C8 -> 0.5 | D9: =D$7*$C$9 -> 9992108.1
A11: المجموع | C11: =SUM(C13:C61) -> 36905049 | D11: =SUM(D13:D19) -> 22995212 | E11: =SUM(E13:E19) -> 1 | F11: =SUM(F13:F19) -> 9992108.1 | G11: =SUM(G13:G19) -> 1 | H11: =SUM(H13:H19) -> 9992108.1 | I11: =SUM(I13:I19) -> 20088199 | J11: =SUM(J13:J19) -> 22891230 | K11: =SUM(K13:K19) -> 740505.93 | ... M11: =SUM(M13:M19) -> 1
A12: رقم | B12: الشركاء | C12: رأس المال الافتتاحي | D12: رأس المال النسبي | E12: نسب تقسيم رؤوس الأموال | F12: الأرباح مقابل المال | G12: نسب تقسيم أرباح الجهد | H12: الأرباح مقابل الجهد | I12: مقدم أرباح الشركاء | J12: المجموع | K12: زكاة السنة التجارية 2,58% | L12: رأس المال الجديد | M12: نسب رؤوس الأموال
A13: 1 | B13: ='Nv capital'!B11 -> الواهج عمر بن يحي | C13: ='Nv capital'!H11 -> 0 | D13: ='Nv capital'!I11 -> 0 | E13: =D13/$D$11 -> 0 | F13: =$D$9*E13 -> 0 | G13: 1 | H13: =$D$8*G13 -> 9992108.1 | I13: ='Avances asso'!C6 -> 19888199 | J13: =C13+F13+H13-I13 -> -9896090.5 | M13: =L13/$L$11 -> 0
A14: 2 | B14: ='Nv capital'!B12 -> بن عزوز مبخوتة | C14: ='Nv capital'!H12 -> 10000000 | D14: ='Nv capital'!I12 -> 10000000 | E14: =D14/$D$11 -> 0.43487313 | F14: =$D$9*E14 -> 4345299.4 | G14: 0 | H14: =$D$8*G14 -> 0 | I14: ='Avances asso'!C9 -> 0 | J14: =C14+F14+H14-I14 -> 14345299 | K14: =($J14-($E14*' Bilan cloture'!$D$6))*2.58% -> 324270.08 | L14: =J14 -> 14345299 | M14: =L14/$L$11 -> 0.43752583
A15: 3 | B15: ='Nv capital'!B13 -> كروشي الحاج بابهون | C15: ='Nv capital'!H13 -> 10167921 | D15: ='Nv capital'!I13 -> 10167921 | E15: =D15/$D$11 -> 0.44217558 | F15: =$D$9*E15 -> 4418266.2 | G15: 0 | H15: =$D$8*G15 -> 0 | I15: ='Avances asso'!C8 -> 0 | J15: =C15+F15+H15-I15 -> 14586187 | K15: =($J15-($E15*' Bilan cloture'!$D$6))*2.58% -> 329715.26 | L15: =J15 -> 14586187 | M15: =L15/$L$11 -> 0.44487281
A16: 4 | B16: ='Nv capital'!B14 -> بوسربة ياسمينة | C16: ='Nv capital'!H14 -> 607993.9 | D16: ='Nv capital'!I14 -> 607993.9 | E16: =D16/$D$11 -> 0.026440021 | F16: =$D$9*E16 -> 264191.55 | G16: 0 | H16: =$D$8*G16 -> 0 | I16: ='Avances asso'!C9 -> 0 | J16: =C16+F16+H16-I16 -> 872185.45 | K16: =($J16-($E16*' Bilan cloture'!$D$6))*2.58% -> 19715.423 | L16: =J16 -> 872185.45 | M16: =L16/$L$11 -> 0.026601303
A17: 5 | B17: ='Nv capital'!B15 -> بعوشي رسثم | C17: ='Nv capital'!C15 -> 1000000 | D17: ='Nv capital'!I15 -> 1000000 | E17: =D17/$D$11 -> 0.043487313 | F17: =$D$9*E17 -> 434529.94 | G17: 0 | H17: =$D$8*G17 -> 0 | I17: ='Avances asso'!C10 -> 200000 | J17: =C17+F17+H17-I17 -> 1234529.9 | K17: =($J17-($E17*' Bilan cloture'!$D$6))*2.58% -> 27267.008 | L17: =J17 -> 1234529.9 | M17: =L17/$L$11 -> 0.037652664
A18: 6 | B18: ='Nv capital'!B16 -> بوسريح نعيمة | C18: ='Nv capital'!C16 -> 500000 | D18: ='Nv capital'!I16 -> 500000 | E18: =D18/$D$11 -> 0.021743657 | F18: =$D$9*E18 -> 217264.97 | G18: 0 | H18: =$D$8*G18 -> 0 | I18: ='Avances asso'!C11 -> 0 | J18: =C18+F18+H18-I18 -> 717264.97 | K18: =($J18-($E18*' Bilan cloture'!$D$6))*2.58% -> 16213.504 | L18: =J18 -> 717264.97 | M18: =L18/$L$11 -> 0.021876291
A19: 7 | B19: ='Nv capital'!B17 -> بكاير حرمية بنت محمد | C19: ='Nv capital'!C17 -> 719297.09 | D19: ='Nv capital'!I17 -> 719297.09 | E19: =D19/$D$11 -> 0.031280298 | F19: =$D$9*E19 -> 312556.12 | G19: 0 | H19: =$D$8*G19 -> 0 | I19: ='Avances asso'!C12 -> 0 | J19: =C19+F19+H19-I19 -> 1031853.2 | K19: =($J19-($E19*' Bilan cloture'!$D$6))*2.58% -> 23324.653 | L19: =J19 -> 1031853.2 | M19: =L19/$L$11 -> 0.031471105
A20: 8 | B20: بكاير رابح بن محمد | C20: ='Nv capital'!C18 -> 2183503.5 | D20: ='Nv capital'!I18 -> 2183503.5 | E20: =D20/$D$11 -> 0.094954703 | F20: =$D$9*E20 -> 948797.65 | G20: 0 | H20: =$D$8*G20 -> 0 | I20: ='Avances asso'!C13 -> 0 | J20: =C20+F20+H20-I20 -> 3132301.2 | K20: =($J20-($E20*' Bilan cloture'!$D$6))*2.58% -> 70804.487 | L20: =J20 -> 3132301.2 | M20: =L20/$L$11 -> 0.095533919
A21: 9 | B21: ='Nv capital'!B19 -> لعساكر عبد الحميد | C21: ='Nv capital'!C19 -> 1375264 | D21: ='Nv capital'!I19 -> 1375264 | E21: =D21/$D$11 -> 0.059806536 | F21: =$D$9*E21 -> 597593.38 | G21: 0 | H21: =$D$8*G21 -> 0 | I21: ='Avances asso'!C14 -> 70000 | J21: =C21+F21+H21-I21 -> 1902857.4 | K21: =($J21-($E21*' Bilan cloture'!$D$6))*2.58% -> 42789.697 | L21: =J21 -> 1902857.4 | M21: =L21/$L$11 -> 0.05803638
A22: 10 | B22: ='Nv capital'!B20 -> الواهج احمد | C22: ='Nv capital'!C20 -> 708995.97 | D22: ='Nv capital'!I20 -> 708995.97 | E22: =D22/$D$11 -> 0.03083233 | F22: =$D$9*E22 -> 308079.98 | G22: 0 | H22: =$D$8*G22 -> 0 | I22: ='Avances asso'!C15 -> 0 | J22: =C22+F22+H22-I22 -> 1017075.9 | K22: =($J22-($E22*' Bilan cloture'!$D$6))*2.58% -> 22990.618 | L22: =J22 -> 1017075.9 | M22: =L22/$L$11 -> 0.031020405
A23: 11 | B23: ='Nv capital'!B21 -> مبروك مبروك طولقة | C23: ='Nv capital'!C21 -> 3000000 | D23: ='Nv capital'!I21 -> 3000000 | E23: =D23/$D$11 -> 0.13046194 | F23: =$D$9*E23 -> 1303589.8 | G23: 0 | H23: =$D$8*G23 -> 0 | I23: ='Avances asso'!C16 -> 0 | J23: =C23+F23+H23-I23 -> 4303589.8 | K23: =($J23-($E23*' Bilan cloture'!$D$6))*2.58% -> 97281.024 | L23: =J23 -> 4303589.8 | M23: =L23/$L$11 -> 0.13125775
A24: 12 | B24: ='Nv capital'!B22 -> بن يامي فؤاد بن علي | C24: ='Nv capital'!C22 -> 340739.85 | D24: ='Nv capital'!I22 -> 340739.85 | E24: =D24/$D$11 -> 0.014817861 | F24: =$D$9*E24 -> 148061.67 | G24: 0 | H24: =$D$8*G24 -> 0 | I24: ='Avances asso'!C17 -> 0 | J24: =C24+F24+H24-I24 -> 488801.52 | K24: =($J24-($E24*' Bilan cloture'!$D$6))*2.58% -> 11049.174 | L24: =J24 -> 488801.52 | M24: =L24/$L$11 -> 0.014908248
A25: 13 | B25: ='Nv capital'!B23 -> الواهج اسية | C25: ='Nv capital'!C23 -> 513448.84 | D25: ='Nv capital'!I23 -> 513448.84 | E25: =D25/$D$11 -> 0.022328511 | F25: =$D$9*E25 -> 223108.89 | G25: 0 | H25: =$D$8*G25 -> 0 | I25: ='Avances asso'!C18 -> 150000 | J25: =C25+F25+H25-I25 -> 586557.73 | K25: =($J25-($E25*' Bilan cloture'!$D$6))*2.58% -> 12779.61 | L25: =J25 -> 586557.73 | M25: =L25/$L$11 -> 0.017889773
A26: 14 | B26: ='Nv capital'!B24 -> صالح والحاج خوخة | C26: ='Nv capital'!C24 -> 72123.07 | D26: ='Nv capital'!I24 -> 72123.07 | E26: =D26/$D$11 -> 0.0031364386 | F26: =$D$9*E26 -> 31339.633 | G26: 0 | H26: =$D$8*G26 -> 0 | I26: ='Avances asso'!C19 -> 0 | J26: =C26+F26+H26-I26 -> 103462.7 | K26: =($J26-($E26*' Bilan cloture'!$D$6))*2.58% -> 2338.7354 | L26: =J26 -> 103462.7 | M26: =L26/$L$11 -> 0.0031555706
A27: 15 | B27: ='Nv capital'!B25 -> الواهج مامة | C27: ='Nv capital'!E25 -> 500000 | D27: ='Nv capital'!I25 -> 234693.88 | E27: =D27/$D$11 -> 0.010206206 | F27: =$D$9*E27 -> 101981.52 | G27: 0 | H27: =$D$8*G27 -> 0 | I27: ='Avances asso'!C20 -> 0 | J27: =C27+F27+H27-I27 -> 601981.52 | K27: =($J27-($E27*' Bilan cloture'!$D$6))*2.58% -> 14455.318 | L27: =J27 -> 601981.52 | M27: =L27/$L$11 -> 0.018360193
A28: 16 | B28: ='Nv capital'!B26 -> صالح والحاج فاطمة | C28: ='Nv capital'!C26 -> 22034.67 | D28: ='Nv capital'!I26 -> 22034.67 | E28: =D28/$D$11 -> 0.0009582286 | F28: =$D$9*E28 -> 9574.7238 | G28: 0 | H28: =$D$8*G28 -> 0 | I28: ='Avances asso'!C21 -> 0 | J28: =C28+F28+H28-I28 -> 31609.394 | K28: =($J28-($E28*' Bilan cloture'!$D$6))*2.58% -> 714.51842 | L28: =J28 -> 31609.394 | M28: =L28/$L$11 -> 0.00096407372
A29: 17 | B29: ='Nv capital'!B27 -> موسى المال سليمان | C29: ='Nv capital'!C27 -> 642035.45 | D29: ='Nv capital'!I27 -> 642035.45 | E29: =D29/$D$11 -> 0.027920397 | F29: =$D$9*E29 -> 278983.62 | G29: 0 | H29: =$D$8*G29 -> 0 | I29: ='Avances asso'!C22 -> 0 | J29: =C29+F29+H29-I29 -> 921019.07 | K29: =($J29-($E29*' Bilan cloture'!$D$6))*2.58% -> 20819.289 | L29: =J29 -> 921019.07 | M29: =L29/$L$11 -> 0.028090709
A30: 18 | B30: ='Nv capital'!B28 -> باسليمان محمد بن صالح | C30: ='Nv capital'!C28 -> 403492.59 | D30: ='Nv capital'!I28 -> 403492.59 | E30: =D30/$D$11 -> 0.017546809 | F30: =$D$9*E30 -> 175329.61 | G30: 0 | H30: =$D$8*G30 -> 0 | I30: ='Avances asso'!C23 -> 0 | J30: =C30+F30+H30-I30 -> 578822.2 | K30: =($J30-($E30*' Bilan cloture'!$D$6))*2.58% -> 13084.057 | L30: =J30 -> 578822.2 | M30: =L30/$L$11 -> 0.017653843
A31: 19 | B31: ='Nv capital'!B29 -> بن يامي اسلام بن حمزة | C31: ='Nv capital'!E29 -> 70000 | D31: ='Nv capital'!I29 -> 54761.905 | E31: =D31/$D$11 -> 0.0023814481 | F31: =$D$9*E31 -> 23795.687 | G31: 0 | H31: =$D$8*G31 -> 0 | I31: ='Avances asso'!C24 -> 0 | J31: =C31+F31+H31-I31 -> 93795.687 | K31: =($J31-($E31*' Bilan cloture'!$D$6))*2.58% -> 2168.9076 | L31: =J31 -> 93795.687 | M31: =L31/$L$11 -> 0.0028607305
A32: 20 | B32: ='Nv capital'!B30 -> بن يامي محمد بن حمزة | C32: ='Nv capital'!E30 -> 100000 | D32: ='Nv capital'!I30 -> 78231.293 | E32: =D32/$D$11 -> 0.0034020687 | F32: =$D$9*E32 -> 33993.839 | G32: 0 | H32: =$D$8*G32 -> 0 | I32: ='Avances asso'!C25 -> 0 | J32: =C32+F32+H32-I32 -> 133993.84 | K32: =($J32-($E32*' Bilan cloture'!$D$6))*2.58% -> 3098.4394 | L32: =J32 -> 133993.84 | M32: =L32/$L$11 -> 0.0040867579
A33: 21 | B33: ='Nv capital'!B31 -> خن لقمان | C33: ='Nv capital'!E31 -> 110310 | D33: ='Nv capital'!I31 -> 60282.789 | E33: =D33/$D$11 -> 0.0026215365 | F33: =$D$9*E33 -> 26194.677 | G33: 0 | H33: =$D$8*G33 -> 0 | I33: ='Avances asso'!C26 -> 0 | J33: =C33+F33+H33-I33 -> 136504.68 | K33: =($J33-($E33*' Bilan cloture'!$D$6))*2.58% -> 3245.4925 | L33: =J33 -> 136504.68 | M33: =L33/$L$11 -> 0.0041633374
A34: 22 | B34: ='Nv capital'!B32 -> مدرسة فسايل الامل | C34: ='Nv capital'!E32 -> 1200000 | D34: ='Nv capital'!I32 -> 927891.16 | E34: =D34/$D$11 -> 0.040351494 | F34: =$D$9*E34 -> 403196.49 | G34: 0 | H34: =$D$8*G34 -> 0 | I34: ='Avances asso'!C27 -> 0 | J34: =C34+F34+H34-I34 -> 1603196.5 | K34: =($J34-($E34*' Bilan cloture'!$D$6))*2.58% -> 37109.142 | L34: =J34 -> 1603196.5 | M34: =L34/$L$11 -> 0.048896844
A35: 23 | B35: ='Nv capital'!B33 -> الواهج فاطمة الزهراء | C35: ='Nv capital'!E33 -> 100000 | D35: ='Nv capital'!I33 -> 5668.9342 | E35: =D35/$D$11 -> 0.00024652672 | F35: =$D$9*E35 -> 2463.3216 | G35: 0 | H35: =$D$8*G35 -> 0 | I35: ='Avances asso'!C28 -> 0 | J35: =C35+F35+H35-I35 -> 102463.32 | K35: =($J35-($E35*' Bilan cloture'!$D$6))*2.58% -> 2617.5681 | L35: =J35 -> 102463.32 | M35: =L35/$L$11 -> 0.0031250898
A36: 24 | B36: ='Nv capital'!B34 -> الواهج لالة | C36: ='Nv capital'!E34 -> 180000 | D36: ='Nv capital'!I34 -> 94693.878 | E36: =D36/$D$11 -> 0.0041179823 | F36: =$D$9*E36 -> 41147.325 | G36: 0 | H36: =$D$8*G36 -> 0 | I36: ='Avances asso'!C29 -> 0 | J36: =C36+F36+H36-I36 -> 221147.32 | K36: =($J36-($E36*' Bilan cloture'!$D$6))*2.58% -> 5271.5371 | L36: =J36 -> 221147.32 | M36: =L36/$L$11 -> 0.0067449039
A37: 25 | B37: ='Nv capital'!B35 -> صالح والحاج ادريس بن سليمان | C37: ='Nv capital'!E35 -> 100000 | D37: ='Nv capital'!I35 -> 21768.707 | E37: =D37/$D$11 -> 0.00094666261 | F37: =$D$9*E37 -> 9459.1551 | G37: 0 | H37: =$D$8*G37 -> 0 | I37: ='Avances asso'!C30 -> 0 | J37: =C37+F37+H37-I37 -> 109459.16 | K37: =($J37-($E37*' Bilan cloture'!$D$6))*2.58% -> 2724.2614 | L37: =J37 -> 109459.16 | M37: =L37/$L$11 -> 0.0033384599
A38: 26 | B38: ='Nv capital'!B36 -> صالح والحاج سليمان بن عمر | C38: ='Nv capital'!E36 -> 100000 | D38: ='Nv capital'!I36 -> 90249.433 | E38: =D38/$D$11 -> 0.0039247054 | F38: =$D$9*E38 -> 39216.081 | G38: 0 | H38: =$D$8*G38 -> 0 | I38: ='Avances asso'!C31 -> 0 | J38: =C38+F38+H38-I38 -> 139216.08 | K38: =($J38-($E38*' Bilan cloture'!$D$6))*2.58% -> 3178.0837 | L38: =J38 -> 139216.08 | M38: =L38/$L$11 -> 0.0042460341
A39: 27 | B39: ='Nv capital'!B37 -> صالح والحاج سليمان ين عمر | C39: ='Nv capital'!E37 -> 500000 | D39: ='Nv capital'!I37 -> 157596.37 | E39: =D39/$D$11 -> 0.0068534428 | F39: =$D$9*E39 -> 68480.342 | G39: 0 | H39: =$D$8*G39 -> 0 | I39: ='Avances asso'!C32 -> 0 | J39: =C39+F39+H39-I39 -> 568480.34 | K39: =($J39-($E39*' Bilan cloture'!$D$6))*2.58% -> 13944.392 | L39: =J39 -> 568480.34 | M39: =L39/$L$11 -> 0.01733842
A40: 28 | B40: ='Nv capital'!B38 -> طالب باحمد نانة | C40: ='Nv capital'!E38 -> 40000 | D40: ='Nv capital'!I38 -> 21859.41 | E40: =D40/$D$11 -> 0.00095060703 | F40: =$D$9*E40 -> 9498.5683 | G40: 0 | H40: =$D$8*G40 -> 0 | I40: ='Avances asso'!C33 -> 0 | J40: =C40+F40+H40-I40 -> 49498.568 | K40: =($J40-($E40*' Bilan cloture'!$D$6))*2.58% -> 1176.8625 | L40: =J40 -> 49498.568 | M40: =L40/$L$11 -> 0.0015096863
A41: 29 | B41: ='Nv capital'!B39 -> النادي الرياضي فسائل الامل | C41: ='Nv capital'!E39 -> 100000 | D41: ='Nv capital'!I39 -> 73696.145 | E41: =D41/$D$11 -> 0.0032048474 | F41: =$D$9*E41 -> 32023.181 | G41: 0 | H41: =$D$8*G41 -> 0 | I41: ='Avances asso'!C34 -> 0 | J41: =C41+F41+H41-I41 -> 132023.18 | K41: =($J41-($E41*' Bilan cloture'!$D$6))*2.58% -> 3068.385 | L41: =J41 -> 132023.18 | M41: =L41/$L$11 -> 0.0040266536
A42: 30 | B42: ='Nv capital'!B40 -> الواهج عمر بن يحي بن حمو | C42: ='Nv capital'!C40 -> 1547888.9 | D42: ='Nv capital'!I40 -> 1547888.9 | E42: =D42/$D$11 -> 0.067313531 | F42: =$D$9*E42 -> 672604.08 | G42: 0 | H42: =$D$8*G42 -> 0 | I42: ='Avances asso'!C35 -> 0 | J42: =C42+F42+H42-I42 -> 2220493 | K42: =($J42-($E42*' Bilan cloture'!$D$6))*2.58% -> 50193.407 | L42: =J42 -> 2220493 | M42: =L42/$L$11 -> 0.067724138

Sheet Avances asso
A2: مقدم أرباح الشركاء لسنة 2020
A4: المجموع | C4: =SUM(C6:C104) -> 20808199
A5: رقم | B5: الشركاء | C5: مقدم أرباح الشركاء
A6: 1 | B6: ='Nv capital'!B11 -> الواهج عمر بن يحي | C6: =6179240.63+13708958 -> 19888199
A7: =IF(B6<>B7,A6+1,A6) -> 2 | B7: ='Nv capital'!B12 -> بن عزوز مبخوتة | C7: 500000
A8: =IF(B7<>B8,A7+1,A7) -> 3 | B8: ='Nv capital'!B13 -> كروشي الحاج بابهون | C8: 0
A9: 4 | B9: ='Nv capital'!B14 -> بوسربة ياسمينة | C9: 0
A10: 5 | B10: ='Nv capital'!B15 -> بعوشي رسثم | C10: 200000
A11: 6 | B11: ='Nv capital'!B16 -> بوسريح نعيمة
A12: 7 | B12: ='Nv capital'!B17 -> بكاير حرمية بنت محمد
A13: 8 | B13: ='Nv capital'!B18 -> بكاير رابح بن محمد
A14: 9 | B14: ='Nv capital'!B19 -> لعساكر عبد الحميد | C14: 70000
A15: 10 | B15: ='Nv capital'!B20 -> الواهج احمد
A16: 11 | B16: ='Nv capital'!B21 -> مبروك مبروك طولقة
A17: 12 | B17: ='Nv capital'!B22 -> بن يامي فؤاد بن علي
A18: 13 | B18: الواهج اسية | C18: 150000
A19: 14 | B19: صالح والحاج خوخة
A20: 15 | B20: صالح والحاج خوخة
A21: 16 | B21: صالح والحاج فاطمة
A22: 17 | B22: موسى المال سليمان
A23: 18 | B23: باسليمان محمد بن صالح

Sheet Fiche associé
D9: N°
B10: =LOOKUP($D$10,'Repartition globale'!$A$13:$A$44,'Repartition globale'!$B$13:$B$44) -> الواهج عمر بن يحي | C10: هذا بيان حساب السيد: | D10: 1
B11: في محل صياغة الفتح الى تاريخ 13 ربيع الثاني 1446 ه
A13: Capital investi: | B13: =SUMIF('Repartition globale'!$A$13:$A$46,'Fiche associé'!$D$10,'Repartition globale'!$C$13:$D$46) -> 0 | C13: رأس المال المستثمر:
A14: Capital parapport nbr jours ouvrés | B14: =SUMIF('Repartition globale'!$A$13:$A$46,'Fiche associé'!$D$10,'Repartition globale'!$D$13:$D$46) -> 0 | C14: رأس المال العامل بالنسبة لعدد الأيام:
A15: BENEFICE DU CAPITAL : | B15: =SUMIF('Repartition globale'!$A$13:$A$46,'Fiche associé'!$D$10,'Repartition globale'!$F$13:$F$46) -> 0 | C15: أرباح مقابل المال :
A16: Rentabilité des capiteaux: | B16: =B15/B14 -> #DIV/0! | C16: مردودية رأس المال:
A17: BENEFICE DE L'EFFORT: | B17: =SUMIF('Repartition globale'!$A$13:$A$46,'Fiche associé'!$D$10,'Repartition globale'!$H$13:$H$46) -> 9992108.1 | C17: أرباح مقابل الجهد :
A18: Avances associés: | B18: =SUMIF('Repartition globale'!$A$13:$A$46,'Fiche associé'!$D$10,'Repartition globale'!$I$13:$I$46) -> 19888199 | C18: مقدم الأرباح:
A19: TOTAL: | B19: =SUMIF('Repartition globale'!$A$13:$A$46,'Fiche associé'!$D$10,'Repartition globale'!$J$13:$J$46) -> -9896090.5 | C19: المجموع :
A20: ZAKAT: | B20: =SUMIF('Repartition globale'!$A$13:$A$46,'Fiche associé'!$D$10,'Repartition globale'!$K$13:$K$46) -> 0 | C20: زكاة السنة التجارية:
A21: NOUVEAU CAPITAL : | B21: =SUMIF('Repartition globale'!$A$13:$A$46,'Fiche associé'!$D$10,'Repartition globale'!$L$13:$L$46) -> 0 | C21: رأس المال الجديد :

Sheet  Bilan départ
A1: ="الميزانية الافتتاحية لمؤسسة "&Données!B1&" في "&DAY(Données!$B$6+1)&"/"&MONTH(Données!$B$6+1)&"/"&YEAR(Données!$B$6+1) -> الميزانية الافتتاحية لمؤسسة صياغة الفتح في 19/10/2024
A3: Actif / الأصول | F3: Passif / الخصوم
A4: Code | B4: Libéllé de l'Opération | D4: Montant | F4: Code | G4: Libéllé de l'Opération | I4: Montant
A5: Compta | F5: Compta
A6: =D6/D27 -> 0.06911239 | B6: Investissement / الاستثمارات | D6: =SUM(D7:D10) -> 4085540 | F6: =I6/I27 -> 0.33993723 | G6: Fonds Propres / رؤوس الأموال | I6: =SUM(I7:I10) -> 18656474
A7: 2 | B7: =IF(' Bilan cloture'!B7="","",' Bilan cloture'!B7) -> Materiels & équipements | C7: =IF(' Bilan cloture'!C7="","",' Bilan cloture'!C7) -> التجهيزات | D7: =' Bilan cloture'!D7 -> 569310 | F7: 1 | G7: =IF(' Bilan cloture'!G7="","",' Bilan cloture'!G7) -> Capiteaux des associés | H7: =IF(' Bilan cloture'!H7="","",' Bilan cloture'!H7) -> رؤوس أموال الشركاء | I7: ='Repartition globale'!L11-SUM('Repartition globale'!G7:H8) -> 18656474
B8: =IF(' Bilan cloture'!B8="","",' Bilan cloture'!B8) -> Matériel Roulant | C8: =IF(' Bilan cloture'!C8="","",' Bilan cloture'!C8) -> معدات النقل | D8: =' Bilan cloture'!D8 -> 2000000 | G8: =IF(' Bilan cloture'!G8="","",' Bilan cloture'!G8) | H8: =IF(' Bilan cloture'!H8="","",' Bilan cloture'!H8)
B9: =IF(' Bilan cloture'!B9="","",' Bilan cloture'!B9) -> Materiels & équipements | C9: =IF(' Bilan cloture'!C9="","",' Bilan cloture'!C9) -> التجهيزات | D9: =' Bilan cloture'!D9 -> 1516230 | G9: =IF(' Bilan cloture'!G9="","",' Bilan cloture'!G9) | H9: =IF(' Bilan cloture'!H9="","",' Bilan cloture'!H9)
B10: =IF(' Bilan cloture'!B10="","",' Bilan cloture'!B10) -> Materiels & équipements | C10: =IF(' Bilan cloture'!C10="","",' Bilan cloture'!C10) -> التجهيزات | D10: =' Bilan cloture'!D10 -> 0 | G10: =IF(' Bilan cloture'!G10="","",' Bilan cloture'!G10) | H10: =IF(' Bilan cloture'!H10="","",' Bilan cloture'!H10)
A11: =D11/D27 -> 0.61981244 | B11: Stocks / المخزونات | D11: =SUM(D12:D13) -> 36639863 | F11: =I11/I27 -> 0.66006277 | G11: Dettes / الديون | I11: =SUM(I12:I18) -> 36225640
A12: 3 | B12: =IF(' Bilan cloture'!B12="","",' Bilan cloture'!B12) -> Stocks Marchandises OR | C12: =IF(' Bilan cloture'!C12="","",' Bilan cloture'!C12) -> مخزون السلع | D12: =' Bilan cloture'!D12 -> 36489863 | F12: 4 | G12: =IF(' Bilan cloture'!G12="","",' Bilan cloture'!G12) -> Dettes Fournisseurs | H12: =IF(' Bilan cloture'!H12="","",' Bilan cloture'!H12) -> ديون الموردين | I12: =' Bilan cloture'!I12 -> 2441869.1
B13: =IF(' Bilan cloture'!B14="","",' Bilan cloture'!B14) -> Stocks Marchandises P/O | C13: =IF(' Bilan cloture'!C14="","",' Bilan cloture'!C14) | D13: =' Bilan cloture'!D14 -> 150000 | G13: =IF(' Bilan cloture'!G14="","",' Bilan cloture'!G14) -> Dettes Fournisseurs Casse | H13: =IF(' Bilan cloture'!H14="","",' Bilan cloture'!H14) -> ديون الموردين | I13: =' Bilan cloture'!I14 -> 11721510
A14: =D14/D27 -> 0.29295164 | B14: Créances / الحقوق | D14: =SUM(D15:D22) -> 17317671 | G14: =IF(' Bilan cloture'!G15="","",' Bilan cloture'!G15) -> Avances clients (versements) | H14: =IF(' Bilan cloture'!H15="","",' Bilan cloture'!H15) -> تسبيقات الزبائن | I14: =' Bilan cloture'!I15 -> 16543749
A15: 4 | B15: =IF(' Bilan cloture'!B16="","",' Bilan cloture'!B16) -> Créances Clients | C15: =IF(' Bilan cloture'!C16="","",' Bilan cloture'!C16) -> مستحقات لدى الزبائن | D15: =' Bilan cloture'!D16 -> 5829108 | G15: =IF(' Bilan cloture'!G16="","",' Bilan cloture'!G16) -> Avances clients Casse | H15: =IF(' Bilan cloture'!H16="","",' Bilan cloture'!H16) -> تسبيقات الزبائن | I15: =' Bilan cloture'!I16 -> 5106570
B16: =IF(' Bilan cloture'!B17="","",' Bilan cloture'!B17) -> Créances Clients Casse | C16: =IF(' Bilan cloture'!C17="","",' Bilan cloture'!C17) -> مستحقات لدى الزبائن | D16: =' Bilan cloture'!D17 -> 9715 | G16: =IF(' Bilan cloture'!G17="","",' Bilan cloture'!G17) -> Dettes Personnel | H16: =IF(' Bilan cloture'!H17="","",' Bilan cloture'!H17) | I16: =' Bilan cloture'!I17 -> 411941.5
B17: =IF(' Bilan cloture'!B18="","",' Bilan cloture'!B18) -> Avances fournisseurs | C17: =IF(' Bilan cloture'!C18="","",' Bilan cloture'!C18) -> تسبيقات للموردين | D17: =' Bilan cloture'!D18 -> 267528.62 | G17: =IF(' Bilan cloture'!G18="","",' Bilan cloture'!G18) -> Dettes Inpot Tripinal Berriane | H17: =IF(' Bilan cloture'!H18="","",' Bilan cloture'!H18) | I17: =' Bilan cloture'!I18 -> 0
B18: =IF(' Bilan cloture'!B19="","",' Bilan cloture'!B19) -> Avances fournisseurs Casse 18 | C18: =IF(' Bilan cloture'!C19="","",' Bilan cloture'!C19) -> تسبيقات للموردين | D18: =' Bilan cloture'!D19 -> 1271360 | G18: =IF(' Bilan cloture'!G19="","",' Bilan cloture'!G19) | H18: =IF(' Bilan cloture'!H19="","",' Bilan cloture'!H19) | I18: =' Bilan cloture'!I19 -> 0
B19: =IF(' Bilan cloture'!B21="","",' Bilan cloture'!B21) -> Avances associers | C19: =IF(' Bilan cloture'!C21="","",' Bilan cloture'!C21) -> تسبيقات للشركاء
B20: =IF(' Bilan cloture'!B22="","",' Bilan cloture'!B22) -> Prêt salariés | C20: =IF(' Bilan cloture'!C22="","",' Bilan cloture'!C22) -> سلف للعمال | D20: =' Bilan cloture'!D22 -> 43869
B21: Avance associé Omar Louhedj 2016 | D21: =-'Repartition globale'!J13 -> 9896090.5
A23: =D23/D27 -> 0.01812353 | B23: Disponibilités / السيولة | D23: =SUM(D24:D26) -> 1071362.3
A24: 5 | B24: =IF(' Bilan cloture'!B26="","",' Bilan cloture'!B26) -> Trésorie | C24: =IF(' Bilan cloture'!C26="","",' Bilan cloture'!C26) -> الخزينة | D24: =' Bilan cloture'!D26 -> 775910
B25: =IF(' Bilan cloture'!B27="","",' Bilan cloture'!B27) -> Compte courant Banque BDL | C25: =IF(' Bilan cloture'!C27="","",' Bilan cloture'!C27) -> الحساب الجاري البنكي | D25: =' Bilan cloture'!D27 -> 15452.28
B26: =IF(' Bilan cloture'!B28="","",' Bilan cloture'!B28) -> Devise-euro | C26: =IF(' Bilan cloture'!C28="","",' Bilan cloture'!C28) -> 1120 | D26: =' Bilan cloture'!D28 -> 280000
B27: Total Actif | D27: =D6+D11+D14+D23 -> 59114437 | F27: Total Passif | I27: =I11+I6 -> 54882113 | J27: =D27-I27 -> 4232323.2

Sheet stoks arg
G1: =SUM(G5:G38167) -> 3044406.9
D3: =SUBTOTAL(9,D5:D160) -> 12910.36 | G3: =SUBTOTAL(9,G5:G153) -> 3044406.9
A4: N° | B4: articles | C4: Ref | D4: poid | E4: Quant | F4: prix U | G4: somme
A5: 1 | B5: argent mar.925 | D5: =10+130+107.9+88.5+151.6+30+595.49+2.59+347.15+513.47+280.43+386.7+358.99+561.64+348.8+407.45+195.13+250.19+213.98+287.86 -> 5267.87 | F5: 350 | G5: =D5*F5 -> 1843754.5
A6: 1 | B6: argent mar.500 | D6: =105.26+22.62+54.09+7.3+15.6+40.13+54+218.07+56+40+99+120+85+512.58+299.36+225.15+8+134.78+393.3+79.3+60+49.46+34.77+192.75+354+628.1 -> 3888.62 | F6: 220 | G6: =D6*F6 -> 855496.4
A7: 1 | B7: argent casse.500 | D7: =156.71+95+109.14+230.7+23.1+26.32+2.97+14.26+543.9+566.48+381.2+477+85.65+80.92+118.5 -> 2911.85 | F7: 100 | G7: =D7*F7 -> 291185
A8: 1 | B8: argent casse.250 | D8: 782.67 | F8: 50 | G8: =D8*F8 -> 39133.5
A9: 2 | B9: argent casse.999 | D9: =27.35+32 -> 59.35 | F9: 250 | G9: =D9*F9 -> 14837.5
A10: 2 | G10: =E10*F10 -> 0
A11: 3 | G11: =E11*F11 -> 0
A12: 3 | G12: =E12*F12 -> 0
A13: 4 | G13: =E13*F13 -> 0
A14: 5 | G14: =E14*F14 -> 0
A15: 6 | G15: =E15*F15 -> 0
A16: 7 | G16: =E16*F16 -> 0
A17: 8 | G17: =E17*F17 -> 0
A18: 9 | G18: =E18*F18 -> 0
A19: 10 | G19: =E19*F19 -> 0
A20: 11 | G20: =E20*F20 -> 0
A21: 12 | G21: =E21*F21 -> 0
... A34: 20 | G34: =E34*F34 -> 0
A35: 21
A36: 22
A37: 23
A38: 24
A39: 25
A40: 26
A41: 27
A42: 28
A43: 29
A44: 29

Sheet stok PO
G1: =SUM(G5:G38166) -> 150000
D3: =SUBTOTAL(9,D5:D159) -> 0 | G3: =SUBTOTAL(9,G5:G152) -> 150000
A4: N° | B4: articles | C4: Ref | D4: poid | E4: Quant | F4: prix U | G4: somme
A5: 1 | B5: Parure | G5: =E5*F5 -> 0
A6: 1 | B6: perles | C6: djouher | G6: =E6*F6 -> 0
A7: 1 | B7: perles | C7: zazaghe | G7: =E7*F7 -> 0
A8: 1 | B8: perles | C8: colier harme | G8: =E8*F8 -> 0
A9: 2 | B9: perles | C9: coraille | G9: =E9*F9 -> 0
A10: 2 | B10: embalage | C10: lux
A11: 3 | B11: Plaqué or | C11: Divers | G11: 150000
A12: 3
A13: 4
A14: 5
A15: 6
A16: 7
A17: 8
A18: 9
A19: 10
A20: 11
A21: 12
A22: 13
A23: 14
... A43: 29

Sheet stocks or
I1: =SUM(I5:I38156) -> 36489863
C3: =SUBTOTAL(9,C5:C148) -> 1995.69 | D3: =SUBTOTAL(9,D5:D148) -> 267.88 | I3: =SUBTOTAL(9,I5:I142) -> 36489863
A4: N° | B4: articles | C4: poid(g)or | D4: poid(g)or | E4: Ref | F4: Quant | G4: prix casse | H4: prix façon | I4: somme
A5: 1 | B5: balieure et recube MAG | D5: 75 | G5: 14500 | I5: =D5*G5 -> 1087500
A6: 2 | B6: casse18 | I6: =D6*G6 -> 0
A7: 3 | B7: casse18 | D7: =5.02+28.56+69+1.31+5.63+3.5+1.82+4.08+5.08+6.19+5.24 -> 135.43 | G7: 14500 | I7: =D7*G7 -> 1963735
A8: 4 | B8: casse21 | D8: =0.53+3.84+21.78 -> 26.15 | G8: 16500 | I8: =D8*G8 -> 431475
A9: 5 | B9: or 750 | C9: =4.57+2.85+2.94+3.18+2.58+2.47+1.23+42.72+2.3+1.82+1.8+34.37+45.02 -> 147.85 | E9: itali | G9: 15000 | H9: 3000 | I9: =C9*(G9+H9) -> 2661300
A10: 5 | B10: or 750 | C10: =31.03+27.27+20.29+29.53+10.63+3.28+8.11+10.65+3.95+6.79+9.77+9.43+3.83+8.18+2.14+40.83+72.9+25.52 -> 324.13 | E10: itali | G10: 15000 | H10: 3500 | I10: =C10*(G10+H10) -> 5996405
A11: 6 | B11: or 750 | C11: =31.59+16.09 -> 47.68 | E11: local PS | G11: 15000 | H11: 1500 | I11: =C11*(G11+H11) -> 786720
A12: 7 | B12: or 750 | C12: =19.03+11.03 -> 30.06 | E12: local SPS | G12: 15000 | H12: 1150 | I12: =C12*(G12+H12) -> 485469
A13: 8 | B13: or articles | C13: =1.24+2.15+1.32+3.41+1.41+12.33+3.09+2.06+3.43+2.56+1.25+2.93+2.28+1.54+2.15+14.28+2.3+4.58+7.35+7.56+53.43+17.67+21.82+2.12+8.03+8.84+12.16+2.25+7.8+11.7+8+3.39+6.16+38.04+24.79+47.56+12.22+30.4+53.78+56.87+53.61+30.05+26.32+15.79+21.49+20.35+14.32+4.92+14.16+75.14+48.7+21.36+5.58+39.02 -> 897.06 | E13: SP | G13: 14500 | H13: 1200 | I13: =C13*(G13+H13) -> 14083842
A14: 9 | B14: or articles | C14: =16.05+30+30+17.13+30.18 -> 123.36 | E14: mesaise | G14: 14500 | H14: 650 | I14: =C14*(G14+H14) -> 1868904
A15: 10 | B15: or articles | C15: =22.14+30+30.14+11.12 -> 93.4 | E15: mesaise | G15: 14500 | H15: 750 | I15: =C15*(G15+H15) -> 1424350
B16: or articles | C16: 60.09 | E16: mesaise local PS | G16: 15300 | H16: 750 | I16: =C16*(G16+H16) -> 964444.5
B17: or articles | C17: 20 | E17: mesaise local PS | G17: 15300 | H17: 850 | I17: =C17*(G17+H17) -> 323000
A18: 11 | B18: or articles | C18: =1.4+5.35+2.24+2.62+3.83+0.85+3.47+22.94+1.32+4.83+5.69+4.23+2.4+12.9 -> 74.07 | E18: AVP | G18: 14500 | H18: 800 | I18: =C18*(G18+H18) -> 1133271
A19: 12 | B19: or articles | E19: PL | I19: =(G19+H19)*D19 -> 0
A20: 13 | B20: or articles | C20: =2+4+3+27.77+32.87+3.96 -> 73.6 | E20: louice | G20: 14500 | H20: 500 | I20: =C20*(G20+H20) -> 1104000
A21: 14 | B21: or articles | C21: 47.52 | E21: mesaise | G21: 14700 | H21: 680 | I21: =C21*(G21+H21) -> 730857.6
A22: 15 | B22: or fin | D22: 6.32 | G22: 18500 | I22: =D22*G22 -> 116920
A23: 16 | B23: or articles.21 | D23: =4.21+4.5+7.25+9.02 -> 24.98 | G23: 19000 | I23: =D23*G23 -> 474620
B24: or articles | C24: 56.87 | E24: bague solitaire | G24: 14500 | H24: 500 | I24: =C24*(G24+H24) -> 853050

Sheet client
B1: Prix casse 18 | C1: 14500 | F1: =SUM(F6:F359)*C1 -> 9715 | G1: =SUM(G6:G359)*C1+H3 -> 5106570 | I1: =SUM(I6:I359) -> 5829108 | J1: =SUM(J6:J359) -> 16543749
B2: Prix casse 21 | C2: 16500
E3: =E4*C2 -> 0 | F3: =F4*C1 -> 9715 | G3: =G4*C1 -> 4350870 | H3: =H4*C2 -> 755700 | I3: =SUBTOTAL(9,I6:I360) -> 5829108 | J3: =SUBTOTAL(9,J6:J360) -> 16543749
E4: =SUBTOTAL(9,E6:E361) -> 0 | F4: =SUBTOTAL(9,F6:F361) -> 0.67 | G4: =SUBTOTAL(9,G6:G361) -> 300.06 | H4: =SUBTOTAL(9,H6:H361) -> 45.8
A5: N° | B5: client | C5: téléphone | D5: adresse | E5: Creance casse21 | F5: Creance casse18 | G5: dette casse18 | H5: dette casse21 | I5: Creance | J5: dette
A6: 1 | B6: client divers | F6: 0.67 | G6: 300.06 | H6: 45.8
A7: 2 | B7: client divers | I7: 5441263 | J7: 16543749
A8: 3 | B8: client divers reparation | I8: 68845 | K8: 257.02
A9: 4 | B9: client divers dorure | I9: 19000
A10: 4 | B10: debouz hadj kacem | I10: 300000
A11: 5
A12: 6
A13: 7
A14: 8
A15: 9
A16: 10
A17: 11
A18: 13
A19: 14
A20: 15
A21: 16
A22: 17
... A189: 184

Sheet Frs
F2: =SUM(F7:F3205)*$C$3 -> 1271360 | G2: =G4+H4 -> 11721510 | I2: =SUM(I7:I312) -> 267528.62 | J2: =SUM(J7:J312) -> 2441869.1
B3: Prix casse 18 | C3: 14500
B4: Prix casse 21 | C4: 16500 | E4: =E5*C4 -> 964260 | F4: =F5*C3 -> 1271360 | G4: =G5*C3 -> 11721510 | H4: =H5*C4 -> 0 | I4: =SUBTOTAL(9,I6:I315) -> 267528.62 | J4: =SUBTOTAL(9,J6:J315) -> 2441869.1
E5: =SUBTOTAL(9,E7:E316) -> 58.44 | F5: =SUBTOTAL(9,F7:F316) -> 87.68 | G5: =SUBTOTAL(9,G7:G316) -> 808.38 | H5: =SUBTOTAL(9,H7:H316) -> 0
A6: N° | B6: fourniseure | C6: téléphone | D6: adresse | E6: Creance casse21 | F6: Creance casse18 | G6: dette casse18 | H6: dette casse21 | I6: Creance | J6: dette
A7: 1 | B7: At b1 yahia | E7: 14.52 | G7: 44.61 | J7: 684487.22
A8: 2 | B8: Ben abdellah bakir | F8: 9.12 | I8: 1957.34
A9: 3 | B9: At b2 Or | G9: 227.11 | J9: 288716
A10: 4 | B10: At b2 | J10: 1292728.6
A11: 5 | B11: babker abdelaziz/M2 | J11: 16900
A12: 6 | B12: Ben yami omar | G12: 68.39 | J12: 9190.5
A13: 7 | B13: Rachid batna | G13: 168.68 | J13: =3895.5+4000 -> 7895.5
A14: 8 | B14: Azghar moussa | G14: 62.71 | J14: 10721.9
A15: 9 | B15: Hamza 750 | G15: 117.07
A16: 10 | B16: Ghecham malik | G16: 64.7 | K16: 247.46
A17: 11 | B17: Hakim drisi | G17: 34.96 | I17: 57320
A18: 12 | B18: salah arg | J18: 120000
A19: 13 | B19: Khettara med | E19: 43.56 | F19: 77.04 | G19: 18.28 | J19: 11229.4
A20: 14 | B20: magasin elfeth ghardaia | I20: 122100
A21: 15 | B21: Khaled ben azouz | E21: 0.36 | I21: 528
A22: 16 | B22: babker abdelaziz | G22: 1.87 | I22: 64623.28
A23: 17 | B23: med djelfa | F23: 1.52 | I23: 21000

Sheet personnel
H4: =SUBTOTAL(9,H6:H29917) -> 43869 | I4: =SUBTOTAL(9,I6:I29917) -> 411941.5 | J4: =SUBTOTAL(9,J6:J29917) -> 0 | K4: =SUBTOTAL(9,K6:K29917) -> 0
A5: N° | B5: Bon | C5: date | D5: Non et prenom | E5: téléphone | F5: Réf | G5: désignation | H5: creance | I5: dette | J5: Entrée | K5: sortie
A6: 1 | D6: Moussalmal slimen | I6: 268241.5
A7: 6 | D7: Moussalmal yemma | I7: 143700
A8: 5 | D8: Louahedj ahmed | H8: 43869
A9: 8
A10: 9
A11: 10
A12: 11
A13: 12
A14: 13
A15: 14
A16: 15
A17: 16
A18: 17
A19: 18
A20: 19
A21: 20

Sheet Invest Mag
A1: Aménagement | S1: Aménagement | T1: =SUMIF($B$10:$B$1429,S1,$T$10:$T$14029) -> 65333.333 | AG1: Aménagement | AH1: =SUMIF($B$10:$B$1429,AG1,$AH$10:$AH$14029) -> 49333.333 | AU1: Aménagement | AV1: =SUMIF($B$10:$B$1429,AU1,$AV$10:$AV$14029) -> 52200 | BI1: Aménagement | BJ1: =SUMIF($B$10:$B$1429,BI1,$BJ$10:$BJ$14029) -> 32700 | BW1: Aménagement | BX1: =SUMIF($B$10:$B$1429,BW1,$BX$10:$BX$14029) -> 13200 | CK1: Aménagement | CL1: =SUMIF($B$10:$B$1429,CK1,$CL$10:$CL$14029) -> 9200 | CY1: Aménagement | CZ1: =SUMIF($B$10:$B$1429,CY1,$CZ$10:$CZ$14029) -> 4866.6667 | DM1: Aménagement | DN1: =SUMIF($B$10:$B$1429,DM1,$DN$10:$DN$14029) -> 4583.3333 | EA1: Aménagement | EB1: =SUMIF($B$10:$B$1429,EA1,$EB$10:$EB$14029) -> 4650
A2: Equipements | C2: Première année amortissement | E2: 41944 | S2: Equipements | T2: =SUMIF($B$10:$B$1429,S2,$T$10:$T$14029) -> 0 | AG2: Equipements | AH2: =SUMIF($B$10:$B$1429,AG2,$AH$10:$AH$14029) -> 0 | AU2: Equipements | AV2: =SUMIF($B$10:$B$1429,AU2,$AV$10:$AV$14029) -> 0 | BI2: Equipements | BJ2: =SUMIF($B$10:$B$1429,BI2,$BJ$10:$BJ$14029) -> 0 | BW2: Equipements | BX2: =SUMIF($B$10:$B$1429,BW2,$BX$10:$BX$14029) -> 0 | CK2: Equipements | CL2: =SUMIF($B$10:$B$1429,CK2,$CL$10:$CL$14029) -> 0 | CY2: Equipements | CZ2: =SUMIF($B$10:$B$1429,CY2,$CZ$10:$CZ$14029) -> 0 | DM2: Equipements | DN2: =SUMIF($B$10:$B$1429,DM2,$DN$10:$DN$14029) -> 0 | EA2: Equipements | EB2: =SUMIF($B$10:$B$1429,EA2,$EB$10:$EB$14029) -> 0
A3: Matériels | S3: Matériels | T3: =SUMIF($B$10:$B$1429,S3,$T$10:$T$14029) -> 0 | AG3: Matériels | AH3: =SUMIF($B$10:$B$1429,AG3,$AH$10:$AH$14029) -> 0 | AU3: Matériels | AV3: =SUMIF($B$10:$B$1429,AU3,$AV$10:$AV$14029) -> 41976.944 | BI3: Matériels | BJ3: =SUMIF($B$10:$B$1429,BI3,$BJ$10:$BJ$14029) -> 173996.94 | BW3: Matériels | BX3: =SUMIF($B$10:$B$1429,BW3,$BX$10:$BX$14029) -> 129973.61 | CK3: Matériels | CL3: =SUMIF($B$10:$B$1429,CK3,$CL$10:$CL$14029) -> 105973.61 | CY3: Matériels | CZ3: =SUMIF($B$10:$B$1429,CY3,$CZ$10:$CZ$14029) -> 54113.333 | DM3: Matériels | DN3: =SUMIF($B$10:$B$1429,DM3,$DN$10:$DN$14029) -> 50493.333 | EA3: Matériels | EB3: =SUMIF($B$10:$B$1429,EA3,$EB$10:$EB$14029) -> 57733.333
A4: Mobilier | S4: Mobilier | T4: =SUMIF($B$10:$B$1429,S4,$T$10:$T$14029) -> 0 | AG4: Mobilier | AH4: =SUMIF($B$10:$B$1429,AG4,$AH$10:$AH$14029) -> 0 | AU4: Mobilier | AV4: =SUMIF($B$10:$B$1429,AU4,$AV$10:$AV$14029) -> 0 | BI4: Mobilier | BJ4: =SUMIF($B$10:$B$1429,BI4,$BJ$10:$BJ$14029) -> 0 | BW4: Mobilier | BX4: =SUMIF($B$10:$B$1429,BW4,$BX$10:$BX$14029) -> 0 | CK4: Mobilier | CL4: =SUMIF($B$10:$B$1429,CK4,$CL$10:$CL$14029) -> 0 | CY4: Mobilier | CZ4: =SUMIF($B$10:$B$1429,CY4,$CZ$10:$CZ$14029) -> 0 | DM4: Mobilier | DN4: =SUMIF($B$10:$B$1429,DM4,$DN$10:$DN$14029) -> 0 | EA4: Mobilier | EB4: =SUMIF($B$10:$B$1429,EA4,$EB$10:$EB$14029) -> 0
A5: Résidence | S5: Résidence | T5: =SUMIF($B$10:$B$1429,S5,$T$10:$T$14029) -> 0 | AG5: Résidence | AH5: =SUMIF($B$10:$B$1429,AG5,$AH$10:$AH$14029) -> 0 | AU5: Résidence | AV5: =SUMIF($B$10:$B$1429,AU5,$AV$10:$AV$14029) -> 0 | BI5: Résidence | BJ5: =SUMIF($B$10:$B$1429,BI5,$BJ$10:$BJ$14029) -> 0 | BW5: Résidence | BX5: =SUMIF($B$10:$B$1429,BW5,$BX$10:$BX$14029) -> 0 | CK5: Résidence | CL5: =SUMIF($B$10:$B$1429,CK5,$CL$10:$CL$14029) -> 0 | CY5: Résidence | CZ5: =SUMIF($B$10:$B$1429,CY5,$CZ$10:$CZ$14029) -> 0 | DM5: Résidence | DN5: =SUMIF($B$10:$B$1429,DM5,$DN$10:$DN$14029) -> 0 | EA5: Résidence | EB5: =SUMIF($B$10:$B$1429,EA5,$EB$10:$EB$14029) -> 0
A6: Matériel Roulant | T6: =SUMIF($B$10:$B$1429,S6,$T$10:$T$14029) -> 0 | AH6: =SUMIF($B$10:$B$1429,AG6,$AH$10:$AH$14029) -> 0 | AV6: =SUMIF($B$10:$B$1429,AU6,$AV$10:$AV$14029) -> 0 | BJ6: =SUMIF($B$10:$B$1429,BI6,$BJ$10:$BJ$14029) -> 0 | BX6: =SUMIF($B$10:$B$1429,BW6,$BX$10:$BX$14029) -> 0 | CL6: =SUMIF($B$10:$B$1429,CK6,$CL$10:$CL$14029) -> 0 | CZ6: =SUMIF($B$10:$B$1429,CY6,$CZ$10:$CZ$14029) -> 0 | DN6: =SUMIF($B$10:$B$1429,DM6,$DN$10:$DN$14029) -> 0 | EB6: =SUMIF($B$10:$B$1429,EA6,$EB$10:$EB$14029) -> 0
D8: =SUBTOTAL(9,D10:D439) -> 569310 | G8: =SUBTOTAL(9,G10:G439) -> 0 | H8: =SUBTOTAL(9,H10:H439) -> 1333.3333 | I8: =SUBTOTAL(9,I10:I439) -> 1333.3333 | J8: =SUBTOTAL(9,J10:J439) -> 1333.3333 | K8: =SUBTOTAL(9,K10:K439) -> 1333.3333 | L8: =SUBTOTAL(9,L10:L439) -> 1333.3333 | M8: =SUBTOTAL(9,M10:M439) -> 1333.3333 | N8: =SUBTOTAL(9,N10:N439) -> 1333.3333 | ... EB8: =SUBTOTAL(9,EB10:EB439) -> 62383.333
A9: Date d'achat | B9: Classement | C9: Désignation | D9: Montant | E9: Durée | F9: Amortissement | G9: =EOMONTH($E$2,0) -> 41973 | H9: =EOMONTH(G9,1) -> 42004 | I9: =EOMONTH(H9,1) -> 42035 | J9: =EOMONTH(I9,1) -> 42063 | K9: =EOMONTH(J9,1) -> 42094 | L9: =EOMONTH(K9,1) -> 42124 | M9: =EOMONTH(L9,1) -> 42155 | N9: =EOMONTH(M9,1) -> 42185 | O9: =EOMONTH(N9,1) -> 42216 | ... R9: =EOMONTH(Q9,1) -> 42308 | S9: ="Amortissement"&" "&YEAR(E2)+1 -> Amortissement 2015 | T9: ="Valeur résiduelle"&" "&YEAR(E2)+1 -> Valeur résiduelle 2015 | U9: =EOMONTH(R9,1) -> 42338 | V9: =EOMONTH(U9,1) -> 42369 | W9: =EOMONTH(V9,1) -> 42400 | X9: =EOMONTH(W9,1) -> 42429 | Y9: =EOMONTH(X9,1) -> 42460 | Z9: =EOMONTH(Y9,1) -> 42490 | AA9: =EOMONTH(Z9,1) -> 42521 | AB9: =EOMONTH(AA9,1) -> 42551 | AC9: =EOMONTH(AB9,1) -> 42582 | ... AF9: =EOMONTH(AE9,1) -> 42674 | AG9: ="Amortissement"&" "&YEAR(E2)+2 -> Amortissement 2016 | AH9: ="Valeur résiduelle"&" "&YEAR(E2)+2 -> Valeur résiduelle 2016 | AI9: =EOMONTH(AF9,1) -> 42704 | AJ9: =EOMONTH(AI9,1) -> 42735 | AK9: =EOMONTH(AJ9,1) -> 42766 | AL9: =EOMONTH(AK9,1) -> 42794 | AM9: =EOMONTH(AL9,1) -> 42825 | AN9: =EOMONTH(AM9,1) -> 42855 | AO9: =EOMONTH(AN9,1) -> 42886 | AP9: =EOMONTH(AO9,1) -> 42916 | AQ9: =EOMONTH(AP9,1) -> 42947 | ... AT9: =EOMONTH(AS9,1) -> 43039 | AU9: ="Amortissement"&" "&YEAR(E2)+3 -> Amortissement 2017 | AV9: ="Valeur résiduelle"&" "&YEAR(E2)+3 -> Valeur résiduelle 2017 | AW9: =EOMONTH(AT9,1) -> 43069 | AX9: =EOMONTH(AW9,1) -> 43100 | AY9: =EOMONTH(AX9,1) -> 43131 | AZ9: =EOMONTH(AY9,1) -> 43159 | BA9: =EOMONTH(AZ9,1) -> 43190 | BB9: =EOMONTH(BA9,1) -> 43220 | BC9: =EOMONTH(BB9,1) -> 43251 | BD9: =EOMONTH(BC9,1) -> 43281 | BE9: =EOMONTH(BD9,1) -> 43312 | ... BH9: =EOMONTH(BG9,1) -> 43404 | BI9: ="Amortissement"&" "&YEAR(E2)+4 -> Amortissement 2018 | BJ9: ="Valeur résiduelle"&" "&YEAR(E2)+4 -> Valeur résiduelle 2018 | BK9: =EOMONTH(BH9,1) -> 43434 | BL9: =EOMONTH(BK9,1) -> 43465 | BM9: =EOMONTH(BL9,1) -> 43496 | BN9: =EOMONTH(BM9,1) -> 43524 | BO9: =EOMONTH(BN9,1) -> 43555 | BP9: =EOMONTH(BO9,1) -> 43585 | BQ9: =EOMONTH(BP9,1) -> 43616 | BR9: =EOMONTH(BQ9,1) -> 43646 | BS9: =EOMONTH(BR9,1) -> 43677 | ... BV9: =EOMONTH(BU9,1) -> 43769 | BW9: ="Amortissement"&" "&YEAR(E2)+5 -> Amortissement 2019 | BX9: ="Valeur résiduelle"&" "&YEAR(E2)+5 -> Valeur résiduelle 2019 | BY9: =EOMONTH(BV9,1) -> 43799 | BZ9: =EOMONTH(BY9,1) -> 43830 | CA9: =EOMONTH(BZ9,1) -> 43861 | CB9: =EOMONTH(CA9,1) -> 43890 | CC9: =EOMONTH(CB9,1) -> 43921 | CD9: =EOMONTH(CC9,1) -> 43951 | CE9: =EOMONTH(CD9,1) -> 43982 | CF9: =EOMONTH(CE9,1) -> 44012 | CG9: =EOMONTH(CF9,1) -> 44043 | ... CJ9: =EOMONTH(CI9,1) -> 44135 | CK9: ="Amortissement"&" "&YEAR(E2)+6 -> Amortissement 2020 | CL9: ="Valeur résiduelle"&" "&YEAR(E2)+6 -> Valeur résiduelle 2020 | CM9: =EOMONTH(CJ9,1) -> 44165 | CN9: =EOMONTH(CM9,1) -> 44196 | CO9: =EOMONTH(CN9,1) -> 44227 | CP9: =EOMONTH(CO9,1) -> 44255 | CQ9: =EOMONTH(CP9,1) -> 44286 | CR9: =EOMONTH(CQ9,1) -> 44316 | CS9: =EOMONTH(CR9,1) -> 44347 | CT9: =EOMONTH(CS9,1) -> 44377 | CU9: =EOMONTH(CT9,1) -> 44408 | ... CX9: =EOMONTH(CW9,1) -> 44500 | CY9: ="Amortissement"&" "&YEAR(E2)+7 -> Amortissement 2021 | CZ9: ="Valeur résiduelle"&" "&YEAR(E2)+7 -> Valeur résiduelle 2021 | DA9: =EOMONTH(CX9,1) -> 44530 | DB9: =EOMONTH(DA9,1) -> 44561 | DC9: =EOMONTH(DB9,1) -> 44592 | DD9: =EOMONTH(DC9,1) -> 44620 | DE9: =EOMONTH(DD9,1) -> 44651 | DF9: =EOMONTH(DE9,1) -> 44681 | DG9: =EOMONTH(DF9,1) -> 44712 | DH9: =EOMONTH(DG9,1) -> 44742 | DI9: =EOMONTH(DH9,1) -> 44773 | ... DL9: =EOMONTH(DK9,1) -> 44865 | DM9: ="Amortissement"&" "&YEAR(E2)+8 -> Amortissement 2022 | DN9: ="Valeur résiduelle"&" "&YEAR(E2)+8 -> Valeur résiduelle 2022 | DO9: =EOMONTH(DL9,1) -> 44895 | DP9: =EOMONTH(DO9,1) -> 44926 | DQ9: =EOMONTH(DP9,1) -> 44957 | DR9: =EOMONTH(DQ9,1) -> 44985 | DS9: =EOMONTH(DR9,1) -> 45016 | DT9: =EOMONTH(DS9,1) -> 45046 | DU9: =EOMONTH(DT9,1) -> 45077 | DV9: =EOMONTH(DU9,1) -> 45107 | DW9: =EOMONTH(DV9,1) -> 45138 | ... DZ9: =EOMONTH(DY9,1) -> 45230 | EA9: ="Amortissement"&" "&YEAR(E2)+9 -> Amortissement 2023 | EB9: ="Valeur résiduelle"&" "&YEAR(E2)+9 -> Valeur résiduelle 2023
A10: 41974 | B10: Aménagement | C10: Vitrine interieur magasin | D10: 80000 | E10: 5 | F10: =D10/E10 -> 16000 | G10: =IF(OR($F10<=0,(G$9-$A10)>(365*$E10)),0,IF($A10<=G$9,$F10/12,0)) -> 0 | H10: =IF(OR($F10<=0,(H$9-$A10)>(365*$E10)),0,IF($A10<=H$9,$F10/12,0)) -> 1333.3333 | I10: =IF(OR($F10<=0,(I$9-$A10)>(365*$E10)),0,IF($A10<=I$9,$F10/12,0)) -> 1333.3333 | J10: =IF(OR($F10<=0,(J$9-$A10)>(365*$E10)),0,IF($A10<=J$9,$F10/12,0)) -> 1333.3333 | K10: =IF(OR($F10<=0,(K$9-$A10)>(365*$E10)),0,IF($A10<=K$9,$F10/12,0)) -> 1333.3333 | L10: =IF(OR($F10<=0,(L$9-$A10)>(365*$E10)),0,IF($A10<=L$9,$F10/12,0)) -> 1333.3333 | M10: =IF(OR($F10<=0,(M$9-$A10)>(365*$E10)),0,IF($A10<=M$9,$F10/12,0)) -> 1333.3333 | N10: =IF(OR($F10<=0,(N$9-$A10)>(365*$E10)),0,IF($A10<=N$9,$F10/12,0)) -> 1333.3333 | ... R10: =IF(OR($F10<=0,(R$9-$A10)>(365*$E10)),0,IF($A10<=R$9,$F10/12,0)) -> 1333.3333 | S10: =SUM(G10:R10) -> 14666.667 | T10: =IF(AND($R$9>A10,$S10<>0),$D10-$S10,0) -> 65333.333 | U10: =IF(OR($F10<=0,(U$9-$A10)>(365*$E10)),0,IF($A10<=U$9,$F10/12,0)) -> 1333.3333 | V10: =IF(OR($F10<=0,(V$9-$A10)>(365*$E10)),0,IF($A10<=V$9,$F10/12,0)) -> 1333.3333 | W10: =IF(OR($F10<=0,(W$9-$A10)>(365*$E10)),0,IF($A10<=W$9,$F10/12,0)) -> 1333.3333 | X10: =IF(OR($F10<=0,(X$9-$A10)>(365*$E10)),0,IF($A10<=X$9,$F10/12,0)) -> 1333.3333 | Y10: =IF(OR($F10<=0,(Y$9-$A10)>(365*$E10)),0,IF($A10<=Y$9,$F10/12,0)) -> 1333.3333 | Z10: =IF(OR($F10<=0,(Z$9-$A10)>(365*$E10)),0,IF($A10<=Z$9,$F10/12,0)) -> 1333.3333 | AA10: =IF(OR($F10<=0,(AA$9-$A10)>(365*$E10)),0,IF($A10<=AA$9,$F10/12,0)) -> 1333.3333 | AB10: =IF(OR($F10<=0,(AB$9-$A10)>(365*$E10)),0,IF($A10<=AB$9,$F10/12,0)) -> 1333.3333 | ... AF10: =IF(OR($F10<=0,(AF$9-$A10)>(365*$E10)),0,IF($A10<=AF$9,$F10/12,0)) -> 1333.3333 | AG10: =SUM(U10:AF10) -> 16000 | AH10: =IF(AND($AF$9>$A10,$AG10<>0),$D10-$S10-$AG10,0) -> 49333.333 | AI10: =IF(OR($F10<=0,(AI$9-$A10)>(365*$E10)),0,IF($A10<=AI$9,$F10/12,0)) -> 1333.3333 | AJ10: =IF(OR($F10<=0,(AJ$9-$A10)>(365*$E10)),0,IF($A10<=AJ$9,$F10/12,0)) -> 1333.3333 | AK10: =IF(OR($F10<=0,(AK$9-$A10)>(365*$E10)),0,IF($A10<=AK$9,$F10/12,0)) -> 1333.3333 | AL10: =IF(OR($F10<=0,(AL$9-$A10)>(365*$E10)),0,IF($A10<=AL$9,$F10/12,0)) -> 1333.3333 | AM10: =IF(OR($F10<=0,(AM$9-$A10)>(365*$E10)),0,IF($A10<=AM$9,$F10/12,0)) -> 1333.3333 | AN10: =IF(OR($F10<=0,(AN$9-$A10)>(365*$E10)),0,IF($A10<=AN$9,$F10/12,0)) -> 1333.3333 | AO10: =IF(OR($F10<=0,(AO$9-$A10)>(365*$E10)),0,IF($A10<=AO$9,$F10/12,0)) -> 1333.3333 | AP10: =IF(OR($F10<=0,(AP$9-$A10)>(365*$E10)),0,IF($A10<=AP$9,$F10/12,0)) -> 1333.3333 | ... AT10: =IF(OR($F10<=0,(AT$9-$A10)>(365*$E10)),0,IF($A10<=AT$9,$F10/12,0)) -> 1333.3333 | AU10: =SUM(AI10:AT10) -> 16000 | AV10: =IF(AND($AT$9>$A10,$AU10<>0),$D10-$S10-$AG10-$AU10,0) -> 33333.333 | AW10: =IF(OR($F10<=0,(AW$9-$A10)>(365*$E10)),0,IF($A10<=AW$9,$F10/12,0)) -> 1333.3333 | AX10: =IF(OR($F10<=0,(AX$9-$A10)>(365*$E10)),0,IF($A10<=AX$9,$F10/12,0)) -> 1333.3333 | AY10: =IF(OR($F10<=0,(AY$9-$A10)>(365*$E10)),0,IF($A10<=AY$9,$F10/12,0)) -> 1333.3333 | AZ10: =IF(OR($F10<=0,(AZ$9-$A10)>(365*$E10)),0,IF($A10<=AZ$9,$F10/12,0)) -> 1333.3333 | BA10: =IF(OR($F10<=0,(BA$9-$A10)>(365*$E10)),0,IF($A10<=BA$9,$F10/12,0)) -> 1333.3333 | BB10: =IF(OR($F10<=0,(BB$9-$A10)>(365*$E10)),0,IF($A10<=BB$9,$F10/12,0)) -> 1333.3333 | BC10: =IF(OR($F10<=0,(BC$9-$A10)>(365*$E10)),0,IF($A10<=BC$9,$F10/12,0)) -> 1333.3333 | BD10: =IF(OR($F10<=0,(BD$9-$A10)>(365*$E10)),0,IF($A10<=BD$9,$F10/12,0)) -> 1333.3333 | ... BH10: =IF(OR($F10<=0,(BH$9-$A10)>(365*$E10)),0,IF($A10<=BH$9,$F10/12,0)) -> 1333.3333 | BI10: =SUM(AW10:BH10) -> 16000 | BJ10: =IF(AND($BH$9>$A10,$BI10<>0),$D10-$S10-$AG10-$AU10-$BI10,0) -> 17333.333 | BK10: =IF(OR($BJ10<=0,(BK$9-$A10)>($E10*365)),0,IF($A10<=BK$9,$F10/12)) -> 1333.3333 | BL10: =IF(OR($BJ10<=0,(BL$9-$A10)>($E10*365)),0,IF($A10<=BL$9,$F10/12)) -> 1333.3333 | BM10: =IF(OR($BJ10<=0,(BM$9-$A10)>($E10*365)),0,IF($A10<=BM$9,$F10/12)) -> 1333.3333 | BN10: =IF(OR($BJ10<=0,(BN$9-$A10)>($E10*365)),0,IF($A10<=BN$9,$F10/12)) -> 1333.3333 | BO10: =IF(OR($BJ10<=0,(BO$9-$A10)>($E10*365)),0,IF($A10<=BO$9,$F10/12)) -> 1333.3333 | BP10: =IF(OR($BJ10<=0,(BP$9-$A10)>($E10*365)),0,IF($A10<=BP$9,$F10/12)) -> 1333.3333 | BQ10: =IF(OR($BJ10<=0,(BQ$9-$A10)>($E10*365)),0,IF($A10<=BQ$9,$F10/12)) -> 1333.3333 | BR10: =IF(OR($BJ10<=0,(BR$9-$A10)>($E10*365)),0,IF($A10<=BR$9,$F10/12)) -> 1333.3333 | ... BV10: =IF(OR($BJ10<=0,(BV$9-$A10)>($E10*365)),0,IF($A10<=BV$9,$F10/12)) -> 1333.3333 | BW10: =SUM(BK10:BV10) -> 16000 | BX10: =IF(AND($BV$9>$A10,$BW10<>0),$D10-$S10-$AG10-$AU10-$BI10-$BW10,0) -> 1333.3333 | BY10: =IF(OR($BX10<=0,(BY$9-$A10)>($E10*365)),0,IF($A10<=BY$9,$F10/12)) -> 1333.3333 | BZ10: =IF(OR($BX10<=0,(BZ$9-$A10)>($E10*365)),0,IF($A10<=BZ$9,$F10/12)) -> 0 | CA10: =IF(OR($BX10<=0,(CA$9-$A10)>($E10*365)),0,IF($A10<=CA$9,$F10/12)) -> 0 | CB10: =IF(OR($BX10<=0,(CB$9-$A10)>($E10*365)),0,IF($A10<=CB$9,$F10/12)) -> 0 | CC10: =IF(OR($BX10<=0,(CC$9-$A10)>($E10*365)),0,IF($A10<=CC$9,$F10/12)) -> 0 | CD10: =IF(OR($BX10<=0,(CD$9-$A10)>($E10*365)),0,IF($A10<=CD$9,$F10/12)) -> 0 | CE10: =IF(OR($BX10<=0,(CE$9-$A10)>($E10*365)),0,IF($A10<=CE$9,$F10/12)) -> 0 | CF10: =IF(OR($BX10<=0,(CF$9-$A10)>($E10*365)),0,IF($A10<=CF$9,$F10/12)) -> 0 | ... CJ10: =IF(OR($BX10<=0,(CJ$9-$A10)>($E10*365)),0,IF($A10<=CJ$9,$F10/12)) -> 0 | CK10: =SUM(BY10:CJ10) -> 1333.3333 | CL10: =IF(AND($CJ$9>$A10,$CK10<>0),$D10-$S10-$AG10-$AU10-$BI10-$BW10-$CK$10,0) -> -6.5938366e-12 | CM10: =IF(OR($CL10<=0,(CM$9-$A10)>($E10*365)),0,IF($A10<=CM$9,$F10/12)) -> 0 | CN10: =IF(OR($CL10<=0,(CN$9-$A10)>($E10*365)),0,IF($A10<=CN$9,$F10/12)) -> 0 | CO10: =IF(OR($CL10<=0,(CO$9-$A10)>($E10*365)),0,IF($A10<=CO$9,$F10/12)) -> 0 | CP10: =IF(OR($CL10<=0,(CP$9-$A10)>($E10*365)),0,IF($A10<=CP$9,$F10/12)) -> 0 | CQ10: =IF(OR($CL10<=0,(CQ$9-$A10)>($E10*365)),0,IF($A10<=CQ$9,$F10/12)) -> 0 | CR10: =IF(OR($CL10<=0,(CR$9-$A10)>($E10*365)),0,IF($A10<=CR$9,$F10/12)) -> 0 | CS10: =IF(OR($CL10<=0,(CS$9-$A10)>($E10*365)),0,IF($A10<=CS$9,$F10/12)) -> 0 | CT10: =IF(OR($CL10<=0,(CT$9-$A10)>($E10*365)),0,IF($A10<=CT$9,$F10/12)) -> 0 | ... CX10: =IF(OR($CL10<=0,(CX$9-$A10)>($E10*365)),0,IF($A10<=CX$9,$F10/12)) -> 0 | CY10: =SUM(CM10:CX10) -> 0 | CZ10: =IF(AND($CX$9>$A10,$CY10<>0),$D10-$S10-$AG10-$AU10-$BI10-$BW10-$CK10-$CY10,0) -> 0 | DA10: =IF(OR($CZ10<=0,(DA$9-$A10)>($E10*365)),0,IF($A10<=DA$9,$F10/12)) -> 0 | DB10: =IF(OR($CZ10<=0,(DB$9-$A10)>($E10*365)),0,IF($A10<=DB$9,$F10/12)) -> 0 | DC10: =IF(OR($CZ10<=0,(DC$9-$A10)>($E10*365)),0,IF($A10<=DC$9,$F10/12)) -> 0 | DD10: =IF(OR($CZ10<=0,(DD$9-$A10)>($E10*365)),0,IF($A10<=DD$9,$F10/12)) -> 0 | DE10: =IF(OR($CZ10<=0,(DE$9-$A10)>($E10*365)),0,IF($A10<=DE$9,$F10/12)) -> 0 | DF10: =IF(OR($CZ10<=0,(DF$9-$A10)>($E10*365)),0,IF($A10<=DF$9,$F10/12)) -> 0 | DG10: =IF(OR($CZ10<=0,(DG$9-$A10)>($E10*365)),0,IF($A10<=DG$9,$F10/12)) -> 0 | DH10: =IF(OR($CZ10<=0,(DH$9-$A10)>($E10*365)),0,IF($A10<=DH$9,$F10/12)) -> 0 | ... DL10: =IF(OR($CZ10<=0,(DL$9-$A10)>($E10*365)),0,IF($A10<=DL$9,$F10/12)) -> 0 | DM10: =SUM(DA10:DL10) -> 0 | DN10: =IF(AND($DL$9>$A10,$DM10<>0),$D10-$S10-$AG10-$AU10-$BI10-$BW10-$CK$10-$CY10-$DM10,0) -> 0 | DO10: =IF(OR($DN10<=0,(DO$9-$A10)>($E10*365)),0,IF($A10<=DO$9,$F10/12)) -> 0 | DP10: =IF(OR($DN10<=0,(DP$9-$A10)>($E10*365)),0,IF($A10<=DP$9,$F10/12)) -> 0 | DQ10: =IF(OR($DN10<=0,(DQ$9-$A10)>($E10*365)),0,IF($A10<=DQ$9,$F10/12)) -> 0 | DR10: =IF(OR($DN10<=0,(DR$9-$A10)>($E10*365)),0,IF($A10<=DR$9,$F10/12)) -> 0 | DS10: =IF(OR($DN10<=0,(DS$9-$A10)>($E10*365)),0,IF($A10<=DS$9,$F10/12)) -> 0 | DT10: =IF(OR($DN10<=0,(DT$9-$A10)>($E10*365)),0,IF($A10<=DT$9,$F10/12)) -> 0 | DU10: =IF(OR($DN10<=0,(DU$9-$A10)>($E10*365)),0,IF($A10<=DU$9,$F10/12)) -> 0 | DV10: =IF(OR($DN10<=0,(DV$9-$A10)>($E10*365)),0,IF($A10<=DV$9,$F10/12)) -> 0 | ... DZ10: =IF(OR($DN10<=0,(DZ$9-$A10)>($E10*365)),0,IF($A10<=DZ$9,$F10/12)) -> 0 | EA10: =SUM(DO10:DZ10) -> 0 | EB10: =IF(AND($DZ$9>$A10,$EA10<>0),$D10-$S10-$AG10-$AU10-$BI10-$BW10--CY10-$DM10-$CK10-$EA10,0) -> 0
A11: 42707 | B11: Aménagement | C11: etagéres de burau | D11: 13000 | E11: 5 | F11: =D11/E11 -> 2600 | G11: =IF(OR($F11<=0,(G$9-$A11)>(365*$E11)),0,IF($A11<=G$9,$F11/12,0)) -> 0 | H11: =IF(OR($F11<=0,(H$9-$A11)>(365*$E11)),0,IF($A11<=H$9,$F11/12,0)) -> 0 | I11: =IF(OR($F11<=0,(I$9-$A11)>(365*$E11)),0,IF($A11<=I$9,$F11/12,0)) -> 0 | J11: =IF(OR($F11<=0,(J$9-$A11)>(365*$E11)),0,IF($A11<=J$9,$F11/12,0)) -> 0 | K11: =IF(OR($F11<=0,(K$9-$A11)>(365*$E11)),0,IF($A11<=K$9,$F11/12,0)) -> 0 | L11: =IF(OR($F11<=0,(L$9-$A11)>(365*$E11)),0,IF($A11<=L$9,$F11/12,0)) -> 0 | M11: =IF(OR($F11<=0,(M$9-$A11)>(365*$E11)),0,IF($A11<=M$9,$F11/12,0)) -> 0 | N11: =IF(OR($F11<=0,(N$9-$A11)>(365*$E11)),0,IF($A11<=N$9,$F11/12,0)) -> 0 | ... R11: =IF(OR($F11<=0,(R$9-$A11)>(365*$E11)),0,IF($A11<=R$9,$F11/12,0)) -> 0 | S11: =SUM(G11:R11) -> 0 | T11: =IF(AND($R$9>A11,$S11<>0),$D11-$S11,0) -> 0 | U11: =IF(OR($F11<=0,(U$9-$A11)>(365*$E11)),0,IF($A11<=U$9,$F11/12,0)) -> 0 | V11: =IF(OR($F11<=0,(V$9-$A11)>(365*$E11)),0,IF($A11<=V$9,$F11/12,0)) -> 0 | W11: =IF(OR($F11<=0,(W$9-$A11)>(365*$E11)),0,IF($A11<=W$9,$F11/12,0)) -> 0 | X11: =IF(OR($F11<=0,(X$9-$A11)>(365*$E11)),0,IF($A11<=X$9,$F11/12,0)) -> 0 | Y11: =IF(OR($F11<=0,(Y$9-$A11)>(365*$E11)),0,IF($A11<=Y$9,$F11/12,0)) -> 0 | Z11: =IF(OR($F11<=0,(Z$9-$A11)>(365*$E11)),0,IF($A11<=Z$9,$F11/12,0)) -> 0 | AA11: =IF(OR($F11<=0,(AA$9-$A11)>(365*$E11)),0,IF($A11<=AA$9,$F11/12,0)) -> 0 | AB11: =IF(OR($F11<=0,(AB$9-$A11)>(365*$E11)),0,IF($A11<=AB$9,$F11/12,0)) -> 0 | ... AF11: =IF(OR($F11<=0,(AF$9-$A11)>(365*$E11)),0,IF($A11<=AF$9,$F11/12,0)) -> 0 | AG11: =SUM(U11:AF11) -> 0 | AH11: =IF(AND($AF$9>$A11,$AG11<>0),$D11-$S11-$AG11,0) -> 0 | AI11: =IF(OR($F11<=0,(AI$9-$A11)>(365*$E11)),0,IF($A11<=AI$9,$F11/12,0)) -> 0 | AJ11: =IF(OR($F11<=0,(AJ$9-$A11)>(365*$E11)),0,IF($A11<=AJ$9,$F11/12,0)) -> 216.66667 | AK11: =IF(OR($F11<=0,(AK$9-$A11)>(365*$E11)),0,IF($A11<=AK$9,$F11/12,0)) -> 216.66667 | AL11: =IF(OR($F11<=0,(AL$9-$A11)>(365*$E11)),0,IF($A11<=AL$9,$F11/12,0)) -> 216.66667 | AM11: =IF(OR($F11<=0,(AM$9-$A11)>(365*$E11)),0,IF($A11<=AM$9,$F11/12,0)) -> 216.66667 | AN11: =IF(OR($F11<=0,(AN$9-$A11)>(365*$E11)),0,IF($A11<=AN$9,$F11/12,0)) -> 216.66667 | AO11: =IF(OR($F11<=0,(AO$9-$A11)>(365*$E11)),0,IF($A11<=AO$9,$F11/12,0)) -> 216.66667 | AP11: =IF(OR($F11<=0,(AP$9-$A11)>(365*$E11)),0,IF($A11<=AP$9,$F11/12,0)) -> 216.66667 | ... AT11: =IF(OR($F11<=0,(AT$9-$A11)>(365*$E11)),0,IF($A11<=AT$9,$F11/12,0)) -> 216.66667 | AU11: =SUM(AI11:AT11) -> 2383.3333 | AV11: =IF(AND($AT$9>$A11,$AU11<>0),$D11-$S11-$AG11-$AU11,0) -> 10616.667 | AW11: =IF(OR($F11<=0,(AW$9-$A11)>(365*$E11)),0,IF($A11<=AW$9,$F11/12,0)) -> 216.66667 | AX11: =IF(OR($F11<=0,(AX$9-$A11)>(365*$E11)),0,IF($A11<=AX$9,$F11/12,0)) -> 216.66667 | AY11: =IF(OR($F11<=0,(AY$9-$A11)>(365*$E11)),0,IF($A11<=AY$9,$F11/12,0)) -> 216.66667 | AZ11: =IF(OR($F11<=0,(AZ$9-$A11)>(365*$E11)),0,IF($A11<=AZ$9,$F11/12,0)) -> 216.66667 | BA11: =IF(OR($F11<=0,(BA$9-$A11)>(365*$E11)),0,IF($A11<=BA$9,$F11/12,0)) -> 216.66667 | BB11: =IF(OR($F11<=0,(BB$9-$A11)>(365*$E11)),0,IF($A11<=BB$9,$F11/12,0)) -> 216.66667 | BC11: =IF(OR($F11<=0,(BC$9-$A11)>(365*$E11)),0,IF($A11<=BC$9,$F11/12,0)) -> 216.66667 | BD11: =IF(OR($F11<=0,(BD$9-$A11)>(365*$E11)),0,IF($A11<=BD$9,$F11/12,0)) -> 216.66667 | ... BH11: =IF(OR($F11<=0,(BH$9-$A11)>(365*$E11)),0,IF($A11<=BH$9,$F11/12,0)) -> 216.66667 | BI11: =SUM(AW11:BH11) -> 2600 | BJ11: =IF(AND($BH$9>$A11,$BI11<>0),$D11-$S11-$AG11-$AU11-$BI11,0) -> 8016.6667 | BK11: =IF(OR($BJ11<=0,(BK$9-$A11)>($E11*365)),0,IF($A11<=BK$9,$F11/12)) -> 216.66667 | BL11: =IF(OR($BJ11<=0,(BL$9-$A11)>($E11*365)),0,IF($A11<=BL$9,$F11/12)) -> 216.66667 | BM11: =IF(OR($BJ11<=0,(BM$9-$A11)>($E11*365)),0,IF($A11<=BM$9,$F11/12)) -> 216.66667 | BN11: =IF(OR($BJ11<=0,(BN$9-$A11)>($E11*365)),0,IF($A11<=BN$9,$F11/12)) -> 216.66667 | BO11: =IF(OR($BJ11<=0,(BO$9-$A11)>($E11*365)),0,IF($A11<=BO$9,$F11/12)) -> 216.66667 | BP11: =IF(OR($BJ11<=0,(BP$9-$A11)>($E11*365)),0,IF($A11<=BP$9,$F11/12)) -> 216.66667 | BQ11: =IF(OR($BJ11<=0,(BQ$9-$A11)>($E11*365)),0,IF($A11<=BQ$9,$F11/12)) -> 216.66667 | BR11: =IF(OR($BJ11<=0,(BR$9-$A11)>($E11*365)),0,IF($A11<=BR$9,$F11/12)) -> 216.66667 | ... BV11: =IF(OR($BJ11<=0,(BV$9-$A11)>($E11*365)),0,IF($A11<=BV$9,$F11/12)) -> 216.66667 | BW11: =SUM(BK11:BV11) -> 2600 | BX11: =IF(AND($BV$9>$A11,$BW11<>0),$D11-$S11-$AG11-$AU11-$BI11-$BW11,0) -> 5416.6667 | BY11: =IF(OR($BX11<=0,(BY$9-$A11)>($E11*365)),0,IF($A11<=BY$9,$F11/12)) -> 216.66667 | BZ11: =IF(OR($BX11<=0,(BZ$9-$A11)>($E11*365)),0,IF($A11<=BZ$9,$F11/12)) -> 216.66667 | CA11: =IF(OR($BX11<=0,(CA$9-$A11)>($E11*365)),0,IF($A11<=CA$9,$F11/12)) -> 216.66667 | CB11: =IF(OR($BX11<=0,(CB$9-$A11)>($E11*365)),0,IF($A11<=CB$9,$F11/12)) -> 216.66667 | CC11: =IF(OR($BX11<=0,(CC$9-$A11)>($E11*365)),0,IF($A11<=CC$9,$F11/12)) -> 216.66667 | CD11: =IF(OR($BX11<=0,(CD$9-$A11)>($E11*365)),0,IF($A11<=CD$9,$F11/12)) -> 216.66667 | CE11: =IF(OR($BX11<=0,(CE$9-$A11)>($E11*365)),0,IF($A11<=CE$9,$F11/12)) -> 216.66667 | CF11: =IF(OR($BX11<=0,(CF$9-$A11)>($E11*365)),0,IF($A11<=CF$9,$F11/12)) -> 216.66667 | ... CJ11: =IF(OR($BX11<=0,(CJ$9-$A11)>($E11*365)),0,IF($A11<=CJ$9,$F11/12)) -> 216.66667 | CK11: =SUM(BY11:CJ11) -> 2600 | CL11: =IF(AND($CJ$9>$A11,$CK11<>0),$D11-$S11-$AG11-$AU11-$BI11-$BW11-$CK$10,0) -> 4083.3333 | CM11: =IF(OR($CL11<=0,(CM$9-$A11)>($E11*365)),0,IF($A11<=CM$9,$F11/12)) -> 216.66667 | CN11: =IF(OR($CL11<=0,(CN$9-$A11)>($E11*365)),0,IF($A11<=CN$9,$F11/12)) -> 216.66667 | CO11: =IF(OR($CL11<=0,(CO$9-$A11)>($E11*365)),0,IF($A11<=CO$9,$F11/12)) -> 216.66667 | CP11: =IF(OR($CL11<=0,(CP$9-$A11)>($E11*365)),0,IF($A11<=CP$9,$F11/12)) -> 216.66667 | CQ11: =IF(OR($CL11<=0,(CQ$9-$A11)>($E11*365)),0,IF($A11<=CQ$9,$F11/12)) -> 216.66667 | CR11: =IF(OR($CL11<=0,(CR$9-$A11)>($E11*365)),0,IF($A11<=CR$9,$F11/12)) -> 216.66667 | CS11: =IF(OR($CL11<=0,(CS$9-$A11)>($E11*365)),0,IF($A11<=CS$9,$F11/12)) -> 216.66667 | CT11: =IF(OR($CL11<=0,(CT$9-$A11)>($E11*365)),0,IF($A11<=CT$9,$F11/12)) -> 216.66667 | ... CX11: =IF(OR($CL11<=0,(CX$9-$A11)>($E11*365)),0,IF($A11<=CX$9,$F11/12)) -> 216.66667 | CY11: =SUM(CM11:CX11) -> 2600 | CZ11: =IF(AND($CX$9>$A11,$CY11<>0),$D11-$S11-$AG11-$AU11-$BI11-$BW11-$CK11-$CY11,0) -> 216.66667 | DA11: =IF(OR($CZ11<=0,(DA$9-$A11)>($E11*365)),0,IF($A11<=DA$9,$F11/12)) -> 216.66667 | DB11: =IF(OR($CZ11<=0,(DB$9-$A11)>($E11*365)),0,IF($A11<=DB$9,$F11/12)) -> 0 | DC11: =IF(OR($CZ11<=0,(DC$9-$A11)>($E11*365)),0,IF($A11<=DC$9,$F11/12)) -> 0 | DD11: =IF(OR($CZ11<=0,(DD$9-$A11)>($E11*365)),0,IF($A11<=DD$9,$F11/12)) -> 0 | DE11: =IF(OR($CZ11<=0,(DE$9-$A11)>($E11*365)),0,IF($A11<=DE$9,$F11/12)) -> 0 | DF11: =IF(OR($CZ11<=0,(DF$9-$A11)>($E11*365)),0,IF($A11<=DF$9,$F11/12)) -> 0 | DG11: =IF(OR($CZ11<=0,(DG$9-$A11)>($E11*365)),0,IF($A11<=DG$9,$F11/12)) -> 0 | DH11: =IF(OR($CZ11<=0,(DH$9-$A11)>($E11*365)),0,IF($A11<=DH$9,$F11/12)) -> 0 | ... DL11: =IF(OR($CZ11<=0,(DL$9-$A11)>($E11*365)),0,IF($A11<=DL$9,$F11/12)) -> 0 | DM11: =SUM(DA11:DL11) -> 216.66667 | DN11: =IF(AND($DL$9>$A11,$DM11<>0),$D11-$S11-$AG11-$AU11-$BI11-$BW11-$CK$10-$CY11-$DM11,0) -> 1266.6667 | DO11: =IF(OR($DN11<=0,(DO$9-$A11)>($E11*365)),0,IF($A11<=DO$9,$F11/12)) -> 0 | DP11: =IF(OR($DN11<=0,(DP$9-$A11)>($E11*365)),0,IF($A11<=DP$9,$F11/12)) -> 0 | DQ11: =IF(OR($DN11<=0,(DQ$9-$A11)>($E11*365)),0,IF($A11<=DQ$9,$F11/12)) -> 0 | DR11: =IF(OR($DN11<=0,(DR$9-$A11)>($E11*365)),0,IF($A11<=DR$9,$F11/12)) -> 0 | DS11: =IF(OR($DN11<=0,(DS$9-$A11)>($E11*365)),0,IF($A11<=DS$9,$F11/12)) -> 0 | DT11: =IF(OR($DN11<=0,(DT$9-$A11)>($E11*365)),0,IF($A11<=DT$9,$F11/12)) -> 0 | DU11: =IF(OR($DN11<=0,(DU$9-$A11)>($E11*365)),0,IF($A11<=DU$9,$F11/12)) -> 0 | DV11: =IF(OR($DN11<=0,(DV$9-$A11)>($E11*365)),0,IF($A11<=DV$9,$F11/12)) -> 0 | ... DZ11: =IF(OR($DN11<=0,(DZ$9-$A11)>($E11*365)),0,IF($A11<=DZ$9,$F11/12)) -> 0 | EA11: =SUM(DO11:DZ11) -> 0 | EB11: =IF(AND($DZ$9>$A11,$EA11<>0),$D11-$S11-$AG11-$AU11-$BI11-$BW11--CY11-$DM11-$CK11-$EA11,0) -> 0
A12: 42736 | B12: Matériels | C12: table de réparation | D12: 40000 | E12: 5 | F12: =D12/E12 -> 8000 | G12: =IF(OR($F12<=0,(G$9-$A12)>(365*$E12)),0,IF($A12<=G$9,$F12/12,0)) -> 0 | H12: =IF(OR($F12<=0,(H$9-$A12)>(365*$E12)),0,IF($A12<=H$9,$F12/12,0)) -> 0 | I12: =IF(OR($F12<=0,(I$9-$A12)>(365*$E12)),0,IF($A12<=I$9,$F12/12,0)) -> 0 | J12: =IF(OR($F12<=0,(J$9-$A12)>(365*$E12)),0,IF($A12<=J$9,$F12/12,0)) -> 0 | K12: =IF(OR($F12<=0,(K$9-$A12)>(365*$E12)),0,IF($A12<=K$9,$F12/12,0)) -> 0 | L12: =IF(OR($F12<=0,(L$9-$A12)>(365*$E12)),0,IF($A12<=L$9,$F12/12,0)) -> 0 | M12: =IF(OR($F12<=0,(M$9-$A12)>(365*$E12)),0,IF($A12<=M$9,$F12/12,0)) -> 0 | N12: =IF(OR($F12<=0,(N$9-$A12)>(365*$E12)),0,IF($A12<=N$9,$F12/12,0)) -> 0 | ... R12: =IF(OR($F12<=0,(R$9-$A12)>(365*$E12)),0,IF($A12<=R$9,$F12/12,0)) -> 0 | S12: =SUM(G12:R12) -> 0 | T12: =IF(AND($R$9>A12,$S12<>0),$D12-$S12,0) -> 0 | U12: =IF(OR($F12<=0,(U$9-$A12)>(365*$E12)),0,IF($A12<=U$9,$F12/12,0)) -> 0 | V12: =IF(OR($F12<=0,(V$9-$A12)>(365*$E12)),0,IF($A12<=V$9,$F12/12,0)) -> 0 | W12: =IF(OR($F12<=0,(W$9-$A12)>(365*$E12)),0,IF($A12<=W$9,$F12/12,0)) -> 0 | X12: =IF(OR($F12<=0,(X$9-$A12)>(365*$E12)),0,IF($A12<=X$9,$F12/12,0)) -> 0 | Y12: =IF(OR($F12<=0,(Y$9-$A12)>(365*$E12)),0,IF($A12<=Y$9,$F12/12,0)) -> 0 | Z12: =IF(OR($F12<=0,(Z$9-$A12)>(365*$E12)),0,IF($A12<=Z$9,$F12/12,0)) -> 0 | AA12: =IF(OR($F12<=0,(AA$9-$A12)>(365*$E12)),0,IF($A12<=AA$9,$F12/12,0)) -> 0 | AB12: =IF(OR($F12<=0,(AB$9-$A12)>(365*$E12)),0,IF($A12<=AB$9,$F12/12,0)) -> 0 | ... AF12: =IF(OR($F12<=0,(AF$9-$A12)>(365*$E12)),0,IF($A12<=AF$9,$F12/12,0)) -> 0 | AG12: =SUM(U12:AF12) -> 0 | AH12: =IF(AND($AF$9>$A12,$AG12<>0),$D12-$S12-$AG12,0) -> 0 | AI12: =IF(OR($F12<=0,(AI$9-$A12)>(365*$E12)),0,IF($A12<=AI$9,$F12/12,0)) -> 0 | AJ12: =IF(OR($F12<=0,(AJ$9-$A12)>(365*$E12)),0,IF($A12<=AJ$9,$F12/12,0)) -> 0 | AK12: =IF(OR($F12<=0,(AK$9-$A12)>(365*$E12)),0,IF($A12<=AK$9,$F12/12,0)) -> 666.66667 | AL12: =IF(OR($F12<=0,(AL$9-$A12)>(365*$E12)),0,IF($A12<=AL$9,$F12/12,0)) -> 666.66667 | AM12: =IF(OR($F12<=0,(AM$9-$A12)>(365*$E12)),0,IF($A12<=AM$9,$F12/12,0)) -> 666.66667 | AN12: =IF(OR($F12<=0,(AN$9-$A12)>(365*$E12)),0,IF($A12<=AN$9,$F12/12,0)) -> 666.66667 | AO12: =IF(OR($F12<=0,(AO$9-$A12)>(365*$E12)),0,IF($A12<=AO$9,$F12/12,0)) -> 666.66667 | AP12: =IF(OR($F12<=0,(AP$9-$A12)>(365*$E12)),0,IF($A12<=AP$9,$F12/12,0)) -> 666.66667 | ... AT12: =IF(OR($F12<=0,(AT$9-$A12)>(365*$E12)),0,IF($A12<=AT$9,$F12/12,0)) -> 666.66667 | AU12: =SUM(AI12:AT12) -> 6666.6667 | AV12: =IF(AND($AT$9>$A12,$AU12<>0),$D12-$S12-$AG12-$AU12,0) -> 33333.333 | AW12: =IF(OR($F12<=0,(AW$9-$A12)>(365*$E12)),0,IF($A12<=AW$9,$F12/12,0)) -> 666.66667 | AX12: =IF(OR($F12<=0,(AX$9-$A12)>(365*$E12)),0,IF($A12<=AX$9,$F12/12,0)) -> 666.66667 | AY12: =IF(OR($F12<=0,(AY$9-$A12)>(365*$E12)),0,IF($A12<=AY$9,$F12/12,0)) -> 666.66667 | AZ12: =IF(OR($F12<=0,(AZ$9-$A12)>(365*$E12)),0,IF($A12<=AZ$9,$F12/12,0)) -> 666.66667 | BA12: =IF(OR($F12<=0,(BA$9-$A12)>(365*$E12)),0,IF($A12<=BA$9,$F12/12,0)) -> 666.66667 | BB12: =IF(OR($F12<=0,(BB$9-$A12)>(365*$E12)),0,IF($A12<=BB$9,$F12/12,0)) -> 666.66667 | BC12: =IF(OR($F12<=0,(BC$9-$A12)>(365*$E12)),0,IF($A12<=BC$9,$F12/12,0)) -> 666.66667 | BD12: =IF(OR($F12<=0,(BD$9-$A12)>(365*$E12)),0,IF($A12<=BD$9,$F12/12,0)) -> 666.66667 | ... BH12: =IF(OR($F12<=0,(BH$9-$A12)>(365*$E12)),0,IF($A12<=BH$9,$F12/12,0)) -> 666.66667 | BI12: =SUM(AW12:BH12) -> 8000 | BJ12: =IF(AND($BH$9>$A12,$BI12<>0),$D12-$S12-$AG12-$AU12-$BI12,0) -> 25333.333 | BK12: =IF(OR($BJ12<=0,(BK$9-$A12)>($E12*365)),0,IF($A12<=BK$9,$F12/12)) -> 666.66667 | BL12: =IF(OR($BJ12<=0,(BL$9-$A12)>($E12*365)),0,IF($A12<=BL$9,$F12/12)) -> 666.66667 | BM12: =IF(OR($BJ12<=0,(BM$9-$A12)>($E12*365)),0,IF($A12<=BM$9,$F12/12)) -> 666.66667 | BN12: =IF(OR($BJ12<=0,(BN$9-$A12)>($E12*365)),0,IF($A12<=BN$9,$F12/12)) -> 666.66667 | BO12: =IF(OR($BJ12<=0,(BO$9-$A12)>($E12*365)),0,IF($A12<=BO$9,$F12/12)) -> 666.66667 | BP12: =IF(OR($BJ12<=0,(BP$9-$A12)>($E12*365)),0,IF($A12<=BP$9,$F12/12)) -> 666.66667 | BQ12: =IF(OR($BJ12<=0,(BQ$9-$A12)>($E12*365)),0,IF($A12<=BQ$9,$F12/12)) -> 666.66667 | BR12: =IF(OR($BJ12<=0,(BR$9-$A12)>($E12*365)),0,IF($A12<=BR$9,$F12/12)) -> 666.66667 | ... BV12: =IF(OR($BJ12<=0,(BV$9-$A12)>($E12*365)),0,IF($A12<=BV$9,$F12/12)) -> 666.66667 | BW12: =SUM(BK12:BV12) -> 8000 | BX12: =IF(AND($BV$9>$A12,$BW12<>0),$D12-$S12-$AG12-$AU12-$BI12-$BW12,0) -> 17333.333 | BY12: =IF(OR($BX12<=0,(BY$9-$A12)>($E12*365)),0,IF($A12<=BY$9,$F12/12)) -> 666.66667 | BZ12: =IF(OR($BX12<=0,(BZ$9-$A12)>($E12*365)),0,IF($A12<=BZ$9,$F12/12)) -> 666.66667 | CA12: =IF(OR($BX12<=0,(CA$9-$A12)>($E12*365)),0,IF($A12<=CA$9,$F12/12)) -> 666.66667 | CB12: =IF(OR($BX12<=0,(CB$9-$A12)>($E12*365)),0,IF($A12<=CB$9,$F12/12)) -> 666.66667 | CC12: =IF(OR($BX12<=0,(CC$9-$A12)>($E12*365)),0,IF($A12<=CC$9,$F12/12)) -> 666.66667 | CD12: =IF(OR($BX12<=0,(CD$9-$A12)>($E12*365)),0,IF($A12<=CD$9,$F12/12)) -> 666.66667 | CE12: =IF(OR($BX12<=0,(CE$9-$A12)>($E12*365)),0,IF($A12<=CE$9,$F12/12)) -> 666.66667 | CF12: =IF(OR($BX12<=0,(CF$9-$A12)>($E12*365)),0,IF($A12<=CF$9,$F12/12)) -> 666.66667 | ... CJ12: =IF(OR($BX12<=0,(CJ$9-$A12)>($E12*365)),0,IF($A12<=CJ$9,$F12/12)) -> 666.66667 | CK12: =SUM(BY12:CJ12) -> 8000 | CL12: =IF(AND($CJ$9>$A12,$CK12<>0),$D12-$S12-$AG12-$AU12-$BI12-$BW12-$CK$10,0) -> 16000 | CM12: =IF(OR($CL12<=0,(CM$9-$A12)>($E12*365)),0,IF($A12<=CM$9,$F12/12)) -> 666.66667 | CN12: =IF(OR($CL12<=0,(CN$9-$A12)>($E12*365)),0,IF($A12<=CN$9,$F12/12)) -> 666.66667 | CO12: =IF(OR($CL12<=0,(CO$9-$A12)>($E12*365)),0,IF($A12<=CO$9,$F12/12)) -> 666.66667 | CP12: =IF(OR($CL12<=0,(CP$9-$A12)>($E12*365)),0,IF($A12<=CP$9,$F12/12)) -> 666.66667 | CQ12: =IF(OR($CL12<=0,(CQ$9-$A12)>($E12*365)),0,IF($A12<=CQ$9,$F12/12)) -> 666.66667 | CR12: =IF(OR($CL12<=0,(CR$9-$A12)>($E12*365)),0,IF($A12<=CR$9,$F12/12)) -> 666.66667 | CS12: =IF(OR($CL12<=0,(CS$9-$A12)>($E12*365)),0,IF($A12<=CS$9,$F12/12)) -> 666.66667 | CT12: =IF(OR($CL12<=0,(CT$9-$A12)>($E12*365)),0,IF($A12<=CT$9,$F12/12)) -> 666.66667 | ... CX12: =IF(OR($CL12<=0,(CX$9-$A12)>($E12*365)),0,IF($A12<=CX$9,$F12/12)) -> 666.66667 | CY12: =SUM(CM12:CX12) -> 8000 | CZ12: =IF(AND($CX$9>$A12,$CY12<>0),$D12-$S12-$AG12-$AU12-$BI12-$BW12-$CK12-$CY12,0) -> 1333.3333 | DA12: =IF(OR($CZ12<=0,(DA$9-$A12)>($E12*365)),0,IF($A12<=DA$9,$F12/12)) -> 666.66667 | DB12: =IF(OR($CZ12<=0,(DB$9-$A12)>($E12*365)),0,IF($A12<=DB$9,$F12/12)) -> 666.66667 | DC12: =IF(OR($CZ12<=0,(DC$9-$A12)>($E12*365)),0,IF($A12<=DC$9,$F12/12)) -> 0 | DD12: =IF(OR($CZ12<=0,(DD$9-$A12)>($E12*365)),0,IF($A12<=DD$9,$F12/12)) -> 0 | DE12: =IF(OR($CZ12<=0,(DE$9-$A12)>($E12*365)),0,IF($A12<=DE$9,$F12/12)) -> 0 | DF12: =IF(OR($CZ12<=0,(DF$9-$A12)>($E12*365)),0,IF($A12<=DF$9,$F12/12)) -> 0 | DG12: =IF(OR($CZ12<=0,(DG$9-$A12)>($E12*365)),0,IF($A12<=DG$9,$F12/12)) -> 0 | DH12: =IF(OR($CZ12<=0,(DH$9-$A12)>($E12*365)),0,IF($A12<=DH$9,$F12/12)) -> 0 | ... DL12: =IF(OR($CZ12<=0,(DL$9-$A12)>($E12*365)),0,IF($A12<=DL$9,$F12/12)) -> 0 | DM12: =SUM(DA12:DL12) -> 1333.3333 | DN12: =IF(AND($DL$9>$A12,$DM12<>0),$D12-$S12-$AG12-$AU12-$BI12-$BW12-$CK$10-$CY12-$DM12,0) -> 6666.6667 | DO12: =IF(OR($DN12<=0,(DO$9-$A12)>($E12*365)),0,IF($A12<=DO$9,$F12/12)) -> 0 | DP12: =IF(OR($DN12<=0,(DP$9-$A12)>($E12*365)),0,IF($A12<=DP$9,$F12/12)) -> 0 | DQ12: =IF(OR($DN12<=0,(DQ$9-$A12)>($E12*365)),0,IF($A12<=DQ$9,$F12/12)) -> 0 | DR12: =IF(OR($DN12<=0,(DR$9-$A12)>($E12*365)),0,IF($A12<=DR$9,$F12/12)) -> 0 | DS12: =IF(OR($DN12<=0,(DS$9-$A12)>($E12*365)),0,IF($A12<=DS$9,$F12/12)) -> 0 | DT12: =IF(OR($DN12<=0,(DT$9-$A12)>($E12*365)),0,IF($A12<=DT$9,$F12/12)) -> 0 | DU12: =IF(OR($DN12<=0,(DU$9-$A12)>($E12*365)),0,IF($A12<=DU$9,$F12/12)) -> 0 | DV12: =IF(OR($DN12<=0,(DV$9-$A12)>($E12*365)),0,IF($A12<=DV$9,$F12/12)) -> 0 | ... DZ12: =IF(OR($DN12<=0,(DZ$9-$A12)>($E12*365)),0,IF($A12<=DZ$9,$F12/12)) -> 0 | EA12: =SUM(DO12:DZ12) -> 0 | EB12: =IF(AND($DZ$9>$A12,$EA12<>0),$D12-$S12-$AG12-$AU12-$BI12-$BW12--CY12-$DM12-$CK12-$EA12,0) -> 0
A13: 42744 | B13: Aménagement | C13: boutaille a gaz | D13: 9000 | E13: 10 | F13: =D13/E13 -> 900 | G13: =IF(OR($F13<=0,(G$9-$A13)>(365*$E13)),0,IF($A13<=G$9,$F13/12,0)) -> 0 | H13: =IF(OR($F13<=0,(H$9-$A13)>(365*$E13)),0,IF($A13<=H$9,$F13/12,0)) -> 0 | I13: =IF(OR($F13<=0,(I$9-$A13)>(365*$E13)),0,IF($A13<=I$9,$F13/12,0)) -> 0 | J13: =IF(OR($F13<=0,(J$9-$A13)>(365*$E13)),0,IF($A13<=J$9,$F13/12,0)) -> 0 | K13: =IF(OR($F13<=0,(K$9-$A13)>(365*$E13)),0,IF($A13<=K$9,$F13/12,0)) -> 0 | L13: =IF(OR($F13<=0,(L$9-$A13)>(365*$E13)),0,IF($A13<=L$9,$F13/12,0)) -> 0 | M13: =IF(OR($F13<=0,(M$9-$A13)>(365*$E13)),0,IF($A13<=M$9,$F13/12,0)) -> 0 | N13: =IF(OR($F13<=0,(N$9-$A13)>(365*$E13)),0,IF($A13<=N$9,$F13/12,0)) -> 0 | ... R13: =IF(OR($F13<=0,(R$9-$A13)>(365*$E13)),0,IF($A13<=R$9,$F13/12,0)) -> 0 | S13: =SUM(G13:R13) -> 0 | T13: =IF(AND($R$9>A13,$S13<>0),$D13-$S13,0) -> 0 | U13: =IF(OR($F13<=0,(U$9-$A13)>(365*$E13)),0,IF($A13<=U$9,$F13/12,0)) -> 0 | V13: =IF(OR($F13<=0,(V$9-$A13)>(365*$E13)),0,IF($A13<=V$9,$F13/12,0)) -> 0 | W13: =IF(OR($F13<=0,(W$9-$A13)>(365*$E13)),0,IF($A13<=W$9,$F13/12,0)) -> 0 | X13: =IF(OR($F13<=0,(X$9-$A13)>(365*$E13)),0,IF($A13<=X$9,$F13/12,0)) -> 0 | Y13: =IF(OR($F13<=0,(Y$9-$A13)>(365*$E13)),0,IF($A13<=Y$9,$F13/12,0)) -> 0 | Z13: =IF(OR($F13<=0,(Z$9-$A13)>(365*$E13)),0,IF($A13<=Z$9,$F13/12,0)) -> 0 | AA13: =IF(OR($F13<=0,(AA$9-$A13)>(365*$E13)),0,IF($A13<=AA$9,$F13/12,0)) -> 0 | AB13: =IF(OR($F13<=0,(AB$9-$A13)>(365*$E13)),0,IF($A13<=AB$9,$F13/12,0)) -> 0 | ... AF13: =IF(OR($F13<=0,(AF$9-$A13)>(365*$E13)),0,IF($A13<=AF$9,$F13/12,0)) -> 0 | AG13: =SUM(U13:AF13) -> 0 | AH13: =IF(AND($AF$9>$A13,$AG13<>0),$D13-$S13-$AG13,0) -> 0 | AI13: =IF(OR($F13<=0,(AI$9-$A13)>(365*$E13)),0,IF($A13<=AI$9,$F13/12,0)) -> 0 | AJ13: =IF(OR($F13<=0,(AJ$9-$A13)>(365*$E13)),0,IF($A13<=AJ$9,$F13/12,0)) -> 0 | AK13: =IF(OR($F13<=0,(AK$9-$A13)>(365*$E13)),0,IF($A13<=AK$9,$F13/12,0)) -> 75 | AL13: =IF(OR($F13<=0,(AL$9-$A13)>(365*$E13)),0,IF($A13<=AL$9,$F13/12,0)) -> 75 | AM13: =IF(OR($F13<=0,(AM$9-$A13)>(365*$E13)),0,IF($A13<=AM$9,$F13/12,0)) -> 75 | AN13: =IF(OR($F13<=0,(AN$9-$A13)>(365*$E13)),0,IF($A13<=AN$9,$F13/12,0)) -> 75 | AO13: =IF(OR($F13<=0,(AO$9-$A13)>(365*$E13)),0,IF($A13<=AO$9,$F13/12,0)) -> 75 | AP13: =IF(OR($F13<=0,(AP$9-$A13)>(365*$E13)),0,IF($A13<=AP$9,$F13/12,0)) -> 75 | ... AT13: =IF(OR($F13<=0,(AT$9-$A13)>(365*$E13)),0,IF($A13<=AT$9,$F13/12,0)) -> 75 | AU13: =SUM(AI13:AT13) -> 750 | AV13: =IF(AND($AT$9>$A13,$AU13<>0),$D13-$S13-$AG13-$AU13,0) -> 8250 | AW13: =IF(OR($F13<=0,(AW$9-$A13)>(365*$E13)),0,IF($A13<=AW$9,$F13/12,0)) -> 75 | AX13: =IF(OR($F13<=0,(AX$9-$A13)>(365*$E13)),0,IF($A13<=AX$9,$F13/12,0)) -> 75 | AY13: =IF(OR($F13<=0,(AY$9-$A13)>(365*$E13)),0,IF($A13<=AY$9,$F13/12,0)) -> 75 | AZ13: =IF(OR($F13<=0,(AZ$9-$A13)>(365*$E13)),0,IF($A13<=AZ$9,$F13/12,0)) -> 75 | BA13: =IF(OR($F13<=0,(BA$9-$A13)>(365*$E13)),0,IF($A13<=BA$9,$F13/12,0)) -> 75 | BB13: =IF(OR($F13<=0,(BB$9-$A13)>(365*$E13)),0,IF($A13<=BB$9,$F13/12,0)) -> 75 | BC13: =IF(OR($F13<=0,(BC$9-$A13)>(365*$E13)),0,IF($A13<=BC$9,$F13/12,0)) -> 75 | BD13: =IF(OR($F13<=0,(BD$9-$A13)>(365*$E13)),0,IF($A13<=BD$9,$F13/12,0)) -> 75 | ... BH13: =IF(OR($F13<=0,(BH$9-$A13)>(365*$E13)),0,IF($A13<=BH$9,$F13/12,0)) -> 75 | BI13: =SUM(AW13:BH13) -> 900 | BJ13: =IF(AND($BH$9>$A13,$BI13<>0),$D13-$S13-$AG13-$AU13-$BI13,0) -> 7350 | BK13: =IF(OR($BJ13<=0,(BK$9-$A13)>($E13*365)),0,IF($A13<=BK$9,$F13/12)) -> 75 | BL13: =IF(OR($BJ13<=0,(BL$9-$A13)>($E13*365)),0,IF($A13<=BL$9,$F13/12)) -> 75 | BM13: =IF(OR($BJ13<=0,(BM$9-$A13)>($E13*365)),0,IF($A13<=BM$9,$F13/12)) -> 75 | BN13: =IF(OR($BJ13<=0,(BN$9-$A13)>($E13*365)),0,IF($A13<=BN$9,$F13/12)) -> 75 | BO13: =IF(OR($BJ13<=0,(BO$9-$A13)>($E13*365)),0,IF($A13<=BO$9,$F13/12)) -> 75 | BP13: =IF(OR($BJ13<=0,(BP$9-$A13)>($E13*365)),0,IF($A13<=BP$9,$F13/12)) -> 75 | BQ13: =IF(OR($BJ13<=0,(BQ$9-$A13)>($E13*365)),0,IF($A13<=BQ$9,$F13/12)) -> 75 | BR13: =IF(OR($BJ13<=0,(BR$9-$A13)>($E13*365)),0,IF($A13<=BR$9,$F13/12)) -> 75 | ... BV13: =IF(OR($BJ13<=0,(BV$9-$A13)>($E13*365)),0,IF($A13<=BV$9,$F13/12)) -> 75 | BW13: =SUM(BK13:BV13) -> 900 | BX13: =IF(AND($BV$9>$A13,$BW13<>0),$D13-$S13-$AG13-$AU13-$BI13-$BW13,0) -> 6450 | BY13: =IF(OR($BX13<=0,(BY$9-$A13)>($E13*365)),0,IF($A13<=BY$9,$F13/12)) -> 75 | BZ13: =IF(OR($BX13<=0,(BZ$9-$A13)>($E13*365)),0,IF($A13<=BZ$9,$F13/12)) -> 75 | CA13: =IF(OR($BX13<=0,(CA$9-$A13)>($E13*365)),0,IF($A13<=CA$9,$F13/12)) -> 75 | CB13: =IF(OR($BX13<=0,(CB$9-$A13)>($E13*365)),0,IF($A13<=CB$9,$F13/12)) -> 75 | CC13: =IF(OR($BX13<=0,(CC$9-$A13)>($E13*365)),0,IF($A13<=CC$9,$F13/12)) -> 75 | CD13: =IF(OR($BX13<=0,(CD$9-$A13)>($E13*365)),0,IF($A13<=CD$9,$F13/12)) -> 75 | CE13: =IF(OR($BX13<=0,(CE$9-$A13)>($E13*365)),0,IF($A13<=CE$9,$F13/12)) -> 75 | CF13: =IF(OR($BX13<=0,(CF$9-$A13)>($E13*365)),0,IF($A13<=CF$9,$F13/12)) -> 75 | ... CJ13: =IF(OR($BX13<=0,(CJ$9-$A13)>($E13*365)),0,IF($A13<=CJ$9,$F13/12)) -> 75 | CK13: =SUM(BY13:CJ13) -> 900 | CL13: =IF(AND($CJ$9>$A13,$CK13<>0),$D13-$S13-$AG13-$AU13-$BI13-$BW13-$CK$10,0) -> 5116.6667 | CM13: =IF(OR($CL13<=0,(CM$9-$A13)>($E13*365)),0,IF($A13<=CM$9,$F13/12)) -> 75 | CN13: =IF(OR($CL13<=0,(CN$9-$A13)>($E13*365)),0,IF($A13<=CN$9,$F13/12)) -> 75 | CO13: =IF(OR($CL13<=0,(CO$9-$A13)>($E13*365)),0,IF($A13<=CO$9,$F13/12)) -> 75 | CP13: =IF(OR($CL13<=0,(CP$9-$A13)>($E13*365)),0,IF($A13<=CP$9,$F13/12)) -> 75 | CQ13: =IF(OR($CL13<=0,(CQ$9-$A13)>($E13*365)),0,IF($A13<=CQ$9,$F13/12)) -> 75 | CR13: =IF(OR($CL13<=0,(CR$9-$A13)>($E13*365)),0,IF($A13<=CR$9,$F13/12)) -> 75 | CS13: =IF(OR($CL13<=0,(CS$9-$A13)>($E13*365)),0,IF($A13<=CS$9,$F13/12)) -> 75 | CT13: =IF(OR($CL13<=0,(CT$9-$A13)>($E13*365)),0,IF($A13<=CT$9,$F13/12)) -> 75 | ... CX13: =IF(OR($CL13<=0,(CX$9-$A13)>($E13*365)),0,IF($A13<=CX$9,$F13/12)) -> 75 | CY13: =SUM(CM13:CX13) -> 900 | CZ13: =IF(AND($CX$9>$A13,$CY13<>0),$D13-$S13-$AG13-$AU13-$BI13-$BW13-$CK13-$CY13,0) -> 4650 | DA13: =IF(OR($CZ13<=0,(DA$9-$A13)>($E13*365)),0,IF($A13<=DA$9,$F13/12)) -> 75 | DB13: =IF(OR($CZ13<=0,(DB$9-$A13)>($E13*365)),0,IF($A13<=DB$9,$F13/12)) -> 75 | DC13: =IF(OR($CZ13<=0,(DC$9-$A13)>($E13*365)),0,IF($A13<=DC$9,$F13/12)) -> 75 | DD13: =IF(OR($CZ13<=0,(DD$9-$A13)>($E13*365)),0,IF($A13<=DD$9,$F13/12)) -> 75 | DE13: =IF(OR($CZ13<=0,(DE$9-$A13)>($E13*365)),0,IF($A13<=DE$9,$F13/12)) -> 75 | DF13: =IF(OR($CZ13<=0,(DF$9-$A13)>($E13*365)),0,IF($A13<=DF$9,$F13/12)) -> 75 | DG13: =IF(OR($CZ13<=0,(DG$9-$A13)>($E13*365)),0,IF($A13<=DG$9,$F13/12)) -> 75 | DH13: =IF(OR($CZ13<=0,(DH$9-$A13)>($E13*365)),0,IF($A13<=DH$9,$F13/12)) -> 75 | ... DL13: =IF(OR($CZ13<=0,(DL$9-$A13)>($E13*365)),0,IF($A13<=DL$9,$F13/12)) -> 75 | DM13: =SUM(DA13:DL13) -> 900 | DN13: =IF(AND($DL$9>$A13,$DM13<>0),$D13-$S13-$AG13-$AU13-$BI13-$BW13-$CK$10-$CY13-$DM13,0) -> 3316.6667 | DO13: =IF(OR($DN13<=0,(DO$9-$A13)>($E13*365)),0,IF($A13<=DO$9,$F13/12)) -> 75 | DP13: =IF(OR($DN13<=0,(DP$9-$A13)>($E13*365)),0,IF($A13<=DP$9,$F13/12)) -> 75 | DQ13: =IF(OR($DN13<=0,(DQ$9-$A13)>($E13*365)),0,IF($A13<=DQ$9,$F13/12)) -> 75 | DR13: =IF(OR($DN13<=0,(DR$9-$A13)>($E13*365)),0,IF($A13<=DR$9,$F13/12)) -> 75 | DS13: =IF(OR($DN13<=0,(DS$9-$A13)>($E13*365)),0,IF($A13<=DS$9,$F13/12)) -> 75 | DT13: =IF(OR($DN13<=0,(DT$9-$A13)>($E13*365)),0,IF($A13<=DT$9,$F13/12)) -> 75 | DU13: =IF(OR($DN13<=0,(DU$9-$A13)>($E13*365)),0,IF($A13<=DU$9,$F13/12)) -> 75 | DV13: =IF(OR($DN13<=0,(DV$9-$A13)>($E13*365)),0,IF($A13<=DV$9,$F13/12)) -> 75 | ... DZ13: =IF(OR($DN13<=0,(DZ$9-$A13)>($E13*365)),0,IF($A13<=DZ$9,$F13/12)) -> 75 | EA13: =SUM(DO13:DZ13) -> 900 | EB13: =IF(AND($DZ$9>$A13,$EA13<>0),$D13-$S13-$AG13-$AU13-$BI13-$BW13--CY13-$DM13-$CK13-$EA13,0) -> 4650
A14: 42864 | B14: Matériel Roulant | C14: poite finition | D14: 5300 | E14: 1 | F14: =D14/E14 -> 5300 | G14: =IF(OR($F14<=0,(G$9-$A14)>(365*$E14)),0,IF($A14<=G$9,$F14/12,0)) -> 0 | H14: =IF(OR($F14<=0,(H$9-$A14)>(365*$E14)),0,IF($A14<=H$9,$F14/12,0)) -> 0 | I14: =IF(OR($F14<=0,(I$9-$A14)>(365*$E14)),0,IF($A14<=I$9,$F14/12,0)) -> 0 | J14: =IF(OR($F14<=0,(J$9-$A14)>(365*$E14)),0,IF($A14<=J$9,$F14/12,0)) -> 0 | K14: =IF(OR($F14<=0,(K$9-$A14)>(365*$E14)),0,IF($A14<=K$9,$F14/12,0)) -> 0 | L14: =IF(OR($F14<=0,(L$9-$A14)>(365*$E14)),0,IF($A14<=L$9,$F14/12,0)) -> 0 | M14: =IF(OR($F14<=0,(M$9-$A14)>(365*$E14)),0,IF($A14<=M$9,$F14/12,0)) -> 0 | N14: =IF(OR($F14<=0,(N$9-$A14)>(365*$E14)),0,IF($A14<=N$9,$F14/12,0)) -> 0 | ... R14: =IF(OR($F14<=0,(R$9-$A14)>(365*$E14)),0,IF($A14<=R$9,$F14/12,0)) -> 0 | S14: =SUM(G14:R14) -> 0 | T14: =IF(AND($R$9>A14,$S14<>0),$D14-$S14,0) -> 0 | U14: =IF(OR($F14<=0,(U$9-$A14)>(365*$E14)),0,IF($A14<=U$9,$F14/12,0)) -> 0 | V14: =IF(OR($F14<=0,(V$9-$A14)>(365*$E14)),0,IF($A14<=V$9,$F14/12,0)) -> 0 | W14: =IF(OR($F14<=0,(W$9-$A14)>(365*$E14)),0,IF($A14<=W$9,$F14/12,0)) -> 0 | X14: =IF(OR($F14<=0,(X$9-$A14)>(365*$E14)),0,IF($A14<=X$9,$F14/12,0)) -> 0 | Y14: =IF(OR($F14<=0,(Y$9-$A14)>(365*$E14)),0,IF($A14<=Y$9,$F14/12,0)) -> 0 | Z14: =IF(OR($F14<=0,(Z$9-$A14)>(365*$E14)),0,IF($A14<=Z$9,$F14/12,0)) -> 0 | AA14: =IF(OR($F14<=0,(AA$9-$A14)>(365*$E14)),0,IF($A14<=AA$9,$F14/12,0)) -> 0 | AB14: =IF(OR($F14<=0,(AB$9-$A14)>(365*$E14)),0,IF($A14<=AB$9,$F14/12,0)) -> 0 | ... AF14: =IF(OR($F14<=0,(AF$9-$A14)>(365*$E14)),0,IF($A14<=AF$9,$F14/12,0)) -> 0 | AG14: =SUM(U14:AF14) -> 0 | AH14: =IF(AND($AF$9>$A14,$AG14<>0),$D14-$S14-$AG14,0) -> 0 | AI14: =IF(OR($F14<=0,(AI$9-$A14)>(365*$E14)),0,IF($A14<=AI$9,$F14/12,0)) -> 0 | AJ14: =IF(OR($F14<=0,(AJ$9-$A14)>(365*$E14)),0,IF($A14<=AJ$9,$F14/12,0)) -> 0 | AK14: =IF(OR($F14<=0,(AK$9-$A14)>(365*$E14)),0,IF($A14<=AK$9,$F14/12,0)) -> 0 | AL14: =IF(OR($F14<=0,(AL$9-$A14)>(365*$E14)),0,IF($A14<=AL$9,$F14/12,0)) -> 0 | AM14: =IF(OR($F14<=0,(AM$9-$A14)>(365*$E14)),0,IF($A14<=AM$9,$F14/12,0)) -> 0 | AN14: =IF(OR($F14<=0,(AN$9-$A14)>(365*$E14)),0,IF($A14<=AN$9,$F14/12,0)) -> 0 | AO14: =IF(OR($F14<=0,(AO$9-$A14)>(365*$E14)),0,IF($A14<=AO$9,$F14/12,0)) -> 441.66667 | AP14: =IF(OR($F14<=0,(AP$9-$A14)>(365*$E14)),0,IF($A14<=AP$9,$F14/12,0)) -> 441.66667 | ... AT14: =IF(OR($F14<=0,(AT$9-$A14)>(365*$E14)),0,IF($A14<=AT$9,$F14/12,0)) -> 441.66667 | AU14: =SUM(AI14:AT14) -> 2650 | AV14: =IF(AND($AT$9>$A14,$AU14<>0),$D14-$S14-$AG14-$AU14,0) -> 2650 | AW14: =IF(OR($F14<=0,(AW$9-$A14)>(365*$E14)),0,IF($A14<=AW$9,$F14/12,0)) -> 441.66667 | AX14: =IF(OR($F14<=0,(AX$9-$A14)>(365*$E14)),0,IF($A14<=AX$9,$F14/12,0)) -> 441.66667 | AY14: =IF(OR($F14<=0,(AY$9-$A14)>(365*$E14)),0,IF($A14<=AY$9,$F14/12,0)) -> 441.66667 | AZ14: =IF(OR($F14<=0,(AZ$9-$A14)>(365*$E14)),0,IF($A14<=AZ$9,$F14/12,0)) -> 441.66667 | BA14: =IF(OR($F14<=0,(BA$9-$A14)>(365*$E14)),0,IF($A14<=BA$9,$F14/12,0)) -> 441.66667 | BB14: =IF(OR($F14<=0,(BB$9-$A14)>(365*$E14)),0,IF($A14<=BB$9,$F14/12,0)) -> 441.66667 | BC14: =IF(OR($F14<=0,(BC$9-$A14)>(365*$E14)),0,IF($A14<=BC$9,$F14/12,0)) -> 0 | BD14: =IF(OR($F14<=0,(BD$9-$A14)>(365*$E14)),0,IF($A14<=BD$9,$F14/12,0)) -> 0 | ... BH14: =IF(OR($F14<=0,(BH$9-$A14)>(365*$E14)),0,IF($A14<=BH$9,$F14/12,0)) -> 0 | BI14: =SUM(AW14:BH14) -> 2650 | BJ14: =IF(AND($BH$9>$A14,$BI14<>0),$D14-$S14-$AG14-$AU14-$BI14,0) -> 0 | BK14: =IF(OR($BJ14<=0,(BK$9-$A14)>($E14*365)),0,IF($A14<=BK$9,$F14/12)) -> 0 | BL14: =IF(OR($BJ14<=0,(BL$9-$A14)>($E14*365)),0,IF($A14<=BL$9,$F14/12)) -> 0 | BM14: =IF(OR($BJ14<=0,(BM$9-$A14)>($E14*365)),0,IF($A14<=BM$9,$F14/12)) -> 0 | BN14: =IF(OR($BJ14<=0,(BN$9-$A14)>($E14*365)),0,IF($A14<=BN$9,$F14/12)) -> 0 | BO14: =IF(OR($BJ14<=0,(BO$9-$A14)>($E14*365)),0,IF($A14<=BO$9,$F14/12)) -> 0 | BP14: =IF(OR($BJ14<=0,(BP$9-$A14)>($E14*365)),0,IF($A14<=BP$9,$F14/12)) -> 0 | BQ14: =IF(OR($BJ14<=0,(BQ$9-$A14)>($E14*365)),0,IF($A14<=BQ$9,$F14/12)) -> 0 | BR14: =IF(OR($BJ14<=0,(BR$9-$A14)>($E14*365)),0,IF($A14<=BR$9,$F14/12)) -> 0 | ... BV14: =IF(OR($BJ14<=0,(BV$9-$A14)>($E14*365)),0,IF($A14<=BV$9,$F14/12)) -> 0 | BW14: =SUM(BK14:BV14) -> 0 | BX14: =IF(AND($BV$9>$A14,$BW14<>0),$D14-$S14-$AG14-$AU14-$BI14-$BW14,0) -> 0 | BY14: =IF(OR($BX14<=0,(BY$9-$A14)>($E14*365)),0,IF($A14<=BY$9,$F14/12)) -> 0 | BZ14: =IF(OR($BX14<=0,(BZ$9-$A14)>($E14*365)),0,IF($A14<=BZ$9,$F14/12)) -> 0 | CA14: =IF(OR($BX14<=0,(CA$9-$A14)>($E14*365)),0,IF($A14<=CA$9,$F14/12)) -> 0 | CB14: =IF(OR($BX14<=0,(CB$9-$A14)>($E14*365)),0,IF($A14<=CB$9,$F14/12)) -> 0 | CC14: =IF(OR($BX14<=0,(CC$9-$A14)>($E14*365)),0,IF($A14<=CC$9,$F14/12)) -> 0 | CD14: =IF(OR($BX14<=0,(CD$9-$A14)>($E14*365)),0,IF($A14<=CD$9,$F14/12)) -> 0 | CE14: =IF(OR($BX14<=0,(CE$9-$A14)>($E14*365)),0,IF($A14<=CE$9,$F14/12)) -> 0 | CF14: =IF(OR($BX14<=0,(CF$9-$A14)>($E14*365)),0,IF($A14<=CF$9,$F14/12)) -> 0 | ... CJ14: =IF(OR($BX14<=0,(CJ$9-$A14)>($E14*365)),0,IF($A14<=CJ$9,$F14/12)) -> 0 | CK14: =SUM(BY14:CJ14) -> 0 | CL14: =IF(AND($CJ$9>$A14,$CK14<>0),$D14-$S14-$AG14-$AU14-$BI14-$BW14-$CK$10,0) -> 0 | CM14: =IF(OR($CL14<=0,(CM$9-$A14)>($E14*365)),0,IF($A14<=CM$9,$F14/12)) -> 0 | CN14: =IF(OR($CL14<=0,(CN$9-$A14)>($E14*365)),0,IF($A14<=CN$9,$F14/12)) -> 0 | CO14: =IF(OR($CL14<=0,(CO$9-$A14)>($E14*365)),0,IF($A14<=CO$9,$F14/12)) -> 0 | CP14: =IF(OR($CL14<=0,(CP$9-$A14)>($E14*365)),0,IF($A14<=CP$9,$F14/12)) -> 0 | CQ14: =IF(OR($CL14<=0,(CQ$9-$A14)>($E14*365)),0,IF($A14<=CQ$9,$F14/12)) -> 0 | CR14: =IF(OR($CL14<=0,(CR$9-$A14)>($E14*365)),0,IF($A14<=CR$9,$F14/12)) -> 0 | CS14: =IF(OR($CL14<=0,(CS$9-$A14)>($E14*365)),0,IF($A14<=CS$9,$F14/12)) -> 0 | CT14: =IF(OR($CL14<=0,(CT$9-$A14)>($E14*365)),0,IF($A14<=CT$9,$F14/12)) -> 0 | ... CX14: =IF(OR($CL14<=0,(CX$9-$A14)>($E14*365)),0,IF($A14<=CX$9,$F14/12)) -> 0 | CY14: =SUM(CM14:CX14) -> 0 | CZ14: =IF(AND($CX$9>$A14,$CY14<>0),$D14-$S14-$AG14-$AU14-$BI14-$BW14-$CK14-$CY14,0) -> 0 | DA14: =IF(OR($CZ14<=0,(DA$9-$A14)>($E14*365)),0,IF($A14<=DA$9,$F14/12)) -> 0 | DB14: =IF(OR($CZ14<=0,(DB$9-$A14)>($E14*365)),0,IF($A14<=DB$9,$F14/12)) -> 0 | DC14: =IF(OR($CZ14<=0,(DC$9-$A14)>($E14*365)),0,IF($A14<=DC$9,$F14/12)) -> 0 | DD14: =IF(OR($CZ14<=0,(DD$9-$A14)>($E14*365)),0,IF($A14<=DD$9,$F14/12)) -> 0 | DE14: =IF(OR($CZ14<=0,(DE$9-$A14)>($E14*365)),0,IF($A14<=DE$9,$F14/12)) -> 0 | DF14: =IF(OR($CZ14<=0,(DF$9-$A14)>($E14*365)),0,IF($A14<=DF$9,$F14/12)) -> 0 | DG14: =IF(OR($CZ14<=0,(DG$9-$A14)>($E14*365)),0,IF($A14<=DG$9,$F14/12)) -> 0 | DH14: =IF(OR($CZ14<=0,(DH$9-$A14)>($E14*365)),0,IF($A14<=DH$9,$F14/12)) -> 0 | ... DL14: =IF(OR($CZ14<=0,(DL$9-$A14)>($E14*365)),0,IF($A14<=DL$9,$F14/12)) -> 0 | DM14: =SUM(DA14:DL14) -> 0 | DN14: =IF(AND($DL$9>$A14,$DM14<>0),$D14-$S14-$AG14-$AU14-$BI14-$BW14-$CK$10-$CY14-$DM14,0) -> 0 | DO14: =IF(OR($DN14<=0,(DO$9-$A14)>($E14*365)),0,IF($A14<=DO$9,$F14/12)) -> 0 | DP14: =IF(OR($DN14<=0,(DP$9-$A14)>($E14*365)),0,IF($A14<=DP$9,$F14/12)) -> 0 | DQ14: =IF(OR($DN14<=0,(DQ$9-$A14)>($E14*365)),0,IF($A14<=DQ$9,$F14/12)) -> 0 | DR14: =IF(OR($DN14<=0,(DR$9-$A14)>($E14*365)),0,IF($A14<=DR$9,$F14/12)) -> 0 | DS14: =IF(OR($DN14<=0,(DS$9-$A14)>($E14*365)),0,IF($A14<=DS$9,$F14/12)) -> 0 | DT14: =IF(OR($DN14<=0,(DT$9-$A14)>($E14*365)),0,IF($A14<=DT$9,$F14/12)) -> 0 | DU14: =IF(OR($DN14<=0,(DU$9-$A14)>($E14*365)),0,IF($A14<=DU$9,$F14/12)) -> 0 | DV14: =IF(OR($DN14<=0,(DV$9-$A14)>($E14*365)),0,IF($A14<=DV$9,$F14/12)) -> 0 | ... DZ14: =IF(OR($DN14<=0,(DZ$9-$A14)>($E14*365)),0,IF($A14<=DZ$9,$F14/12)) -> 0 | EA14: =SUM(DO14:DZ14) -> 0 | EB14: =IF(AND($DZ$9>$A14,$EA14<>0),$D14-$S14-$AG14-$AU14-$BI14-$BW14--CY14-$DM14-$CK14-$EA14,0) -> 0
A15: 42865 | B15: Matériels | C15: pière a mriser | D15: 2800 | E15: 5 | F15: =D15/E15 -> 560 | G15: =IF(OR($F15<=0,(G$9-$A15)>(365*$E15)),0,IF($A15<=G$9,$F15/12,0)) -> 0 | H15: =IF(OR($F15<=0,(H$9-$A15)>(365*$E15)),0,IF($A15<=H$9,$F15/12,0)) -> 0 | I15: =IF(OR($F15<=0,(I$9-$A15)>(365*$E15)),0,IF($A15<=I$9,$F15/12,0)) -> 0 | J15: =IF(OR($F15<=0,(J$9-$A15)>(365*$E15)),0,IF($A15<=J$9,$F15/12,0)) -> 0 | K15: =IF(OR($F15<=0,(K$9-$A15)>(365*$E15)),0,IF($A15<=K$9,$F15/12,0)) -> 0 | L15: =IF(OR($F15<=0,(L$9-$A15)>(365*$E15)),0,IF($A15<=L$9,$F15/12,0)) -> 0 | M15: =IF(OR($F15<=0,(M$9-$A15)>(365*$E15)),0,IF($A15<=M$9,$F15/12,0)) -> 0 | N15: =IF(OR($F15<=0,(N$9-$A15)>(365*$E15)),0,IF($A15<=N$9,$F15/12,0)) -> 0 | ... R15: =IF(OR($F15<=0,(R$9-$A15)>(365*$E15)),0,IF($A15<=R$9,$F15/12,0)) -> 0 | S15: =SUM(G15:R15) -> 0 | T15: =IF(AND($R$9>A15,$S15<>0),$D15-$S15,0) -> 0 | U15: =IF(OR($F15<=0,(U$9-$A15)>(365*$E15)),0,IF($A15<=U$9,$F15/12,0)) -> 0 | V15: =IF(OR($F15<=0,(V$9-$A15)>(365*$E15)),0,IF($A15<=V$9,$F15/12,0)) -> 0 | W15: =IF(OR($F15<=0,(W$9-$A15)>(365*$E15)),0,IF($A15<=W$9,$F15/12,0)) -> 0 | X15: =IF(OR($F15<=0,(X$9-$A15)>(365*$E15)),0,IF($A15<=X$9,$F15/12,0)) -> 0 | Y15: =IF(OR($F15<=0,(Y$9-$A15)>(365*$E15)),0,IF($A15<=Y$9,$F15/12,0)) -> 0 | Z15: =IF(OR($F15<=0,(Z$9-$A15)>(365*$E15)),0,IF($A15<=Z$9,$F15/12,0)) -> 0 | AA15: =IF(OR($F15<=0,(AA$9-$A15)>(365*$E15)),0,IF($A15<=AA$9,$F15/12,0)) -> 0 | AB15: =IF(OR($F15<=0,(AB$9-$A15)>(365*$E15)),0,IF($A15<=AB$9,$F15/12,0)) -> 0 | ... AF15: =IF(OR($F15<=0,(AF$9-$A15)>(365*$E15)),0,IF($A15<=AF$9,$F15/12,0)) -> 0 | AG15: =SUM(U15:AF15) -> 0 | AH15: =IF(AND($AF$9>$A15,$AG15<>0),$D15-$S15-$AG15,0) -> 0 | AI15: =IF(OR($F15<=0,(AI$9-$A15)>(365*$E15)),0,IF($A15<=AI$9,$F15/12,0)) -> 0 | AJ15: =IF(OR($F15<=0,(AJ$9-$A15)>(365*$E15)),0,IF($A15<=AJ$9,$F15/12,0)) -> 0 | AK15: =IF(OR($F15<=0,(AK$9-$A15)>(365*$E15)),0,IF($A15<=AK$9,$F15/12,0)) -> 0 | AL15: =IF(OR($F15<=0,(AL$9-$A15)>(365*$E15)),0,IF($A15<=AL$9,$F15/12,0)) -> 0 | AM15: =IF(OR($F15<=0,(AM$9-$A15)>(365*$E15)),0,IF($A15<=AM$9,$F15/12,0)) -> 0 | AN15: =IF(OR($F15<=0,(AN$9-$A15)>(365*$E15)),0,IF($A15<=AN$9,$F15/12,0)) -> 0 | AO15: =IF(OR($F15<=0,(AO$9-$A15)>(365*$E15)),0,IF($A15<=AO$9,$F15/12,0)) -> 46.666667 | AP15: =IF(OR($F15<=0,(AP$9-$A15)>(365*$E15)),0,IF($A15<=AP$9,$F15/12,0)) -> 46.666667 | ... AT15: =IF(OR($F15<=0,(AT$9-$A15)>(365*$E15)),0,IF($A15<=AT$9,$F15/12,0)) -> 46.666667 | AU15: =SUM(AI15:AT15) -> 280 | AV15: =IF(AND($AT$9>$A15,$AU15<>0),$D15-$S15-$AG15-$AU15,0) -> 2520 | AW15: =IF(OR($F15<=0,(AW$9-$A15)>(365*$E15)),0,IF($A15<=AW$9,$F15/12,0)) -> 46.666667 | AX15: =IF(OR($F15<=0,(AX$9-$A15)>(365*$E15)),0,IF($A15<=AX$9,$F15/12,0)) -> 46.666667 | AY15: =IF(OR($F15<=0,(AY$9-$A15)>(365*$E15)),0,IF($A15<=AY$9,$F15/12,0)) -> 46.666667 | AZ15: =IF(OR($F15<=0,(AZ$9-$A15)>(365*$E15)),0,IF($A15<=AZ$9,$F15/12,0)) -> 46.666667 | BA15: =IF(OR($F15<=0,(BA$9-$A15)>(365*$E15)),0,IF($A15<=BA$9,$F15/12,0)) -> 46.666667 | BB15: =IF(OR($F15<=0,(BB$9-$A15)>(365*$E15)),0,IF($A15<=BB$9,$F15/12,0)) -> 46.666667 | BC15: =IF(OR($F15<=0,(BC$9-$A15)>(365*$E15)),0,IF($A15<=BC$9,$F15/12,0)) -> 46.666667 | BD15: =IF(OR($F15<=0,(BD$9-$A15)>(365*$E15)),0,IF($A15<=BD$9,$F15/12,0)) -> 46.666667 | ... BH15: =IF(OR($F15<=0,(BH$9-$A15)>(365*$E15)),0,IF($A15<=BH$9,$F15/12,0)) -> 46.666667 | BI15: =SUM(AW15:BH15) -> 560 | BJ15: =IF(AND($BH$9>$A15,$BI15<>0),$D15-$S15-$AG15-$AU15-$BI15,0) -> 1960 | BK15: =IF(OR($BJ15<=0,(BK$9-$A15)>($E15*365)),0,IF($A15<=BK$9,$F15/12)) -> 46.666667 | BL15: =IF(OR($BJ15<=0,(BL$9-$A15)>($E15*365)),0,IF($A15<=BL$9,$F15/12)) -> 46.666667 | BM15: =IF(OR($BJ15<=0,(BM$9-$A15)>($E15*365)),0,IF($A15<=BM$9,$F15/12)) -> 46.666667 | BN15: =IF(OR($BJ15<=0,(BN$9-$A15)>($E15*365)),0,IF($A15<=BN$9,$F15/12)) -> 46.666667 | BO15: =IF(OR($BJ15<=0,(BO$9-$A15)>($E15*365)),0,IF($A15<=BO$9,$F15/12)) -> 46.666667 | BP15: =IF(OR($BJ15<=0,(BP$9-$A15)>($E15*365)),0,IF($A15<=BP$9,$F15/12)) -> 46.666667 | BQ15: =IF(OR($BJ15<=0,(BQ$9-$A15)>($E15*365)),0,IF($A15<=BQ$9,$F15/12)) -> 46.666667 | BR15: =IF(OR($BJ15<=0,(BR$9-$A15)>($E15*365)),0,IF($A15<=BR$9,$F15/12)) -> 46.666667 | ... BV15: =IF(OR($BJ15<=0,(BV$9-$A15)>($E15*365)),0,IF($A15<=BV$9,$F15/12)) -> 46.666667 | BW15: =SUM(BK15:BV15) -> 560 | BX15: =IF(AND($BV$9>$A15,$BW15<>0),$D15-$S15-$AG15-$AU15-$BI15-$BW15,0) -> 1400 | BY15: =IF(OR($BX15<=0,(BY$9-$A15)>($E15*365)),0,IF($A15<=BY$9,$F15/12)) -> 46.666667 | BZ15: =IF(OR($BX15<=0,(BZ$9-$A15)>($E15*365)),0,IF($A15<=BZ$9,$F15/12)) -> 46.666667 | CA15: =IF(OR($BX15<=0,(CA$9-$A15)>($E15*365)),0,IF($A15<=CA$9,$F15/12)) -> 46.666667 | CB15: =IF(OR($BX15<=0,(CB$9-$A15)>($E15*365)),0,IF($A15<=CB$9,$F15/12)) -> 46.666667 | CC15: =IF(OR($BX15<=0,(CC$9-$A15)>($E15*365)),0,IF($A15<=CC$9,$F15/12)) -> 46.666667 | CD15: =IF(OR($BX15<=0,(CD$9-$A15)>($E15*365)),0,IF($A15<=CD$9,$F15/12)) -> 46.666667 | CE15: =IF(OR($BX15<=0,(CE$9-$A15)>($E15*365)),0,IF($A15<=CE$9,$F15/12)) -> 46.666667 | CF15: =IF(OR($BX15<=0,(CF$9-$A15)>($E15*365)),0,IF($A15<=CF$9,$F15/12)) -> 46.666667 | ... CJ15: =IF(OR($BX15<=0,(CJ$9-$A15)>($E15*365)),0,IF($A15<=CJ$9,$F15/12)) -> 46.666667 | CK15: =SUM(BY15:CJ15) -> 560 | CL15: =IF(AND($CJ$9>$A15,$CK15<>0),$D15-$S15-$AG15-$AU15-$BI15-$BW15-$CK$10,0) -> 66.666667 | CM15: =IF(OR($CL15<=0,(CM$9-$A15)>($E15*365)),0,IF($A15<=CM$9,$F15/12)) -> 46.666667 | CN15: =IF(OR($CL15<=0,(CN$9-$A15)>($E15*365)),0,IF($A15<=CN$9,$F15/12)) -> 46.666667 | CO15: =IF(OR($CL15<=0,(CO$9-$A15)>($E15*365)),0,IF($A15<=CO$9,$F15/12)) -> 46.666667 | CP15: =IF(OR($CL15<=0,(CP$9-$A15)>($E15*365)),0,IF($A15<=CP$9,$F15/12)) -> 46.666667 | CQ15: =IF(OR($CL15<=0,(CQ$9-$A15)>($E15*365)),0,IF($A15<=CQ$9,$F15/12)) -> 46.666667 | CR15: =IF(OR($CL15<=0,(CR$9-$A15)>($E15*365)),0,IF($A15<=CR$9,$F15/12)) -> 46.666667 | CS15: =IF(OR($CL15<=0,(CS$9-$A15)>($E15*365)),0,IF($A15<=CS$9,$F15/12)) -> 46.666667 | CT15: =IF(OR($CL15<=0,(CT$9-$A15)>($E15*365)),0,IF($A15<=CT$9,$F15/12)) -> 46.666667 | ... CX15: =IF(OR($CL15<=0,(CX$9-$A15)>($E15*365)),0,IF($A15<=CX$9,$F15/12)) -> 46.666667 | CY15: =SUM(CM15:CX15) -> 560 | CZ15: =IF(AND($CX$9>$A15,$CY15<>0),$D15-$S15-$AG15-$AU15-$BI15-$BW15-$CK15-$CY15,0) -> 280 | DA15: =IF(OR($CZ15<=0,(DA$9-$A15)>($E15*365)),0,IF($A15<=DA$9,$F15/12)) -> 46.666667 | DB15: =IF(OR($CZ15<=0,(DB$9-$A15)>($E15*365)),0,IF($A15<=DB$9,$F15/12)) -> 46.666667 | DC15: =IF(OR($CZ15<=0,(DC$9-$A15)>($E15*365)),0,IF($A15<=DC$9,$F15/12)) -> 46.666667 | DD15: =IF(OR($CZ15<=0,(DD$9-$A15)>($E15*365)),0,IF($A15<=DD$9,$F15/12)) -> 46.666667 | DE15: =IF(OR($CZ15<=0,(DE$9-$A15)>($E15*365)),0,IF($A15<=DE$9,$F15/12)) -> 46.666667 | DF15: =IF(OR($CZ15<=0,(DF$9-$A15)>($E15*365)),0,IF($A15<=DF$9,$F15/12)) -> 46.666667 | DG15: =IF(OR($CZ15<=0,(DG$9-$A15)>($E15*365)),0,IF($A15<=DG$9,$F15/12)) -> 0 | DH15: =IF(OR($CZ15<=0,(DH$9-$A15)>($E15*365)),0,IF($A15<=DH$9,$F15/12)) -> 0 | ... DL15: =IF(OR($CZ15<=0,(DL$9-$A15)>($E15*365)),0,IF($A15<=DL$9,$F15/12)) -> 0 | DM15: =SUM(DA15:DL15) -> 280 | DN15: =IF(AND($DL$9>$A15,$DM15<>0),$D15-$S15-$AG15-$AU15-$BI15-$BW15-$CK$10-$CY15-$DM15,0) -> -773.33333 | DO15: =IF(OR($DN15<=0,(DO$9-$A15)>($E15*365)),0,IF($A15<=DO$9,$F15/12)) -> 0 | DP15: =IF(OR($DN15<=0,(DP$9-$A15)>($E15*365)),0,IF($A15<=DP$9,$F15/12)) -> 0 | DQ15: =IF(OR($DN15<=0,(DQ$9-$A15)>($E15*365)),0,IF($A15<=DQ$9,$F15/12)) -> 0 | DR15: =IF(OR($DN15<=0,(DR$9-$A15)>($E15*365)),0,IF($A15<=DR$9,$F15/12)) -> 0 | DS15: =IF(OR($DN15<=0,(DS$9-$A15)>($E15*365)),0,IF($A15<=DS$9,$F15/12)) -> 0 | DT15: =IF(OR($DN15<=0,(DT$9-$A15)>($E15*365)),0,IF($A15<=DT$9,$F15/12)) -> 0 | DU15: =IF(OR($DN15<=0,(DU$9-$A15)>($E15*365)),0,IF($A15<=DU$9,$F15/12)) -> 0 | DV15: =IF(OR($DN15<=0,(DV$9-$A15)>($E15*365)),0,IF($A15<=DV$9,$F15/12)) -> 0 | ... DZ15: =IF(OR($DN15<=0,(DZ$9-$A15)>($E15*365)),0,IF($A15<=DZ$9,$F15/12)) -> 0 | EA15: =SUM(DO15:DZ15) -> 0 | EB15: =IF(AND($DZ$9>$A15,$EA15<>0),$D15-$S15-$AG15-$AU15-$BI15-$BW15--CY15-$DM15-$CK15-$EA15,0) -> 0
A16: 42866 | B16: Matériel Roulant | C16: pinces | D16: 2400 | E16: 3 | F16: =D16/E16 -> 800 | G16: =IF(OR($F16<=0,(G$9-$A16)>(365*$E16)),0,IF($A16<=G$9,$F16/12,0)) -> 0 | H16: =IF(OR($F16<=0,(H$9-$A16)>(365*$E16)),0,IF($A16<=H$9,$F16/12,0)) -> 0 | I16: =IF(OR($F16<=0,(I$9-$A16)>(365*$E16)),0,IF($A16<=I$9,$F16/12,0)) -> 0 | J16: =IF(OR($F16<=0,(J$9-$A16)>(365*$E16)),0,IF($A16<=J$9,$F16/12,0)) -> 0 | K16: =IF(OR($F16<=0,(K$9-$A16)>(365*$E16)),0,IF($A16<=K$9,$F16/12,0)) -> 0 | L16: =IF(OR($F16<=0,(L$9-$A16)>(365*$E16)),0,IF($A16<=L$9,$F16/12,0)) -> 0 | M16: =IF(OR($F16<=0,(M$9-$A16)>(365*$E16)),0,IF($A16<=M$9,$F16/12,0)) -> 0 | N16: =IF(OR($F16<=0,(N$9-$A16)>(365*$E16)),0,IF($A16<=N$9,$F16/12,0)) -> 0 | ... R16: =IF(OR($F16<=0,(R$9-$A16)>(365*$E16)),0,IF($A16<=R$9,$F16/12,0)) -> 0 | S16: =SUM(G16:R16) -> 0 | T16: =IF(AND($R$9>A16,$S16<>0),$D16-$S16,0) -> 0 | U16: =IF(OR($F16<=0,(U$9-$A16)>(365*$E16)),0,IF($A16<=U$9,$F16/12,0)) -> 0 | V16: =IF(OR($F16<=0,(V$9-$A16)>(365*$E16)),0,IF($A16<=V$9,$F16/12,0)) -> 0 | W16: =IF(OR($F16<=0,(W$9-$A16)>(365*$E16)),0,IF($A16<=W$9,$F16/12,0)) -> 0 | X16: =IF(OR($F16<=0,(X$9-$A16)>(365*$E16)),0,IF($A16<=X$9,$F16/12,0)) -> 0 | Y16: =IF(OR($F16<=0,(Y$9-$A16)>(365*$E16)),0,IF($A16<=Y$9,$F16/12,0)) -> 0 | Z16: =IF(OR($F16<=0,(Z$9-$A16)>(365*$E16)),0,IF($A16<=Z$9,$F16/12,0)) -> 0 | AA16: =IF(OR($F16<=0,(AA$9-$A16)>(365*$E16)),0,IF($A16<=AA$9,$F16/12,0)) -> 0 | AB16: =IF(OR($F16<=0,(AB$9-$A16)>(365*$E16)),0,IF($A16<=AB$9,$F16/12,0)) -> 0 | ... AF16: =IF(OR($F16<=0,(AF$9-$A16)>(365*$E16)),0,IF($A16<=AF$9,$F16/12,0)) -> 0 | AG16: =SUM(U16:AF16) -> 0 | AH16: =IF(AND($AF$9>$A16,$AG16<>0),$D16-$S16-$AG16,0) -> 0 | AI16: =IF(OR($F16<=0,(AI$9-$A16)>(365*$E16)),0,IF($A16<=AI$9,$F16/12,0)) -> 0 | AJ16: =IF(OR($F16<=0,(AJ$9-$A16)>(365*$E16)),0,IF($A16<=AJ$9,$F16/12,0)) -> 0 | AK16: =IF(OR($F16<=0,(AK$9-$A16)>(365*$E16)),0,IF($A16<=AK$9,$F16/12,0)) -> 0 | AL16: =IF(OR($F16<=0,(AL$9-$A16)>(365*$E16)),0,IF($A16<=AL$9,$F16/12,0)) -> 0 | AM16: =IF(OR($F16<=0,(AM$9-$A16)>(365*$E16)),0,IF($A16<=AM$9,$F16/12,0)) -> 0 | AN16: =IF(OR($F16<=0,(AN$9-$A16)>(365*$E16)),0,IF($A16<=AN$9,$F16/12,0)) -> 0 | AO16: =IF(OR($F16<=0,(AO$9-$A16)>(365*$E16)),0,IF($A16<=AO$9,$F16/12,0)) -> 66.666667 | AP16: =IF(OR($F16<=0,(AP$9-$A16)>(365*$E16)),0,IF($A16<=AP$9,$F16/12,0)) -> 66.666667 | ... AT16: =IF(OR($F16<=0,(AT$9-$A16)>(365*$E16)),0,IF($A16<=AT$9,$F16/12,0)) -> 66.666667 | AU16: =SUM(AI16:AT16) -> 400 | AV16: =IF(AND($AT$9>$A16,$AU16<>0),$D16-$S16-$AG16-$AU16,0) -> 2000 | AW16: =IF(OR($F16<=0,(AW$9-$A16)>(365*$E16)),0,IF($A16<=AW$9,$F16/12,0)) -> 66.666667 | AX16: =IF(OR($F16<=0,(AX$9-$A16)>(365*$E16)),0,IF($A16<=AX$9,$F16/12,0)) -> 66.666667 | AY16: =IF(OR($F16<=0,(AY$9-$A16)>(365*$E16)),0,IF($A16<=AY$9,$F16/12,0)) -> 66.666667 | AZ16: =IF(OR($F16<=0,(AZ$9-$A16)>(365*$E16)),0,IF($A16<=AZ$9,$F16/12,0)) -> 66.666667 | BA16: =IF(OR($F16<=0,(BA$9-$A16)>(365*$E16)),0,IF($A16<=BA$9,$F16/12,0)) -> 66.666667 | BB16: =IF(OR($F16<=0,(BB$9-$A16)>(365*$E16)),0,IF($A16<=BB$9,$F16/12,0)) -> 66.666667 | BC16: =IF(OR($F16<=0,(BC$9-$A16)>(365*$E16)),0,IF($A16<=BC$9,$F16/12,0)) -> 66.666667 | BD16: =IF(OR($F16<=0,(BD$9-$A16)>(365*$E16)),0,IF($A16<=BD$9,$F16/12,0)) -> 66.666667 | ... BH16: =IF(OR($F16<=0,(BH$9-$A16)>(365*$E16)),0,IF($A16<=BH$9,$F16/12,0)) -> 66.666667 | BI16: =SUM(AW16:BH16) -> 800 | BJ16: =IF(AND($BH$9>$A16,$BI16<>0),$D16-$S16-$AG16-$AU16-$BI16,0) -> 1200 | BK16: =IF(OR($BJ16<=0,(BK$9-$A16)>($E16*365)),0,IF($A16<=BK$9,$F16/12)) -> 66.666667 | BL16: =IF(OR($BJ16<=0,(BL$9-$A16)>($E16*365)),0,IF($A16<=BL$9,$F16/12)) -> 66.666667 | BM16: =IF(OR($BJ16<=0,(BM$9-$A16)>($E16*365)),0,IF($A16<=BM$9,$F16/12)) -> 66.666667 | BN16: =IF(OR($BJ16<=0,(BN$9-$A16)>($E16*365)),0,IF($A16<=BN$9,$F16/12)) -> 66.666667 | BO16: =IF(OR($BJ16<=0,(BO$9-$A16)>($E16*365)),0,IF($A16<=BO$9,$F16/12)) -> 66.666667 | BP16: =IF(OR($BJ16<=0,(BP$9-$A16)>($E16*365)),0,IF($A16<=BP$9,$F16/12)) -> 66.666667 | BQ16: =IF(OR($BJ16<=0,(BQ$9-$A16)>($E16*365)),0,IF($A16<=BQ$9,$F16/12)) -> 66.666667 | BR16: =IF(OR($BJ16<=0,(BR$9-$A16)>($E16*365)),0,IF($A16<=BR$9,$F16/12)) -> 66.666667 | ... BV16: =IF(OR($BJ16<=0,(BV$9-$A16)>($E16*365)),0,IF($A16<=BV$9,$F16/12)) -> 66.666667 | BW16: =SUM(BK16:BV16) -> 800 | BX16: =IF(AND($BV$9>$A16,$BW16<>0),$D16-$S16-$AG16-$AU16-$BI16-$BW16,0) -> 400 | BY16: =IF(OR($BX16<=0,(BY$9-$A16)>($E16*365)),0,IF($A16<=BY$9,$F16/12)) -> 66.666667 | BZ16: =IF(OR($BX16<=0,(BZ$9-$A16)>($E16*365)),0,IF($A16<=BZ$9,$F16/12)) -> 66.666667 | CA16: =IF(OR($BX16<=0,(CA$9-$A16)>($E16*365)),0,IF($A16<=CA$9,$F16/12)) -> 66.666667 | CB16: =IF(OR($BX16<=0,(CB$9-$A16)>($E16*365)),0,IF($A16<=CB$9,$F16/12)) -> 66.666667 | CC16: =IF(OR($BX16<=0,(CC$9-$A16)>($E16*365)),0,IF($A16<=CC$9,$F16/12)) -> 66.666667 | CD16: =IF(OR($BX16<=0,(CD$9-$A16)>($E16*365)),0,IF($A16<=CD$9,$F16/12)) -> 66.666667 | CE16: =IF(OR($BX16<=0,(CE$9-$A16)>($E16*365)),0,IF($A16<=CE$9,$F16/12)) -> 0 | CF16: =IF(OR($BX16<=0,(CF$9-$A16)>($E16*365)),0,IF($A16<=CF$9,$F16/12)) -> 0 | ... CJ16: =IF(OR($BX16<=0,(CJ$9-$A16)>($E16*365)),0,IF($A16<=CJ$9,$F16/12)) -> 0 | CK16: =SUM(BY16:CJ16) -> 400 | CL16: =IF(AND($CJ$9>$A16,$CK16<>0),$D16-$S16-$AG16-$AU16-$BI16-$BW16-$CK$10,0) -> -933.33333 | CM16: =IF(OR($CL16<=0,(CM$9-$A16)>($E16*365)),0,IF($A16<=CM$9,$F16/12)) -> 0 | CN16: =IF(OR($CL16<=0,(CN$9-$A16)>($E16*365)),0,IF($A16<=CN$9,$F16/12)) -> 0 | CO16: =IF(OR($CL16<=0,(CO$9-$A16)>($E16*365)),0,IF($A16<=CO$9,$F16/12)) -> 0 | CP16: =IF(OR($CL16<=0,(CP$9-$A16)>($E16*365)),0,IF($A16<=CP$9,$F16/12)) -> 0 | CQ16: =IF(OR($CL16<=0,(CQ$9-$A16)>($E16*365)),0,IF($A16<=CQ$9,$F16/12)) -> 0 | CR16: =IF(OR($CL16<=0,(CR$9-$A16)>($E16*365)),0,IF($A16<=CR$9,$F16/12)) -> 0 | CS16: =IF(OR($CL16<=0,(CS$9-$A16)>($E16*365)),0,IF($A16<=CS$9,$F16/12)) -> 0 | CT16: =IF(OR($CL16<=0,(CT$9-$A16)>($E16*365)),0,IF($A16<=CT$9,$F16/12)) -> 0 | ... CX16: =IF(OR($CL16<=0,(CX$9-$A16)>($E16*365)),0,IF($A16<=CX$9,$F16/12)) -> 0 | CY16: =SUM(CM16:CX16) -> 0 | CZ16: =IF(AND($CX$9>$A16,$CY16<>0),$D16-$S16-$AG16-$AU16-$BI16-$BW16-$CK16-$CY16,0) -> 0 | DA16: =IF(OR($CZ16<=0,(DA$9-$A16)>($E16*365)),0,IF($A16<=DA$9,$F16/12)) -> 0 | DB16: =IF(OR($CZ16<=0,(DB$9-$A16)>($E16*365)),0,IF($A16<=DB$9,$F16/12)) -> 0 | DC16: =IF(OR($CZ16<=0,(DC$9-$A16)>($E16*365)),0,IF($A16<=DC$9,$F16/12)) -> 0 | DD16: =IF(OR($CZ16<=0,(DD$9-$A16)>($E16*365)),0,IF($A16<=DD$9,$F16/12)) -> 0 | DE16: =IF(OR($CZ16<=0,(DE$9-$A16)>($E16*365)),0,IF($A16<=DE$9,$F16/12)) -> 0 | DF16: =IF(OR($CZ16<=0,(DF$9-$A16)>($E16*365)),0,IF($A16<=DF$9,$F16/12)) -> 0 | DG16: =IF(OR($CZ16<=0,(DG$9-$A16)>($E16*365)),0,IF($A16<=DG$9,$F16/12)) -> 0 | DH16: =IF(OR($CZ16<=0,(DH$9-$A16)>($E16*365)),0,IF($A16<=DH$9,$F16/12)) -> 0 | ... DL16: =IF(OR($CZ16<=0,(DL$9-$A16)>($E16*365)),0,IF($A16<=DL$9,$F16/12)) -> 0 | DM16: =SUM(DA16:DL16) -> 0 | DN16: =IF(AND($DL$9>$A16,$DM16<>0),$D16-$S16-$AG16-$AU16-$BI16-$BW16-$CK$10-$CY16-$DM16,0) -> 0 | DO16: =IF(OR($DN16<=0,(DO$9-$A16)>($E16*365)),0,IF($A16<=DO$9,$F16/12)) -> 0 | DP16: =IF(OR($DN16<=0,(DP$9-$A16)>($E16*365)),0,IF($A16<=DP$9,$F16/12)) -> 0 | DQ16: =IF(OR($DN16<=0,(DQ$9-$A16)>($E16*365)),0,IF($A16<=DQ$9,$F16/12)) -> 0 | DR16: =IF(OR($DN16<=0,(DR$9-$A16)>($E16*365)),0,IF($A16<=DR$9,$F16/12)) -> 0 | DS16: =IF(OR($DN16<=0,(DS$9-$A16)>($E16*365)),0,IF($A16<=DS$9,$F16/12)) -> 0 | DT16: =IF(OR($DN16<=0,(DT$9-$A16)>($E16*365)),0,IF($A16<=DT$9,$F16/12)) -> 0 | DU16: =IF(OR($DN16<=0,(DU$9-$A16)>($E16*365)),0,IF($A16<=DU$9,$F16/12)) -> 0 | DV16: =IF(OR($DN16<=0,(DV$9-$A16)>($E16*365)),0,IF($A16<=DV$9,$F16/12)) -> 0 | ... DZ16: =IF(OR($DN16<=0,(DZ$9-$A16)>($E16*365)),0,IF($A16<=DZ$9,$F16/12)) -> 0 | EA16: =SUM(DO16:DZ16) -> 0 | EB16: =IF(AND($DZ$9>$A16,$EA16<>0),$D16-$S16-$AG16-$AU16-$BI16-$BW16--CY16-$DM16-$CK16-$EA16,0) -> 0
A17: 42867 | B17: Matériel Roulant | C17: pinces coupente | D17: 1900 | E17: 3 | F17: =D17/E17 -> 633.33333 | G17: =IF(OR($F17<=0,(G$9-$A17)>(365*$E17)),0,IF($A17<=G$9,$F17/12,0)) -> 0 | H17: =IF(OR($F17<=0,(H$9-$A17)>(365*$E17)),0,IF($A17<=H$9,$F17/12,0)) -> 0 | I17: =IF(OR($F17<=0,(I$9-$A17)>(365*$E17)),0,IF($A17<=I$9,$F17/12,0)) -> 0 | J17: =IF(OR($F17<=0,(J$9-$A17)>(365*$E17)),0,IF($A17<=J$9,$F17/12,0)) -> 0 | K17: =IF(OR($F17<=0,(K$9-$A17)>(365*$E17)),0,IF($A17<=K$9,$F17/12,0)) -> 0 | L17: =IF(OR($F17<=0,(L$9-$A17)>(365*$E17)),0,IF($A17<=L$9,$F17/12,0)) -> 0 | M17: =IF(OR($F17<=0,(M$9-$A17)>(365*$E17)),0,IF($A17<=M$9,$F17/12,0)) -> 0 | N17: =IF(OR($F17<=0,(N$9-$A17)>(365*$E17)),0,IF($A17<=N$9,$F17/12,0)) -> 0 | ... R17: =IF(OR($F17<=0,(R$9-$A17)>(365*$E17)),0,IF($A17<=R$9,$F17/12,0)) -> 0 | S17: =SUM(G17:R17) -> 0 | T17: =IF(AND($R$9>A17,$S17<>0),$D17-$S17,0) -> 0 | U17: =IF(OR($F17<=0,(U$9-$A17)>(365*$E17)),0,IF($A17<=U$9,$F17/12,0)) -> 0 | V17: =IF(OR($F17<=0,(V$9-$A17)>(365*$E17)),0,IF($A17<=V$9,$F17/12,0)) -> 0 | W17: =IF(OR($F17<=0,(W$9-$A17)>(365*$E17)),0,IF($A17<=W$9,$F17/12,0)) -> 0 | X17: =IF(OR($F17<=0,(X$9-$A17)>(365*$E17)),0,IF($A17<=X$9,$F17/12,0)) -> 0 | Y17: =IF(OR($F17<=0,(Y$9-$A17)>(365*$E17)),0,IF($A17<=Y$9,$F17/12,0)) -> 0 | Z17: =IF(OR($F17<=0,(Z$9-$A17)>(365*$E17)),0,IF($A17<=Z$9,$F17/12,0)) -> 0 | AA17: =IF(OR($F17<=0,(AA$9-$A17)>(365*$E17)),0,IF($A17<=AA$9,$F17/12,0)) -> 0 | AB17: =IF(OR($F17<=0,(AB$9-$A17)>(365*$E17)),0,IF($A17<=AB$9,$F17/12,0)) -> 0 | ... AF17: =IF(OR($F17<=0,(AF$9-$A17)>(365*$E17)),0,IF($A17<=AF$9,$F17/12,0)) -> 0 | AG17: =SUM(U17:AF17) -> 0 | AH17: =IF(AND($AF$9>$A17,$AG17<>0),$D17-$S17-$AG17,0) -> 0 | AI17: =IF(OR($F17<=0,(AI$9-$A17)>(365*$E17)),0,IF($A17<=AI$9,$F17/12,0)) -> 0 | AJ17: =IF(OR($F17<=0,(AJ$9-$A17)>(365*$E17)),0,IF($A17<=AJ$9,$F17/12,0)) -> 0 | AK17: =IF(OR($F17<=0,(AK$9-$A17)>(365*$E17)),0,IF($A17<=AK$9,$F17/12,0)) -> 0 | AL17: =IF(OR($F17<=0,(AL$9-$A17)>(365*$E17)),0,IF($A17<=AL$9,$F17/12,0)) -> 0 | AM17: =IF(OR($F17<=0,(AM$9-$A17)>(365*$E17)),0,IF($A17<=AM$9,$F17/12,0)) -> 0 | AN17: =IF(OR($F17<=0,(AN$9-$A17)>(365*$E17)),0,IF($A17<=AN$9,$F17/12,0)) -> 0 | AO17: =IF(OR($F17<=0,(AO$9-$A17)>(365*$E17)),0,IF($A17<=AO$9,$F17/12,0)) -> 52.777778 | AP17: =IF(OR($F17<=0,(AP$9-$A17)>(365*$E17)),0,IF($A17<=AP$9,$F17/12,0)) -> 52.777778 | ... AT17: =IF(OR($F17<=0,(AT$9-$A17)>(365*$E17)),0,IF($A17<=AT$9,$F17/12,0)) -> 52.777778 | AU17: =SUM(AI17:AT17) -> 316.66667 | AV17: =IF(AND($AT$9>$A17,$AU17<>0),$D17-$S17-$AG17-$AU17,0) -> 1583.3333 | AW17: =IF(OR($F17<=0,(AW$9-$A17)>(365*$E17)),0,IF($A17<=AW$9,$F17/12,0)) -> 52.777778 | AX17: =IF(OR($F17<=0,(AX$9-$A17)>(365*$E17)),0,IF($A17<=AX$9,$F17/12,0)) -> 52.777778 | AY17: =IF(OR($F17<=0,(AY$9-$A17)>(365*$E17)),0,IF($A17<=AY$9,$F17/12,0)) -> 52.777778 | AZ17: =IF(OR($F17<=0,(AZ$9-$A17)>(365*$E17)),0,IF($A17<=AZ$9,$F17/12,0)) -> 52.777778 | BA17: =IF(OR($F17<=0,(BA$9-$A17)>(365*$E17)),0,IF($A17<=BA$9,$F17/12,0)) -> 52.777778 | BB17: =IF(OR($F17<=0,(BB$9-$A17)>(365*$E17)),0,IF($A17<=BB$9,$F17/12,0)) -> 52.777778 | BC17: =IF(OR($F17<=0,(BC$9-$A17)>(365*$E17)),0,IF($A17<=BC$9,$F17/12,0)) -> 52.777778 | BD17: =IF(OR($F17<=0,(BD$9-$A17)>(365*$E17)),0,IF($A17<=BD$9,$F17/12,0)) -> 52.777778 | ... BH17: =IF(OR($F17<=0,(BH$9-$A17)>(365*$E17)),0,IF($A17<=BH$9,$F17/12,0)) -> 52.777778 | BI17: =SUM(AW17:BH17) -> 633.33333 | BJ17: =IF(AND($BH$9>$A17,$BI17<>0),$D17-$S17-$AG17-$AU17-$BI17,0) -> 950 | BK17: =IF(OR($BJ17<=0,(BK$9-$A17)>($E17*365)),0,IF($A17<=BK$9,$F17/12)) -> 52.777778 | BL17: =IF(OR($BJ17<=0,(BL$9-$A17)>($E17*365)),0,IF($A17<=BL$9,$F17/12)) -> 52.777778 | BM17: =IF(OR($BJ17<=0,(BM$9-$A17)>($E17*365)),0,IF($A17<=BM$9,$F17/12)) -> 52.777778 | BN17: =IF(OR($BJ17<=0,(BN$9-$A17)>($E17*365)),0,IF($A17<=BN$9,$F17/12)) -> 52.777778 | BO17: =IF(OR($BJ17<=0,(BO$9-$A17)>($E17*365)),0,IF($A17<=BO$9,$F17/12)) -> 52.777778 | BP17: =IF(OR($BJ17<=0,(BP$9-$A17)>($E17*365)),0,IF($A17<=BP$9,$F17/12)) -> 52.777778 | BQ17: =IF(OR($BJ17<=0,(BQ$9-$A17)>($E17*365)),0,IF($A17<=BQ$9,$F17/12)) -> 52.777778 | BR17: =IF(OR($BJ17<=0,(BR$9-$A17)>($E17*365)),0,IF($A17<=BR$9,$F17/12)) -> 52.777778 | ... BV17: =IF(OR($BJ17<=0,(BV$9-$A17)>($E17*365)),0,IF($A17<=BV$9,$F17/12)) -> 52.777778 | BW17: =SUM(BK17:BV17) -> 633.33333 | BX17: =IF(AND($BV$9>$A17,$BW17<>0),$D17-$S17-$AG17-$AU17-$BI17-$BW17,0) -> 316.66667 | BY17: =IF(OR($BX17<=0,(BY$9-$A17)>($E17*365)),0,IF($A17<=BY$9,$F17/12)) -> 52.777778 | BZ17: =IF(OR($BX17<=0,(BZ$9-$A17)>($E17*365)),0,IF($A17<=BZ$9,$F17/12)) -> 52.777778 | CA17: =IF(OR($BX17<=0,(CA$9-$A17)>($E17*365)),0,IF($A17<=CA$9,$F17/12)) -> 52.777778 | CB17: =IF(OR($BX17<=0,(CB$9-$A17)>($E17*365)),0,IF($A17<=CB$9,$F17/12)) -> 52.777778 | CC17: =IF(OR($BX17<=0,(CC$9-$A17)>($E17*365)),0,IF($A17<=CC$9,$F17/12)) -> 52.777778 | CD17: =IF(OR($BX17<=0,(CD$9-$A17)>($E17*365)),0,IF($A17<=CD$9,$F17/12)) -> 52.777778 | CE17: =IF(OR($BX17<=0,(CE$9-$A17)>($E17*365)),0,IF($A17<=CE$9,$F17/12)) -> 0 | CF17: =IF(OR($BX17<=0,(CF$9-$A17)>($E17*365)),0,IF($A17<=CF$9,$F17/12)) -> 0 | ... CJ17: =IF(OR($BX17<=0,(CJ$9-$A17)>($E17*365)),0,IF($A17<=CJ$9,$F17/12)) -> 0 | CK17: =SUM(BY17:CJ17) -> 316.66667 | CL17: =IF(AND($CJ$9>$A17,$CK17<>0),$D17-$S17-$AG17-$AU17-$BI17-$BW17-$CK$10,0) -> -1016.6667 | CM17: =IF(OR($CL17<=0,(CM$9-$A17)>($E17*365)),0,IF($A17<=CM$9,$F17/12)) -> 0 | CN17: =IF(OR($CL17<=0,(CN$9-$A17)>($E17*365)),0,IF($A17<=CN$9,$F17/12)) -> 0 | CO17: =IF(OR($CL17<=0,(CO$9-$A17)>($E17*365)),0,IF($A17<=CO$9,$F17/12)) -> 0 | CP17: =IF(OR($CL17<=0,(CP$9-$A17)>($E17*365)),0,IF($A17<=CP$9,$F17/12)) -> 0 | CQ17: =IF(OR($CL17<=0,(CQ$9-$A17)>($E17*365)),0,IF($A17<=CQ$9,$F17/12)) -> 0 | CR17: =IF(OR($CL17<=0,(CR$9-$A17)>($E17*365)),0,IF($A17<=CR$9,$F17/12)) -> 0 | CS17: =IF(OR($CL17<=0,(CS$9-$A17)>($E17*365)),0,IF($A17<=CS$9,$F17/12)) -> 0 | CT17: =IF(OR($CL17<=0,(CT$9-$A17)>($E17*365)),0,IF($A17<=CT$9,$F17/12)) -> 0 | ... CX17: =IF(OR($CL17<=0,(CX$9-$A17)>($E17*365)),0,IF($A17<=CX$9,$F17/12)) -> 0 | CY17: =SUM(CM17:CX17) -> 0 | CZ17: =IF(AND($CX$9>$A17,$CY17<>0),$D17-$S17-$AG17-$AU17-$BI17-$BW17-$CK17-$CY17,0) -> 0 | DA17: =IF(OR($CZ17<=0,(DA$9-$A17)>($E17*365)),0,IF($A17<=DA$9,$F17/12)) -> 0 | DB17: =IF(OR($CZ17<=0,(DB$9-$A17)>($E17*365)),0,IF($A17<=DB$9,$F17/12)) -> 0 | DC17: =IF(OR($CZ17<=0,(DC$9-$A17)>($E17*365)),0,IF($A17<=DC$9,$F17/12)) -> 0 | DD17: =IF(OR($CZ17<=0,(DD$9-$A17)>($E17*365)),0,IF($A17<=DD$9,$F17/12)) -> 0 | DE17: =IF(OR($CZ17<=0,(DE$9-$A17)>($E17*365)),0,IF($A17<=DE$9,$F17/12)) -> 0 | DF17: =IF(OR($CZ17<=0,(DF$9-$A17)>($E17*365)),0,IF($A17<=DF$9,$F17/12)) -> 0 | DG17: =IF(OR($CZ17<=0,(DG$9-$A17)>($E17*365)),0,IF($A17<=DG$9,$F17/12)) -> 0 | DH17: =IF(OR($CZ17<=0,(DH$9-$A17)>($E17*365)),0,IF($A17<=DH$9,$F17/12)) -> 0 | ... DL17: =IF(OR($CZ17<=0,(DL$9-$A17)>($E17*365)),0,IF($A17<=DL$9,$F17/12)) -> 0 | DM17: =SUM(DA17:DL17) -> 0 | DN17: =IF(AND($DL$9>$A17,$DM17<>0),$D17-$S17-$AG17-$AU17-$BI17-$BW17-$CK$10-$CY17-$DM17,0) -> 0 | DO17: =IF(OR($DN17<=0,(DO$9-$A17)>($E17*365)),0,IF($A17<=DO$9,$F17/12)) -> 0 | DP17: =IF(OR($DN17<=0,(DP$9-$A17)>($E17*365)),0,IF($A17<=DP$9,$F17/12)) -> 0 | DQ17: =IF(OR($DN17<=0,(DQ$9-$A17)>($E17*365)),0,IF($A17<=DQ$9,$F17/12)) -> 0 | DR17: =IF(OR($DN17<=0,(DR$9-$A17)>($E17*365)),0,IF($A17<=DR$9,$F17/12)) -> 0 | DS17: =IF(OR($DN17<=0,(DS$9-$A17)>($E17*365)),0,IF($A17<=DS$9,$F17/12)) -> 0 | DT17: =IF(OR($DN17<=0,(DT$9-$A17)>($E17*365)),0,IF($A17<=DT$9,$F17/12)) -> 0 | DU17: =IF(OR($DN17<=0,(DU$9-$A17)>($E17*365)),0,IF($A17<=DU$9,$F17/12)) -> 0 | DV17: =IF(OR($DN17<=0,(DV$9-$A17)>($E17*365)),0,IF($A17<=DV$9,$F17/12)) -> 0 | ... DZ17: =IF(OR($DN17<=0,(DZ$9-$A17)>($E17*365)),0,IF($A17<=DZ$9,$F17/12)) -> 0 | EA17: =SUM(DO17:DZ17) -> 0 | EB17: =IF(AND($DZ$9>$A17,$EA17<>0),$D17-$S17-$AG17-$AU17-$BI17-$BW17--CY17-$DM17-$CK17-$EA17,0) -> 0
A18: 42868 | B18: Matériel Roulant | C18: pinces coupente | D18: 2500 | E18: 3 | F18: =D18/E18 -> 833.33333 | G18: =IF(OR($F18<=0,(G$9-$A18)>(365*$E18)),0,IF($A18<=G$9,$F18/12,0)) -> 0 | H18: =IF(OR($F18<=0,(H$9-$A18)>(365*$E18)),0,IF($A18<=H$9,$F18/12,0)) -> 0 | I18: =IF(OR($F18<=0,(I$9-$A18)>(365*$E18)),0,IF($A18<=I$9,$F18/12,0)) -> 0 | J18: =IF(OR($F18<=0,(J$9-$A18)>(365*$E18)),0,IF($A18<=J$9,$F18/12,0)) -> 0 | K18: =IF(OR($F18<=0,(K$9-$A18)>(365*$E18)),0,IF($A18<=K$9,$F18/12,0)) -> 0 | L18: =IF(OR($F18<=0,(L$9-$A18)>(365*$E18)),0,IF($A18<=L$9,$F18/12,0)) -> 0 | M18: =IF(OR($F18<=0,(M$9-$A18)>(365*$E18)),0,IF($A18<=M$9,$F18/12,0)) -> 0 | N18: =IF(OR($F18<=0,(N$9-$A18)>(365*$E18)),0,IF($A18<=N$9,$F18/12,0)) -> 0 | ... R18: =IF(OR($F18<=0,(R$9-$A18)>(365*$E18)),0,IF($A18<=R$9,$F18/12,0)) -> 0 | S18: =SUM(G18:R18) -> 0 | T18: =IF(AND($R$9>A18,$S18<>0),$D18-$S18,0) -> 0 | U18: =IF(OR($F18<=0,(U$9-$A18)>(365*$E18)),0,IF($A18<=U$9,$F18/12,0)) -> 0 | V18: =IF(OR($F18<=0,(V$9-$A18)>(365*$E18)),0,IF($A18<=V$9,$F18/12,0)) -> 0 | W18: =IF(OR($F18<=0,(W$9-$A18)>(365*$E18)),0,IF($A18<=W$9,$F18/12,0)) -> 0 | X18: =IF(OR($F18<=0,(X$9-$A18)>(365*$E18)),0,IF($A18<=X$9,$F18/12,0)) -> 0 | Y18: =IF(OR($F18<=0,(Y$9-$A18)>(365*$E18)),0,IF($A18<=Y$9,$F18/12,0)) -> 0 | Z18: =IF(OR($F18<=0,(Z$9-$A18)>(365*$E18)),0,IF($A18<=Z$9,$F18/12,0)) -> 0 | AA18: =IF(OR($F18<=0,(AA$9-$A18)>(365*$E18)),0,IF($A18<=AA$9,$F18/12,0)) -> 0 | AB18: =IF(OR($F18<=0,(AB$9-$A18)>(365*$E18)),0,IF($A18<=AB$9,$F18/12,0)) -> 0 | ... AF18: =IF(OR($F18<=0,(AF$9-$A18)>(365*$E18)),0,IF($A18<=AF$9,$F18/12,0)) -> 0 | AG18: =SUM(U18:AF18) -> 0 | AH18: =IF(AND($AF$9>$A18,$AG18<>0),$D18-$S18-$AG18,0) -> 0 | AI18: =IF(OR($F18<=0,(AI$9-$A18)>(365*$E18)),0,IF($A18<=AI$9,$F18/12,0)) -> 0 | AJ18: =IF(OR($F18<=0,(AJ$9-$A18)>(365*$E18)),0,IF($A18<=AJ$9,$F18/12,0)) -> 0 | AK18: =IF(OR($F18<=0,(AK$9-$A18)>(365*$E18)),0,IF($A18<=AK$9,$F18/12,0)) -> 0 | AL18: =IF(OR($F18<=0,(AL$9-$A18)>(365*$E18)),0,IF($A18<=AL$9,$F18/12,0)) -> 0 | AM18: =IF(OR($F18<=0,(AM$9-$A18)>(365*$E18)),0,IF($A18<=AM$9,$F18/12,0)) -> 0 | AN18: =IF(OR($F18<=0,(AN$9-$A18)>(365*$E18)),0,IF($A18<=AN$9,$F18/12,0)) -> 0 | AO18: =IF(OR($F18<=0,(AO$9-$A18)>(365*$E18)),0,IF($A18<=AO$9,$F18/12,0)) -> 69.444444 | AP18: =IF(OR($F18<=0,(AP$9-$A18)>(365*$E18)),0,IF($A18<=AP$9,$F18/12,0)) -> 69.444444 | ... AT18: =IF(OR($F18<=0,(AT$9-$A18)>(365*$E18)),0,IF($A18<=AT$9,$F18/12,0)) -> 69.444444 | AU18: =SUM(AI18:AT18) -> 416.66667 | AV18: =IF(AND($AT$9>$A18,$AU18<>0),$D18-$S18-$AG18-$AU18,0) -> 2083.3333 | AW18: =IF(OR($F18<=0,(AW$9-$A18)>(365*$E18)),0,IF($A18<=AW$9,$F18/12,0)) -> 69.444444 | AX18: =IF(OR($F18<=0,(AX$9-$A18)>(365*$E18)),0,IF($A18<=AX$9,$F18/12,0)) -> 69.444444 | AY18: =IF(OR($F18<=0,(AY$9-$A18)>(365*$E18)),0,IF($A18<=AY$9,$F18/12,0)) -> 69.444444 | AZ18: =IF(OR($F18<=0,(AZ$9-$A18)>(365*$E18)),0,IF($A18<=AZ$9,$F18/12,0)) -> 69.444444 | BA18: =IF(OR($F18<=0,(BA$9-$A18)>(365*$E18)),0,IF($A18<=BA$9,$F18/12,0)) -> 69.444444 | BB18: =IF(OR($F18<=0,(BB$9-$A18)>(365*$E18)),0,IF($A18<=BB$9,$F18/12,0)) -> 69.444444 | BC18: =IF(OR($F18<=0,(BC$9-$A18)>(365*$E18)),0,IF($A18<=BC$9,$F18/12,0)) -> 69.444444 | BD18: =IF(OR($F18<=0,(BD$9-$A18)>(365*$E18)),0,IF($A18<=BD$9,$F18/12,0)) -> 69.444444 | ... BH18: =IF(OR($F18<=0,(BH$9-$A18)>(365*$E18)),0,IF($A18<=BH$9,$F18/12,0)) -> 69.444444 | BI18: =SUM(AW18:BH18) -> 833.33333 | BJ18: =IF(AND($BH$9>$A18,$BI18<>0),$D18-$S18-$AG18-$AU18-$BI18,0) -> 1250 | BK18: =IF(OR($BJ18<=0,(BK$9-$A18)>($E18*365)),0,IF($A18<=BK$9,$F18/12)) -> 69.444444 | BL18: =IF(OR($BJ18<=0,(BL$9-$A18)>($E18*365)),0,IF($A18<=BL$9,$F18/12)) -> 69.444444 | BM18: =IF(OR($BJ18<=0,(BM$9-$A18)>($E18*365)),0,IF($A18<=BM$9,$F18/12)) -> 69.444444 | BN18: =IF(OR($BJ18<=0,(BN$9-$A18)>($E18*365)),0,IF($A18<=BN$9,$F18/12)) -> 69.444444 | BO18: =IF(OR($BJ18<=0,(BO$9-$A18)>($E18*365)),0,IF($A18<=BO$9,$F18/12)) -> 69.444444 | BP18: =IF(OR($BJ18<=0,(BP$9-$A18)>($E18*365)),0,IF($A18<=BP$9,$F18/12)) -> 69.444444 | BQ18: =IF(OR($BJ18<=0,(BQ$9-$A18)>($E18*365)),0,IF($A18<=BQ$9,$F18/12)) -> 69.444444 | BR18: =IF(OR($BJ18<=0,(BR$9-$A18)>($E18*365)),0,IF($A18<=BR$9,$F18/12)) -> 69.444444 | ... BV18: =IF(OR($BJ18<=0,(BV$9-$A18)>($E18*365)),0,IF($A18<=BV$9,$F18/12)) -> 69.444444 | BW18: =SUM(BK18:BV18) -> 833.33333 | BX18: =IF(AND($BV$9>$A18,$BW18<>0),$D18-$S18-$AG18-$AU18-$BI18-$BW18,0) -> 416.66667 | BY18: =IF(OR($BX18<=0,(BY$9-$A18)>($E18*365)),0,IF($A18<=BY$9,$F18/12)) -> 69.444444 | BZ18: =IF(OR($BX18<=0,(BZ$9-$A18)>($E18*365)),0,IF($A18<=BZ$9,$F18/12)) -> 69.444444 | CA18: =IF(OR($BX18<=0,(CA$9-$A18)>($E18*365)),0,IF($A18<=CA$9,$F18/12)) -> 69.444444 | CB18: =IF(OR($BX18<=0,(CB$9-$A18)>($E18*365)),0,IF($A18<=CB$9,$F18/12)) -> 69.444444 | CC18: =IF(OR($BX18<=0,(CC$9-$A18)>($E18*365)),0,IF($A18<=CC$9,$F18/12)) -> 69.444444 | CD18: =IF(OR($BX18<=0,(CD$9-$A18)>($E18*365)),0,IF($A18<=CD$9,$F18/12)) -> 69.444444 | CE18: =IF(OR($BX18<=0,(CE$9-$A18)>($E18*365)),0,IF($A18<=CE$9,$F18/12)) -> 0 | CF18: =IF(OR($BX18<=0,(CF$9-$A18)>($E18*365)),0,IF($A18<=CF$9,$F18/12)) -> 0 | ... CJ18: =IF(OR($BX18<=0,(CJ$9-$A18)>($E18*365)),0,IF($A18<=CJ$9,$F18/12)) -> 0 | CK18: =SUM(BY18:CJ18) -> 416.66667 | CL18: =IF(AND($CJ$9>$A18,$CK18<>0),$D18-$S18-$AG18-$AU18-$BI18-$BW18-$CK$10,0) -> -916.66667 | CM18: =IF(OR($CL18<=0,(CM$9-$A18)>($E18*365)),0,IF($A18<=CM$9,$F18/12)) -> 0 | CN18: =IF(OR($CL18<=0,(CN$9-$A18)>($E18*365)),0,IF($A18<=CN$9,$F18/12)) -> 0 | CO18: =IF(OR($CL18<=0,(CO$9-$A18)>($E18*365)),0,IF($A18<=CO$9,$F18/12)) -> 0 | CP18: =IF(OR($CL18<=0,(CP$9-$A18)>($E18*365)),0,IF($A18<=CP$9,$F18/12)) -> 0 | CQ18: =IF(OR($CL18<=0,(CQ$9-$A18)>($E18*365)),0,IF($A18<=CQ$9,$F18/12)) -> 0 | CR18: =IF(OR($CL18<=0,(CR$9-$A18)>($E18*365)),0,IF($A18<=CR$9,$F18/12)) -> 0 | CS18: =IF(OR($CL18<=0,(CS$9-$A18)>($E18*365)),0,IF($A18<=CS$9,$F18/12)) -> 0 | CT18: =IF(OR($CL18<=0,(CT$9-$A18)>($E18*365)),0,IF($A18<=CT$9,$F18/12)) -> 0 | ... CX18: =IF(OR($CL18<=0,(CX$9-$A18)>($E18*365)),0,IF($A18<=CX$9,$F18/12)) -> 0 | CY18: =SUM(CM18:CX18) -> 0 | CZ18: =IF(AND($CX$9>$A18,$CY18<>0),$D18-$S18-$AG18-$AU18-$BI18-$BW18-$CK18-$CY18,0) -> 0 | DA18: =IF(OR($CZ18<=0,(DA$9-$A18)>($E18*365)),0,IF($A18<=DA$9,$F18/12)) -> 0 | DB18: =IF(OR($CZ18<=0,(DB$9-$A18)>($E18*365)),0,IF($A18<=DB$9,$F18/12)) -> 0 | DC18: =IF(OR($CZ18<=0,(DC$9-$A18)>($E18*365)),0,IF($A18<=DC$9,$F18/12)) -> 0 | DD18: =IF(OR($CZ18<=0,(DD$9-$A18)>($E18*365)),0,IF($A18<=DD$9,$F18/12)) -> 0 | DE18: =IF(OR($CZ18<=0,(DE$9-$A18)>($E18*365)),0,IF($A18<=DE$9,$F18/12)) -> 0 | DF18: =IF(OR($CZ18<=0,(DF$9-$A18)>($E18*365)),0,IF($A18<=DF$9,$F18/12)) -> 0 | DG18: =IF(OR($CZ18<=0,(DG$9-$A18)>($E18*365)),0,IF($A18<=DG$9,$F18/12)) -> 0 | DH18: =IF(OR($CZ18<=0,(DH$9-$A18)>($E18*365)),0,IF($A18<=DH$9,$F18/12)) -> 0 | ... DL18: =IF(OR($CZ18<=0,(DL$9-$A18)>($E18*365)),0,IF($A18<=DL$9,$F18/12)) -> 0 | DM18: =SUM(DA18:DL18) -> 0 | DN18: =IF(AND($DL$9>$A18,$DM18<>0),$D18-$S18-$AG18-$AU18-$BI18-$BW18-$CK$10-$CY18-$DM18,0) -> 0 | DO18: =IF(OR($DN18<=0,(DO$9-$A18)>($E18*365)),0,IF($A18<=DO$9,$F18/12)) -> 0 | DP18: =IF(OR($DN18<=0,(DP$9-$A18)>($E18*365)),0,IF($A18<=DP$9,$F18/12)) -> 0 | DQ18: =IF(OR($DN18<=0,(DQ$9-$A18)>($E18*365)),0,IF($A18<=DQ$9,$F18/12)) -> 0 | DR18: =IF(OR($DN18<=0,(DR$9-$A18)>($E18*365)),0,IF($A18<=DR$9,$F18/12)) -> 0 | DS18: =IF(OR($DN18<=0,(DS$9-$A18)>($E18*365)),0,IF($A18<=DS$9,$F18/12)) -> 0 | DT18: =IF(OR($DN18<=0,(DT$9-$A18)>($E18*365)),0,IF($A18<=DT$9,$F18/12)) -> 0 | DU18: =IF(OR($DN18<=0,(DU$9-$A18)>($E18*365)),0,IF($A18<=DU$9,$F18/12)) -> 0 | DV18: =IF(OR($DN18<=0,(DV$9-$A18)>($E18*365)),0,IF($A18<=DV$9,$F18/12)) -> 0 | ... DZ18: =IF(OR($DN18<=0,(DZ$9-$A18)>($E18*365)),0,IF($A18<=DZ$9,$F18/12)) -> 0 | EA18: =SUM(DO18:DZ18) -> 0 | EB18: =IF(AND($DZ$9>$A18,$EA18<>0),$D18-$S18-$AG18-$AU18-$BI18-$BW18--CY18-$DM18-$CK18-$EA18,0) -> 0
A19: 43018 | B19: Matériels | C19: marteau maié | D19: 230 | E19: 3 | F19: =D19/E19 -> 76.666667 | G19: =IF(OR($F19<=0,(G$9-$A19)>(365*$E19)),0,IF($A19<=G$9,$F19/12,0)) -> 0 | H19: =IF(OR($F19<=0,(H$9-$A19)>(365*$E19)),0,IF($A19<=H$9,$F19/12,0)) -> 0 | I19: =IF(OR($F19<=0,(I$9-$A19)>(365*$E19)),0,IF($A19<=I$9,$F19/12,0)) -> 0 | J19: =IF(OR($F19<=0,(J$9-$A19)>(365*$E19)),0,IF($A19<=J$9,$F19/12,0)) -> 0 | K19: =IF(OR($F19<=0,(K$9-$A19)>(365*$E19)),0,IF($A19<=K$9,$F19/12,0)) -> 0 | L19: =IF(OR($F19<=0,(L$9-$A19)>(365*$E19)),0,IF($A19<=L$9,$F19/12,0)) -> 0 | M19: =IF(OR($F19<=0,(M$9-$A19)>(365*$E19)),0,IF($A19<=M$9,$F19/12,0)) -> 0 | N19: =IF(OR($F19<=0,(N$9-$A19)>(365*$E19)),0,IF($A19<=N$9,$F19/12,0)) -> 0 | ... R19: =IF(OR($F19<=0,(R$9-$A19)>(365*$E19)),0,IF($A19<=R$9,$F19/12,0)) -> 0 | S19: =SUM(G19:R19) -> 0 | T19: =IF(AND($R$9>A19,$S19<>0),$D19-$S19,0) -> 0 | U19: =IF(OR($F19<=0,(U$9-$A19)>(365*$E19)),0,IF($A19<=U$9,$F19/12,0)) -> 0 | V19: =IF(OR($F19<=0,(V$9-$A19)>(365*$E19)),0,IF($A19<=V$9,$F19/12,0)) -> 0 | W19: =IF(OR($F19<=0,(W$9-$A19)>(365*$E19)),0,IF($A19<=W$9,$F19/12,0)) -> 0 | X19: =IF(OR($F19<=0,(X$9-$A19)>(365*$E19)),0,IF($A19<=X$9,$F19/12,0)) -> 0 | Y19: =IF(OR($F19<=0,(Y$9-$A19)>(365*$E19)),0,IF($A19<=Y$9,$F19/12,0)) -> 0 | Z19: =IF(OR($F19<=0,(Z$9-$A19)>(365*$E19)),0,IF($A19<=Z$9,$F19/12,0)) -> 0 | AA19: =IF(OR($F19<=0,(AA$9-$A19)>(365*$E19)),0,IF($A19<=AA$9,$F19/12,0)) -> 0 | AB19: =IF(OR($F19<=0,(AB$9-$A19)>(365*$E19)),0,IF($A19<=AB$9,$F19/12,0)) -> 0 | ... AF19: =IF(OR($F19<=0,(AF$9-$A19)>(365*$E19)),0,IF($A19<=AF$9,$F19/12,0)) -> 0 | AG19: =SUM(U19:AF19) -> 0 | AH19: =IF(AND($AF$9>$A19,$AG19<>0),$D19-$S19-$AG19,0) -> 0 | AI19: =IF(OR($F19<=0,(AI$9-$A19)>(365*$E19)),0,IF($A19<=AI$9,$F19/12,0)) -> 0 | AJ19: =IF(OR($F19<=0,(AJ$9-$A19)>(365*$E19)),0,IF($A19<=AJ$9,$F19/12,0)) -> 0 | AK19: =IF(OR($F19<=0,(AK$9-$A19)>(365*$E19)),0,IF($A19<=AK$9,$F19/12,0)) -> 0 | AL19: =IF(OR($F19<=0,(AL$9-$A19)>(365*$E19)),0,IF($A19<=AL$9,$F19/12,0)) -> 0 | AM19: =IF(OR($F19<=0,(AM$9-$A19)>(365*$E19)),0,IF($A19<=AM$9,$F19/12,0)) -> 0 | AN19: =IF(OR($F19<=0,(AN$9-$A19)>(365*$E19)),0,IF($A19<=AN$9,$F19/12,0)) -> 0 | AO19: =IF(OR($F19<=0,(AO$9-$A19)>(365*$E19)),0,IF($A19<=AO$9,$F19/12,0)) -> 0 | AP19: =IF(OR($F19<=0,(AP$9-$A19)>(365*$E19)),0,IF($A19<=AP$9,$F19/12,0)) -> 0 | ... AT19: =IF(OR($F19<=0,(AT$9-$A19)>(365*$E19)),0,IF($A19<=AT$9,$F19/12,0)) -> 6.3888889 | AU19: =SUM(AI19:AT19) -> 6.3888889 | AV19: =IF(AND($AT$9>$A19,$AU19<>0),$D19-$S19-$AG19-$AU19,0) -> 223.61111 | AW19: =IF(OR($F19<=0,(AW$9-$A19)>(365*$E19)),0,IF($A19<=AW$9,$F19/12,0)) -> 6.3888889 | AX19: =IF(OR($F19<=0,(AX$9-$A19)>(365*$E19)),0,IF($A19<=AX$9,$F19/12,0)) -> 6.3888889 | AY19: =IF(OR($F19<=0,(AY$9-$A19)>(365*$E19)),0,IF($A19<=AY$9,$F19/12,0)) -> 6.3888889 | AZ19: =IF(OR($F19<=0,(AZ$9-$A19)>(365*$E19)),0,IF($A19<=AZ$9,$F19/12,0)) -> 6.3888889 | BA19: =IF(OR($F19<=0,(BA$9-$A19)>(365*$E19)),0,IF($A19<=BA$9,$F19/12,0)) -> 6.3888889 | BB19: =IF(OR($F19<=0,(BB$9-$A19)>(365*$E19)),0,IF($A19<=BB$9,$F19/12,0)) -> 6.3888889 | BC19: =IF(OR($F19<=0,(BC$9-$A19)>(365*$E19)),0,IF($A19<=BC$9,$F19/12,0)) -> 6.3888889 | BD19: =IF(OR($F19<=0,(BD$9-$A19)>(365*$E19)),0,IF($A19<=BD$9,$F19/12,0)) -> 6.3888889 | ... BH19: =IF(OR($F19<=0,(BH$9-$A19)>(365*$E19)),0,IF($A19<=BH$9,$F19/12,0)) -> 6.3888889 | BI19: =SUM(AW19:BH19) -> 76.666667 | BJ19: =IF(AND($BH$9>$A19,$BI19<>0),$D19-$S19-$AG19-$AU19-$BI19,0) -> 146.94444 | BK19: =IF(OR($BJ19<=0,(BK$9-$A19)>($E19*365)),0,IF($A19<=BK$9,$F19/12)) -> 6.3888889 | BL19: =IF(OR($BJ19<=0,(BL$9-$A19)>($E19*365)),0,IF($A19<=BL$9,$F19/12)) -> 6.3888889 | BM19: =IF(OR($BJ19<=0,(BM$9-$A19)>($E19*365)),0,IF($A19<=BM$9,$F19/12)) -> 6.3888889 | BN19: =IF(OR($BJ19<=0,(BN$9-$A19)>($E19*365)),0,IF($A19<=BN$9,$F19/12)) -> 6.3888889 | BO19: =IF(OR($BJ19<=0,(BO$9-$A19)>($E19*365)),0,IF($A19<=BO$9,$F19/12)) -> 6.3888889 | BP19: =IF(OR($BJ19<=0,(BP$9-$A19)>($E19*365)),0,IF($A19<=BP$9,$F19/12)) -> 6.3888889 | BQ19: =IF(OR($BJ19<=0,(BQ$9-$A19)>($E19*365)),0,IF($A19<=BQ$9,$F19/12)) -> 6.3888889 | BR19: =IF(OR($BJ19<=0,(BR$9-$A19)>($E19*365)),0,IF($A19<=BR$9,$F19/12)) -> 6.3888889 | ... BV19: =IF(OR($BJ19<=0,(BV$9-$A19)>($E19*365)),0,IF($A19<=BV$9,$F19/12)) -> 6.3888889 | BW19: =SUM(BK19:BV19) -> 76.666667 | BX19: =IF(AND($BV$9>$A19,$BW19<>0),$D19-$S19-$AG19-$AU19-$BI19-$BW19,0) -> 70.277778 | BY19: =IF(OR($BX19<=0,(BY$9-$A19)>($E19*365)),0,IF($A19<=BY$9,$F19/12)) -> 6.3888889 | BZ19: =IF(OR($BX19<=0,(BZ$9-$A19)>($E19*365)),0,IF($A19<=BZ$9,$F19/12)) -> 6.3888889 | CA19: =IF(OR($BX19<=0,(CA$9-$A19)>($E19*365)),0,IF($A19<=CA$9,$F19/12)) -> 6.3888889 | CB19: =IF(OR($BX19<=0,(CB$9-$A19)>($E19*365)),0,IF($A19<=CB$9,$F19/12)) -> 6.3888889 | CC19: =IF(OR($BX19<=0,(CC$9-$A19)>($E19*365)),0,IF($A19<=CC$9,$F19/12)) -> 6.3888889 | CD19: =IF(OR($BX19<=0,(CD$9-$A19)>($E19*365)),0,IF($A19<=CD$9,$F19/12)) -> 6.3888889 | CE19: =IF(OR($BX19<=0,(CE$9-$A19)>($E19*365)),0,IF($A19<=CE$9,$F19/12)) -> 6.3888889 | CF19: =IF(OR($BX19<=0,(CF$9-$A19)>($E19*365)),0,IF($A19<=CF$9,$F19/12)) -> 6.3888889 | ... CJ19: =IF(OR($BX19<=0,(CJ$9-$A19)>($E19*365)),0,IF($A19<=CJ$9,$F19/12)) -> 0 | CK19: =SUM(BY19:CJ19) -> 70.277778 | CL19: =IF(AND($CJ$9>$A19,$CK19<>0),$D19-$S19-$AG19-$AU19-$BI19-$BW19-$CK$10,0) -> -1263.0556 | CM19: =IF(OR($CL19<=0,(CM$9-$A19)>($E19*365)),0,IF($A19<=CM$9,$F19/12)) -> 0 | CN19: =IF(OR($CL19<=0,(CN$9-$A19)>($E19*365)),0,IF($A19<=CN$9,$F19/12)) -> 0 | CO19: =IF(OR($CL19<=0,(CO$9-$A19)>($E19*365)),0,IF($A19<=CO$9,$F19/12)) -> 0 | CP19: =IF(OR($CL19<=0,(CP$9-$A19)>($E19*365)),0,IF($A19<=CP$9,$F19/12)) -> 0 | CQ19: =IF(OR($CL19<=0,(CQ$9-$A19)>($E19*365)),0,IF($A19<=CQ$9,$F19/12)) -> 0 | CR19: =IF(OR($CL19<=0,(CR$9-$A19)>($E19*365)),0,IF($A19<=CR$9,$F19/12)) -> 0 | CS19: =IF(OR($CL19<=0,(CS$9-$A19)>($E19*365)),0,IF($A19<=CS$9,$F19/12)) -> 0 | CT19: =IF(OR($CL19<=0,(CT$9-$A19)>($E19*365)),0,IF($A19<=CT$9,$F19/12)) -> 0 | ... CX19: =IF(OR($CL19<=0,(CX$9-$A19)>($E19*365)),0,IF($A19<=CX$9,$F19/12)) -> 0 | CY19: =SUM(CM19:CX19) -> 0 | CZ19: =IF(AND($CX$9>$A19,$CY19<>0),$D19-$S19-$AG19-$AU19-$BI19-$BW19-$CK19-$CY19,0) -> 0 | DA19: =IF(OR($CZ19<=0,(DA$9-$A19)>($E19*365)),0,IF($A19<=DA$9,$F19/12)) -> 0 | DB19: =IF(OR($CZ19<=0,(DB$9-$A19)>($E19*365)),0,IF($A19<=DB$9,$F19/12)) -> 0 | DC19: =IF(OR($CZ19<=0,(DC$9-$A19)>($E19*365)),0,IF($A19<=DC$9,$F19/12)) -> 0 | DD19: =IF(OR($CZ19<=0,(DD$9-$A19)>($E19*365)),0,IF($A19<=DD$9,$F19/12)) -> 0 | DE19: =IF(OR($CZ19<=0,(DE$9-$A19)>($E19*365)),0,IF($A19<=DE$9,$F19/12)) -> 0 | DF19: =IF(OR($CZ19<=0,(DF$9-$A19)>($E19*365)),0,IF($A19<=DF$9,$F19/12)) -> 0 | DG19: =IF(OR($CZ19<=0,(DG$9-$A19)>($E19*365)),0,IF($A19<=DG$9,$F19/12)) -> 0 | DH19: =IF(OR($CZ19<=0,(DH$9-$A19)>($E19*365)),0,IF($A19<=DH$9,$F19/12)) -> 0 | ... DL19: =IF(OR($CZ19<=0,(DL$9-$A19)>($E19*365)),0,IF($A19<=DL$9,$F19/12)) -> 0 | DM19: =SUM(DA19:DL19) -> 0 | DN19: =IF(AND($DL$9>$A19,$DM19<>0),$D19-$S19-$AG19-$AU19-$BI19-$BW19-$CK$10-$CY19-$DM19,0) -> 0 | DO19: =IF(OR($DN19<=0,(DO$9-$A19)>($E19*365)),0,IF($A19<=DO$9,$F19/12)) -> 0 | DP19: =IF(OR($DN19<=0,(DP$9-$A19)>($E19*365)),0,IF($A19<=DP$9,$F19/12)) -> 0 | DQ19: =IF(OR($DN19<=0,(DQ$9-$A19)>($E19*365)),0,IF($A19<=DQ$9,$F19/12)) -> 0 | DR19: =IF(OR($DN19<=0,(DR$9-$A19)>($E19*365)),0,IF($A19<=DR$9,$F19/12)) -> 0 | DS19: =IF(OR($DN19<=0,(DS$9-$A19)>($E19*365)),0,IF($A19<=DS$9,$F19/12)) -> 0 | DT19: =IF(OR($DN19<=0,(DT$9-$A19)>($E19*365)),0,IF($A19<=DT$9,$F19/12)) -> 0 | DU19: =IF(OR($DN19<=0,(DU$9-$A19)>($E19*365)),0,IF($A19<=DU$9,$F19/12)) -> 0 | DV19: =IF(OR($DN19<=0,(DV$9-$A19)>($E19*365)),0,IF($A19<=DV$9,$F19/12)) -> 0 | ... DZ19: =IF(OR($DN19<=0,(DZ$9-$A19)>($E19*365)),0,IF($A19<=DZ$9,$F19/12)) -> 0 | EA19: =SUM(DO19:DZ19) -> 0 | EB19: =IF(AND($DZ$9>$A19,$EA19<>0),$D19-$S19-$AG19-$AU19-$BI19-$BW19--CY19-$DM19-$CK19-$EA19,0) -> 0
A20: 43032 | B20: Matériels | C20: motoure prossage | D20: 6000 | E20: 5 | F20: =D20/E20 -> 1200 | G20: =IF(OR($F20<=0,(G$9-$A20)>(365*$E20)),0,IF($A20<=G$9,$F20/12,0)) -> 0 | H20: =IF(OR($F20<=0,(H$9-$A20)>(365*$E20)),0,IF($A20<=H$9,$F20/12,0)) -> 0 | I20: =IF(OR($F20<=0,(I$9-$A20)>(365*$E20)),0,IF($A20<=I$9,$F20/12,0)) -> 0 | J20: =IF(OR($F20<=0,(J$9-$A20)>(365*$E20)),0,IF($A20<=J$9,$F20/12,0)) -> 0 | K20: =IF(OR($F20<=0,(K$9-$A20)>(365*$E20)),0,IF($A20<=K$9,$F20/12,0)) -> 0 | L20: =IF(OR($F20<=0,(L$9-$A20)>(365*$E20)),0,IF($A20<=L$9,$F20/12,0)) -> 0 | M20: =IF(OR($F20<=0,(M$9-$A20)>(365*$E20)),0,IF($A20<=M$9,$F20/12,0)) -> 0 | N20: =IF(OR($F20<=0,(N$9-$A20)>(365*$E20)),0,IF($A20<=N$9,$F20/12,0)) -> 0 | ... R20: =IF(OR($F20<=0,(R$9-$A20)>(365*$E20)),0,IF($A20<=R$9,$F20/12,0)) -> 0 | S20: =SUM(G20:R20) -> 0 | T20: =IF(AND($R$9>A20,$S20<>0),$D20-$S20,0) -> 0 | U20: =IF(OR($F20<=0,(U$9-$A20)>(365*$E20)),0,IF($A20<=U$9,$F20/12,0)) -> 0 | V20: =IF(OR($F20<=0,(V$9-$A20)>(365*$E20)),0,IF($A20<=V$9,$F20/12,0)) -> 0 | W20: =IF(OR($F20<=0,(W$9-$A20)>(365*$E20)),0,IF($A20<=W$9,$F20/12,0)) -> 0 | X20: =IF(OR($F20<=0,(X$9-$A20)>(365*$E20)),0,IF($A20<=X$9,$F20/12,0)) -> 0 | Y20: =IF(OR($F20<=0,(Y$9-$A20)>(365*$E20)),0,IF($A20<=Y$9,$F20/12,0)) -> 0 | Z20: =IF(OR($F20<=0,(Z$9-$A20)>(365*$E20)),0,IF($A20<=Z$9,$F20/12,0)) -> 0 | AA20: =IF(OR($F20<=0,(AA$9-$A20)>(365*$E20)),0,IF($A20<=AA$9,$F20/12,0)) -> 0 | AB20: =IF(OR($F20<=0,(AB$9-$A20)>(365*$E20)),0,IF($A20<=AB$9,$F20/12,0)) -> 0 | ... AF20: =IF(OR($F20<=0,(AF$9-$A20)>(365*$E20)),0,IF($A20<=AF$9,$F20/12,0)) -> 0 | AG20: =SUM(U20:AF20) -> 0 | AH20: =IF(AND($AF$9>$A20,$AG20<>0),$D20-$S20-$AG20,0) -> 0 | AI20: =IF(OR($F20<=0,(AI$9-$A20)>(365*$E20)),0,IF($A20<=AI$9,$F20/12,0)) -> 0 | AJ20: =IF(OR($F20<=0,(AJ$9-$A20)>(365*$E20)),0,IF($A20<=AJ$9,$F20/12,0)) -> 0 | AK20: =IF(OR($F20<=0,(AK$9-$A20)>(365*$E20)),0,IF($A20<=AK$9,$F20/12,0)) -> 0 | AL20: =IF(OR($F20<=0,(AL$9-$A20)>(365*$E20)),0,IF($A20<=AL$9,$F20/12,0)) -> 0 | AM20: =IF(OR($F20<=0,(AM$9-$A20)>(365*$E20)),0,IF($A20<=AM$9,$F20/12,0)) -> 0 | AN20: =IF(OR($F20<=0,(AN$9-$A20)>(365*$E20)),0,IF($A20<=AN$9,$F20/12,0)) -> 0 | AO20: =IF(OR($F20<=0,(AO$9-$A20)>(365*$E20)),0,IF($A20<=AO$9,$F20/12,0)) -> 0 | AP20: =IF(OR($F20<=0,(AP$9-$A20)>(365*$E20)),0,IF($A20<=AP$9,$F20/12,0)) -> 0 | ... AT20: =IF(OR($F20<=0,(AT$9-$A20)>(365*$E20)),0,IF($A20<=AT$9,$F20/12,0)) -> 100 | AU20: =SUM(AI20:AT20) -> 100 | AV20: =IF(AND($AT$9>$A20,$AU20<>0),$D20-$S20-$AG20-$AU20,0) -> 5900 | AW20: =IF(OR($F20<=0,(AW$9-$A20)>(365*$E20)),0,IF($A20<=AW$9,$F20/12,0)) -> 100 | AX20: =IF(OR($F20<=0,(AX$9-$A20)>(365*$E20)),0,IF($A20<=AX$9,$F20/12,0)) -> 100 | AY20: =IF(OR($F20<=0,(AY$9-$A20)>(365*$E20)),0,IF($A20<=AY$9,$F20/12,0)) -> 100 | AZ20: =IF(OR($F20<=0,(AZ$9-$A20)>(365*$E20)),0,IF($A20<=AZ$9,$F20/12,0)) -> 100 | BA20: =IF(OR($F20<=0,(BA$9-$A20)>(365*$E20)),0,IF($A20<=BA$9,$F20/12,0)) -> 100 | BB20: =IF(OR($F20<=0,(BB$9-$A20)>(365*$E20)),0,IF($A20<=BB$9,$F20/12,0)) -> 100 | BC20: =IF(OR($F20<=0,(BC$9-$A20)>(365*$E20)),0,IF($A20<=BC$9,$F20/12,0)) -> 100 | BD20: =IF(OR($F20<=0,(BD$9-$A20)>(365*$E20)),0,IF($A20<=BD$9,$F20/12,0)) -> 100 | ... BH20: =IF(OR($F20<=0,(BH$9-$A20)>(365*$E20)),0,IF($A20<=BH$9,$F20/12,0)) -> 100 | BI20: =SUM(AW20:BH20) -> 1200 | BJ20: =IF(AND($BH$9>$A20,$BI20<>0),$D20-$S20-$AG20-$AU20-$BI20,0) -> 4700 | BK20: =IF(OR($BJ20<=0,(BK$9-$A20)>($E20*365)),0,IF($A20<=BK$9,$F20/12)) -> 100 | BL20: =IF(OR($BJ20<=0,(BL$9-$A20)>($E20*365)),0,IF($A20<=BL$9,$F20/12)) -> 100 | BM20: =IF(OR($BJ20<=0,(BM$9-$A20)>($E20*365)),0,IF($A20<=BM$9,$F20/12)) -> 100 | BN20: =IF(OR($BJ20<=0,(BN$9-$A20)>($E20*365)),0,IF($A20<=BN$9,$F20/12)) -> 100 | BO20: =IF(OR($BJ20<=0,(BO$9-$A20)>($E20*365)),0,IF($A20<=BO$9,$F20/12)) -> 100 | BP20: =IF(OR($BJ20<=0,(BP$9-$A20)>($E20*365)),0,IF($A20<=BP$9,$F20/12)) -> 100 | BQ20: =IF(OR($BJ20<=0,(BQ$9-$A20)>($E20*365)),0,IF($A20<=BQ$9,$F20/12)) -> 100 | BR20: =IF(OR($BJ20<=0,(BR$9-$A20)>($E20*365)),0,IF($A20<=BR$9,$F20/12)) -> 100 | ... BV20: =IF(OR($BJ20<=0,(BV$9-$A20)>($E20*365)),0,IF($A20<=BV$9,$F20/12)) -> 100 | BW20: =SUM(BK20:BV20) -> 1200 | BX20: =IF(AND($BV$9>$A20,$BW20<>0),$D20-$S20-$AG20-$AU20-$BI20-$BW20,0) -> 3500 | BY20: =IF(OR($BX20<=0,(BY$9-$A20)>($E20*365)),0,IF($A20<=BY$9,$F20/12)) -> 100 | BZ20: =IF(OR($BX20<=0,(BZ$9-$A20)>($E20*365)),0,IF($A20<=BZ$9,$F20/12)) -> 100 | CA20: =IF(OR($BX20<=0,(CA$9-$A20)>($E20*365)),0,IF($A20<=CA$9,$F20/12)) -> 100 | CB20: =IF(OR($BX20<=0,(CB$9-$A20)>($E20*365)),0,IF($A20<=CB$9,$F20/12)) -> 100 | CC20: =IF(OR($BX20<=0,(CC$9-$A20)>($E20*365)),0,IF($A20<=CC$9,$F20/12)) -> 100 | CD20: =IF(OR($BX20<=0,(CD$9-$A20)>($E20*365)),0,IF($A20<=CD$9,$F20/12)) -> 100 | CE20: =IF(OR($BX20<=0,(CE$9-$A20)>($E20*365)),0,IF($A20<=CE$9,$F20/12)) -> 100 | CF20: =IF(OR($BX20<=0,(CF$9-$A20)>($E20*365)),0,IF($A20<=CF$9,$F20/12)) -> 100 | ... CJ20: =IF(OR($BX20<=0,(CJ$9-$A20)>($E20*365)),0,IF($A20<=CJ$9,$F20/12)) -> 100 | CK20: =SUM(BY20:CJ20) -> 1200 | CL20: =IF(AND($CJ$9>$A20,$CK20<>0),$D20-$S20-$AG20-$AU20-$BI20-$BW20-$CK$10,0) -> 2166.6667 | CM20: =IF(OR($CL20<=0,(CM$9-$A20)>($E20*365)),0,IF($A20<=CM$9,$F20/12)) -> 100 | CN20: =IF(OR($CL20<=0,(CN$9-$A20)>($E20*365)),0,IF($A20<=CN$9,$F20/12)) -> 100 | CO20: =IF(OR($CL20<=0,(CO$9-$A20)>($E20*365)),0,IF($A20<=CO$9,$F20/12)) -> 100 | CP20: =IF(OR($CL20<=0,(CP$9-$A20)>($E20*365)),0,IF($A20<=CP$9,$F20/12)) -> 100 | CQ20: =IF(OR($CL20<=0,(CQ$9-$A20)>($E20*365)),0,IF($A20<=CQ$9,$F20/12)) -> 100 | CR20: =IF(OR($CL20<=0,(CR$9-$A20)>($E20*365)),0,IF($A20<=CR$9,$F20/12)) -> 100 | CS20: =IF(OR($CL20<=0,(CS$9-$A20)>($E20*365)),0,IF($A20<=CS$9,$F20/12)) -> 100 | CT20: =IF(OR($CL20<=0,(CT$9-$A20)>($E20*365)),0,IF($A20<=CT$9,$F20/12)) -> 100 | ... CX20: =IF(OR($CL20<=0,(CX$9-$A20)>($E20*365)),0,IF($A20<=CX$9,$F20/12)) -> 100 | CY20: =SUM(CM20:CX20) -> 1200 | CZ20: =IF(AND($CX$9>$A20,$CY20<>0),$D20-$S20-$AG20-$AU20-$BI20-$BW20-$CK20-$CY20,0) -> 1100 | DA20: =IF(OR($CZ20<=0,(DA$9-$A20)>($E20*365)),0,IF($A20<=DA$9,$F20/12)) -> 100 | DB20: =IF(OR($CZ20<=0,(DB$9-$A20)>($E20*365)),0,IF($A20<=DB$9,$F20/12)) -> 100 | DC20: =IF(OR($CZ20<=0,(DC$9-$A20)>($E20*365)),0,IF($A20<=DC$9,$F20/12)) -> 100 | DD20: =IF(OR($CZ20<=0,(DD$9-$A20)>($E20*365)),0,IF($A20<=DD$9,$F20/12)) -> 100 | DE20: =IF(OR($CZ20<=0,(DE$9-$A20)>($E20*365)),0,IF($A20<=DE$9,$F20/12)) -> 100 | DF20: =IF(OR($CZ20<=0,(DF$9-$A20)>($E20*365)),0,IF($A20<=DF$9,$F20/12)) -> 100 | DG20: =IF(OR($CZ20<=0,(DG$9-$A20)>($E20*365)),0,IF($A20<=DG$9,$F20/12)) -> 100 | DH20: =IF(OR($CZ20<=0,(DH$9-$A20)>($E20*365)),0,IF($A20<=DH$9,$F20/12)) -> 100 | ... DL20: =IF(OR($CZ20<=0,(DL$9-$A20)>($E20*365)),0,IF($A20<=DL$9,$F20/12)) -> 0 | DM20: =SUM(DA20:DL20) -> 1100 | DN20: =IF(AND($DL$9>$A20,$DM20<>0),$D20-$S20-$AG20-$AU20-$BI20-$BW20-$CK$10-$CY20-$DM20,0) -> -133.33333 | DO20: =IF(OR($DN20<=0,(DO$9-$A20)>($E20*365)),0,IF($A20<=DO$9,$F20/12)) -> 0 | DP20: =IF(OR($DN20<=0,(DP$9-$A20)>($E20*365)),0,IF($A20<=DP$9,$F20/12)) -> 0 | DQ20: =IF(OR($DN20<=0,(DQ$9-$A20)>($E20*365)),0,IF($A20<=DQ$9,$F20/12)) -> 0 | DR20: =IF(OR($DN20<=0,(DR$9-$A20)>($E20*365)),0,IF($A20<=DR$9,$F20/12)) -> 0 | DS20: =IF(OR($DN20<=0,(DS$9-$A20)>($E20*365)),0,IF($A20<=DS$9,$F20/12)) -> 0 | DT20: =IF(OR($DN20<=0,(DT$9-$A20)>($E20*365)),0,IF($A20<=DT$9,$F20/12)) -> 0 | DU20: =IF(OR($DN20<=0,(DU$9-$A20)>($E20*365)),0,IF($A20<=DU$9,$F20/12)) -> 0 | DV20: =IF(OR($DN20<=0,(DV$9-$A20)>($E20*365)),0,IF($A20<=DV$9,$F20/12)) -> 0 | ... DZ20: =IF(OR($DN20<=0,(DZ$9-$A20)>($E20*365)),0,IF($A20<=DZ$9,$F20/12)) -> 0 | EA20: =SUM(DO20:DZ20) -> 0 | EB20: =IF(AND($DZ$9>$A20,$EA20<>0),$D20-$S20-$AG20-$AU20-$BI20-$BW20--CY20-$DM20-$CK20-$EA20,0) -> 0
A21: 43044 | B21: Matériels | C21: tat pompé | D21: 1000 | E21: 10 | F21: =D21/E21 -> 100 | G21: =IF(OR($F21<=0,(G$9-$A21)>(365*$E21)),0,IF($A21<=G$9,$F21/12,0)) -> 0 | H21: =IF(OR($F21<=0,(H$9-$A21)>(365*$E21)),0,IF($A21<=H$9,$F21/12,0)) -> 0 | I21: =IF(OR($F21<=0,(I$9-$A21)>(365*$E21)),0,IF($A21<=I$9,$F21/12,0)) -> 0 | J21: =IF(OR($F21<=0,(J$9-$A21)>(365*$E21)),0,IF($A21<=J$9,$F21/12,0)) -> 0 | K21: =IF(OR($F21<=0,(K$9-$A21)>(365*$E21)),0,IF($A21<=K$9,$F21/12,0)) -> 0 | L21: =IF(OR($F21<=0,(L$9-$A21)>(365*$E21)),0,IF($A21<=L$9,$F21/12,0)) -> 0 | M21: =IF(OR($F21<=0,(M$9-$A21)>(365*$E21)),0,IF($A21<=M$9,$F21/12,0)) -> 0 | N21: =IF(OR($F21<=0,(N$9-$A21)>(365*$E21)),0,IF($A21<=N$9,$F21/12,0)) -> 0 | ... R21: =IF(OR($F21<=0,(R$9-$A21)>(365*$E21)),0,IF($A21<=R$9,$F21/12,0)) -> 0 | S21: =SUM(G21:R21) -> 0 | T21: =IF(AND($R$9>A21,$S21<>0),$D21-$S21,0) -> 0 | U21: =IF(OR($F21<=0,(U$9-$A21)>(365*$E21)),0,IF($A21<=U$9,$F21/12,0)) -> 0 | V21: =IF(OR($F21<=0,(V$9-$A21)>(365*$E21)),0,IF($A21<=V$9,$F21/12,0)) -> 0 | W21: =IF(OR($F21<=0,(W$9-$A21)>(365*$E21)),0,IF($A21<=W$9,$F21/12,0)) -> 0 | X21: =IF(OR($F21<=0,(X$9-$A21)>(365*$E21)),0,IF($A21<=X$9,$F21/12,0)) -> 0 | Y21: =IF(OR($F21<=0,(Y$9-$A21)>(365*$E21)),0,IF($A21<=Y$9,$F21/12,0)) -> 0 | Z21: =IF(OR($F21<=0,(Z$9-$A21)>(365*$E21)),0,IF($A21<=Z$9,$F21/12,0)) -> 0 | AA21: =IF(OR($F21<=0,(AA$9-$A21)>(365*$E21)),0,IF($A21<=AA$9,$F21/12,0)) -> 0 | AB21: =IF(OR($F21<=0,(AB$9-$A21)>(365*$E21)),0,IF($A21<=AB$9,$F21/12,0)) -> 0 | ... AF21: =IF(OR($F21<=0,(AF$9-$A21)>(365*$E21)),0,IF($A21<=AF$9,$F21/12,0)) -> 0 | AG21: =SUM(U21:AF21) -> 0 | AH21: =IF(AND($AF$9>$A21,$AG21<>0),$D21-$S21-$AG21,0) -> 0 | AI21: =IF(OR($F21<=0,(AI$9-$A21)>(365*$E21)),0,IF($A21<=AI$9,$F21/12,0)) -> 0 | AJ21: =IF(OR($F21<=0,(AJ$9-$A21)>(365*$E21)),0,IF($A21<=AJ$9,$F21/12,0)) -> 0 | AK21: =IF(OR($F21<=0,(AK$9-$A21)>(365*$E21)),0,IF($A21<=AK$9,$F21/12,0)) -> 0 | AL21: =IF(OR($F21<=0,(AL$9-$A21)>(365*$E21)),0,IF($A21<=AL$9,$F21/12,0)) -> 0 | AM21: =IF(OR($F21<=0,(AM$9-$A21)>(365*$E21)),0,IF($A21<=AM$9,$F21/12,0)) -> 0 | AN21: =IF(OR($F21<=0,(AN$9-$A21)>(365*$E21)),0,IF($A21<=AN$9,$F21/12,0)) -> 0 | AO21: =IF(OR($F21<=0,(AO$9-$A21)>(365*$E21)),0,IF($A21<=AO$9,$F21/12,0)) -> 0 | AP21: =IF(OR($F21<=0,(AP$9-$A21)>(365*$E21)),0,IF($A21<=AP$9,$F21/12,0)) -> 0 | ... AT21: =IF(OR($F21<=0,(AT$9-$A21)>(365*$E21)),0,IF($A21<=AT$9,$F21/12,0)) -> 0 | AU21: =SUM(AI21:AT21) -> 0 | AV21: =IF(AND($AT$9>$A21,$AU21<>0),$D21-$S21-$AG21-$AU21,0) -> 0 | AW21: =IF(OR($F21<=0,(AW$9-$A21)>(365*$E21)),0,IF($A21<=AW$9,$F21/12,0)) -> 8.3333333 | AX21: =IF(OR($F21<=0,(AX$9-$A21)>(365*$E21)),0,IF($A21<=AX$9,$F21/12,0)) -> 8.3333333 | AY21: =IF(OR($F21<=0,(AY$9-$A21)>(365*$E21)),0,IF($A21<=AY$9,$F21/12,0)) -> 8.3333333 | AZ21: =IF(OR($F21<=0,(AZ$9-$A21)>(365*$E21)),0,IF($A21<=AZ$9,$F21/12,0)) -> 8.3333333 | BA21: =IF(OR($F21<=0,(BA$9-$A21)>(365*$E21)),0,IF($A21<=BA$9,$F21/12,0)) -> 8.3333333 | BB21: =IF(OR($F21<=0,(BB$9-$A21)>(365*$E21)),0,IF($A21<=BB$9,$F21/12,0)) -> 8.3333333 | BC21: =IF(OR($F21<=0,(BC$9-$A21)>(365*$E21)),0,IF($A21<=BC$9,$F21/12,0)) -> 8.3333333 | BD21: =IF(OR($F21<=0,(BD$9-$A21)>(365*$E21)),0,IF($A21<=BD$9,$F21/12,0)) -> 8.3333333 | ... BH21: =IF(OR($F21<=0,(BH$9-$A21)>(365*$E21)),0,IF($A21<=BH$9,$F21/12,0)) -> 8.3333333 | BI21: =SUM(AW21:BH21) -> 100 | BJ21: =IF(AND($BH$9>$A21,$BI21<>0),$D21-$S21-$AG21-$AU21-$BI21,0) -> 900 | BK21: =IF(OR($BJ21<=0,(BK$9-$A21)>($E21*365)),0,IF($A21<=BK$9,$F21/12)) -> 8.3333333 | BL21: =IF(OR($BJ21<=0,(BL$9-$A21)>($E21*365)),0,IF($A21<=BL$9,$F21/12)) -> 8.3333333 | BM21: =IF(OR($BJ21<=0,(BM$9-$A21)>($E21*365)),0,IF($A21<=BM$9,$F21/12)) -> 8.3333333 | BN21: =IF(OR($BJ21<=0,(BN$9-$A21)>($E21*365)),0,IF($A21<=BN$9,$F21/12)) -> 8.3333333 | BO21: =IF(OR($BJ21<=0,(BO$9-$A21)>($E21*365)),0,IF($A21<=BO$9,$F21/12)) -> 8.3333333 | BP21: =IF(OR($BJ21<=0,(BP$9-$A21)>($E21*365)),0,IF($A21<=BP$9,$F21/12)) -> 8.3333333 | BQ21: =IF(OR($BJ21<=0,(BQ$9-$A21)>($E21*365)),0,IF($A21<=BQ$9,$F21/12)) -> 8.3333333 | BR21: =IF(OR($BJ21<=0,(BR$9-$A21)>($E21*365)),0,IF($A21<=BR$9,$F21/12)) -> 8.3333333 | ... BV21: =IF(OR($BJ21<=0,(BV$9-$A21)>($E21*365)),0,IF($A21<=BV$9,$F21/12)) -> 8.3333333 | BW21: =SUM(BK21:BV21) -> 100 | BX21: =IF(AND($BV$9>$A21,$BW21<>0),$D21-$S21-$AG21-$AU21-$BI21-$BW21,0) -> 800 | BY21: =IF(OR($BX21<=0,(BY$9-$A21)>($E21*365)),0,IF($A21<=BY$9,$F21/12)) -> 8.3333333 | BZ21: =IF(OR($BX21<=0,(BZ$9-$A21)>($E21*365)),0,IF($A21<=BZ$9,$F21/12)) -> 8.3333333 | CA21: =IF(OR($BX21<=0,(CA$9-$A21)>($E21*365)),0,IF($A21<=CA$9,$F21/12)) -> 8.3333333 | CB21: =IF(OR($BX21<=0,(CB$9-$A21)>($E21*365)),0,IF($A21<=CB$9,$F21/12)) -> 8.3333333 | CC21: =IF(OR($BX21<=0,(CC$9-$A21)>($E21*365)),0,IF($A21<=CC$9,$F21/12)) -> 8.3333333 | CD21: =IF(OR($BX21<=0,(CD$9-$A21)>($E21*365)),0,IF($A21<=CD$9,$F21/12)) -> 8.3333333 | CE21: =IF(OR($BX21<=0,(CE$9-$A21)>($E21*365)),0,IF($A21<=CE$9,$F21/12)) -> 8.3333333 | CF21: =IF(OR($BX21<=0,(CF$9-$A21)>($E21*365)),0,IF($A21<=CF$9,$F21/12)) -> 8.3333333 | ... CJ21: =IF(OR($BX21<=0,(CJ$9-$A21)>($E21*365)),0,IF($A21<=CJ$9,$F21/12)) -> 8.3333333 | CK21: =SUM(BY21:CJ21) -> 100 | CL21: =IF(AND($CJ$9>$A21,$CK21<>0),$D21-$S21-$AG21-$AU21-$BI21-$BW21-$CK$10,0) -> -533.33333 | CM21: =IF(OR($CL21<=0,(CM$9-$A21)>($E21*365)),0,IF($A21<=CM$9,$F21/12)) -> 0 | CN21: =IF(OR($CL21<=0,(CN$9-$A21)>($E21*365)),0,IF($A21<=CN$9,$F21/12)) -> 0 | CO21: =IF(OR($CL21<=0,(CO$9-$A21)>($E21*365)),0,IF($A21<=CO$9,$F21/12)) -> 0 | CP21: =IF(OR($CL21<=0,(CP$9-$A21)>($E21*365)),0,IF($A21<=CP$9,$F21/12)) -> 0 | CQ21: =IF(OR($CL21<=0,(CQ$9-$A21)>($E21*365)),0,IF($A21<=CQ$9,$F21/12)) -> 0 | CR21: =IF(OR($CL21<=0,(CR$9-$A21)>($E21*365)),0,IF($A21<=CR$9,$F21/12)) -> 0 | CS21: =IF(OR($CL21<=0,(CS$9-$A21)>($E21*365)),0,IF($A21<=CS$9,$F21/12)) -> 0 | CT21: =IF(OR($CL21<=0,(CT$9-$A21)>($E21*365)),0,IF($A21<=CT$9,$F21/12)) -> 0 | ... CX21: =IF(OR($CL21<=0,(CX$9-$A21)>($E21*365)),0,IF($A21<=CX$9,$F21/12)) -> 0 | CY21: =SUM(CM21:CX21) -> 0 | CZ21: =IF(AND($CX$9>$A21,$CY21<>0),$D21-$S21-$AG21-$AU21-$BI21-$BW21-$CK21-$CY21,0) -> 0 | DA21: =IF(OR($CZ21<=0,(DA$9-$A21)>($E21*365)),0,IF($A21<=DA$9,$F21/12)) -> 0 | DB21: =IF(OR($CZ21<=0,(DB$9-$A21)>($E21*365)),0,IF($A21<=DB$9,$F21/12)) -> 0 | DC21: =IF(OR($CZ21<=0,(DC$9-$A21)>($E21*365)),0,IF($A21<=DC$9,$F21/12)) -> 0 | DD21: =IF(OR($CZ21<=0,(DD$9-$A21)>($E21*365)),0,IF($A21<=DD$9,$F21/12)) -> 0 | DE21: =IF(OR($CZ21<=0,(DE$9-$A21)>($E21*365)),0,IF($A21<=DE$9,$F21/12)) -> 0 | DF21: =IF(OR($CZ21<=0,(DF$9-$A21)>($E21*365)),0,IF($A21<=DF$9,$F21/12)) -> 0 | DG21: =IF(OR($CZ21<=0,(DG$9-$A21)>($E21*365)),0,IF($A21<=DG$9,$F21/12)) -> 0 | DH21: =IF(OR($CZ21<=0,(DH$9-$A21)>($E21*365)),0,IF($A21<=DH$9,$F21/12)) -> 0 | ... DL21: =IF(OR($CZ21<=0,(DL$9-$A21)>($E21*365)),0,IF($A21<=DL$9,$F21/12)) -> 0 | DM21: =SUM(DA21:DL21) -> 0 | DN21: =IF(AND($DL$9>$A21,$DM21<>0),$D21-$S21-$AG21-$AU21-$BI21-$BW21-$CK$10-$CY21-$DM21,0) -> 0 | DO21: =IF(OR($DN21<=0,(DO$9-$A21)>($E21*365)),0,IF($A21<=DO$9,$F21/12)) -> 0 | DP21: =IF(OR($DN21<=0,(DP$9-$A21)>($E21*365)),0,IF($A21<=DP$9,$F21/12)) -> 0 | DQ21: =IF(OR($DN21<=0,(DQ$9-$A21)>($E21*365)),0,IF($A21<=DQ$9,$F21/12)) -> 0 | DR21: =IF(OR($DN21<=0,(DR$9-$A21)>($E21*365)),0,IF($A21<=DR$9,$F21/12)) -> 0 | DS21: =IF(OR($DN21<=0,(DS$9-$A21)>($E21*365)),0,IF($A21<=DS$9,$F21/12)) -> 0 | DT21: =IF(OR($DN21<=0,(DT$9-$A21)>($E21*365)),0,IF($A21<=DT$9,$F21/12)) -> 0 | DU21: =IF(OR($DN21<=0,(DU$9-$A21)>($E21*365)),0,IF($A21<=DU$9,$F21/12)) -> 0 | DV21: =IF(OR($DN21<=0,(DV$9-$A21)>($E21*365)),0,IF($A21<=DV$9,$F21/12)) -> 0 | ... DZ21: =IF(OR($DN21<=0,(DZ$9-$A21)>($E21*365)),0,IF($A21<=DZ$9,$F21/12)) -> 0 | EA21: =SUM(DO21:DZ21) -> 0 | EB21: =IF(AND($DZ$9>$A21,$EA21<>0),$D21-$S21-$AG21-$AU21-$BI21-$BW21--CY21-$DM21-$CK21-$EA21,0) -> 0
... A27: 43083 | B27: Matériels | C27: couboire boucle bébé | D27: 13000 | E27: 5 | F27: =D27/E27 -> 2600 | G27: =IF(OR($F27<=0,(G$9-$A27)>(365*$E27)),0,IF($A27<=G$9,$F27/12,0)) -> 0 | H27: =IF(OR($F27<=0,(H$9-$A27)>(365*$E27)),0,IF($A27<=H$9,$F27/12,0)) -> 0 | I27: =IF(OR($F27<=0,(I$9-$A27)>(365*$E27)),0,IF($A27<=I$9,$F27/12,0)) -> 0 | J27: =IF(OR($F27<=0,(J$9-$A27)>(365*$E27)),0,IF($A27<=J$9,$F27/12,0)) -> 0 | K27: =IF(OR($F27<=0,(K$9-$A27)>(365*$E27)),0,IF($A27<=K$9,$F27/12,0)) -> 0 | L27: =IF(OR($F27<=0,(L$9-$A27)>(365*$E27)),0,IF($A27<=L$9,$F27/12,0)) -> 0 | M27: =IF(OR($F27<=0,(M$9-$A27)>(365*$E27)),0,IF($A27<=M$9,$F27/12,0)) -> 0 | N27: =IF(OR($F27<=0,(N$9-$A27)>(365*$E27)),0,IF($A27<=N$9,$F27/12,0)) -> 0 | ... R27: =IF(OR($F27<=0,(R$9-$A27)>(365*$E27)),0,IF($A27<=R$9,$F27/12,0)) -> 0 | S27: =SUM(G27:R27) -> 0 | T27: =IF(AND($R$9>A27,$S27<>0),$D27-$S27,0) -> 0 | U27: =IF(OR($F27<=0,(U$9-$A27)>(365*$E27)),0,IF($A27<=U$9,$F27/12,0)) -> 0 | V27: =IF(OR($F27<=0,(V$9-$A27)>(365*$E27)),0,IF($A27<=V$9,$F27/12,0)) -> 0 | W27: =IF(OR($F27<=0,(W$9-$A27)>(365*$E27)),0,IF($A27<=W$9,$F27/12,0)) -> 0 | X27: =IF(OR($F27<=0,(X$9-$A27)>(365*$E27)),0,IF($A27<=X$9,$F27/12,0)) -> 0 | Y27: =IF(OR($F27<=0,(Y$9-$A27)>(365*$E27)),0,IF($A27<=Y$9,$F27/12,0)) -> 0 | Z27: =IF(OR($F27<=0,(Z$9-$A27)>(365*$E27)),0,IF($A27<=Z$9,$F27/12,0)) -> 0 | AA27: =IF(OR($F27<=0,(AA$9-$A27)>(365*$E27)),0,IF($A27<=AA$9,$F27/12,0)) -> 0 | AB27: =IF(OR($F27<=0,(AB$9-$A27)>(365*$E27)),0,IF($A27<=AB$9,$F27/12,0)) -> 0 | ... AF27: =IF(OR($F27<=0,(AF$9-$A27)>(365*$E27)),0,IF($A27<=AF$9,$F27/12,0)) -> 0 | AG27: =SUM(U27:AF27) -> 0 | AH27: =IF(AND($AF$9>$A27,$AG27<>0),$D27-$S27-$AG27,0) -> 0 | AI27: =IF(OR($F27<=0,(AI$9-$A27)>(365*$E27)),0,IF($A27<=AI$9,$F27/12,0)) -> 0 | AJ27: =IF(OR($F27<=0,(AJ$9-$A27)>(365*$E27)),0,IF($A27<=AJ$9,$F27/12,0)) -> 0 | AK27: =IF(OR($F27<=0,(AK$9-$A27)>(365*$E27)),0,IF($A27<=AK$9,$F27/12,0)) -> 0 | AL27: =IF(OR($F27<=0,(AL$9-$A27)>(365*$E27)),0,IF($A27<=AL$9,$F27/12,0)) -> 0 | AM27: =IF(OR($F27<=0,(AM$9-$A27)>(365*$E27)),0,IF($A27<=AM$9,$F27/12,0)) -> 0 | AN27: =IF(OR($F27<=0,(AN$9-$A27)>(365*$E27)),0,IF($A27<=AN$9,$F27/12,0)) -> 0 | AO27: =IF(OR($F27<=0,(AO$9-$A27)>(365*$E27)),0,IF($A27<=AO$9,$F27/12,0)) -> 0 | AP27: =IF(OR($F27<=0,(AP$9-$A27)>(365*$E27)),0,IF($A27<=AP$9,$F27/12,0)) -> 0 | ... AT27: =IF(OR($F27<=0,(AT$9-$A27)>(365*$E27)),0,IF($A27<=AT$9,$F27/12,0)) -> 0 | AU27: =SUM(AI27:AT27) -> 0 | AV27: =IF(AND($AT$9>$A27,$AU27<>0),$D27-$S27-$AG27-$AU27,0) -> 0 | AW27: =IF(OR($F27<=0,(AW$9-$A27)>(365*$E27)),0,IF($A27<=AW$9,$F27/12,0)) -> 0 | AX27: =IF(OR($F27<=0,(AX$9-$A27)>(365*$E27)),0,IF($A27<=AX$9,$F27/12,0)) -> 216.66667 | AY27: =IF(OR($F27<=0,(AY$9-$A27)>(365*$E27)),0,IF($A27<=AY$9,$F27/12,0)) -> 216.66667 | AZ27: =IF(OR($F27<=0,(AZ$9-$A27)>(365*$E27)),0,IF($A27<=AZ$9,$F27/12,0)) -> 216.66667 | BA27: =IF(OR($F27<=0,(BA$9-$A27)>(365*$E27)),0,IF($A27<=BA$9,$F27/12,0)) -> 216.66667 | BB27: =IF(OR($F27<=0,(BB$9-$A27)>(365*$E27)),0,IF($A27<=BB$9,$F27/12,0)) -> 216.66667 | BC27: =IF(OR($F27<=0,(BC$9-$A27)>(365*$E27)),0,IF($A27<=BC$9,$F27/12,0)) -> 216.66667 | BD27: =IF(OR($F27<=0,(BD$9-$A27)>(365*$E27)),0,IF($A27<=BD$9,$F27/12,0)) -> 216.66667 | ... BH27: =IF(OR($F27<=0,(BH$9-$A27)>(365*$E27)),0,IF($A27<=BH$9,$F27/12,0)) -> 216.66667 | BI27: =SUM(AW27:BH27) -> 2383.3333 | BJ27: =IF(AND($BH$9>$A27,$BI27<>0),$D27-$S27-$AG27-$AU27-$BI27,0) -> 10616.667 | BK27: =IF(OR($BJ27<=0,(BK$9-$A27)>($E27*365)),0,IF($A27<=BK$9,$F27/12)) -> 216.66667 | BL27: =IF(OR($BJ27<=0,(BL$9-$A27)>($E27*365)),0,IF($A27<=BL$9,$F27/12)) -> 216.66667 | BM27: =IF(OR($BJ27<=0,(BM$9-$A27)>($E27*365)),0,IF($A27<=BM$9,$F27/12)) -> 216.66667 | BN27: =IF(OR($BJ27<=0,(BN$9-$A27)>($E27*365)),0,IF($A27<=BN$9,$F27/12)) -> 216.66667 | BO27: =IF(OR($BJ27<=0,(BO$9-$A27)>($E27*365)),0,IF($A27<=BO$9,$F27/12)) -> 216.66667 | BP27: =IF(OR($BJ27<=0,(BP$9-$A27)>($E27*365)),0,IF($A27<=BP$9,$F27/12)) -> 216.66667 | BQ27: =IF(OR($BJ27<=0,(BQ$9-$A27)>($E27*365)),0,IF($A27<=BQ$9,$F27/12)) -> 216.66667 | BR27: =IF(OR($BJ27<=0,(BR$9-$A27)>($E27*365)),0,IF($A27<=BR$9,$F27/12)) -> 216.66667 | ... BV27: =IF(OR($BJ27<=0,(BV$9-$A27)>($E27*365)),0,IF($A27<=BV$9,$F27/12)) -> 216.66667 | BW27: =SUM(BK27:BV27) -> 2600 | BX27: =IF(AND($BV$9>$A27,$BW27<>0),$D27-$S27-$AG27-$AU27-$BI27-$BW27,0) -> 8016.6667 | BY27: =IF(OR($BX27<=0,(BY$9-$A27)>($E27*365)),0,IF($A27<=BY$9,$F27/12)) -> 216.66667 | BZ27: =IF(OR($BX27<=0,(BZ$9-$A27)>($E27*365)),0,IF($A27<=BZ$9,$F27/12)) -> 216.66667 | CA27: =IF(OR($BX27<=0,(CA$9-$A27)>($E27*365)),0,IF($A27<=CA$9,$F27/12)) -> 216.66667 | CB27: =IF(OR($BX27<=0,(CB$9-$A27)>($E27*365)),0,IF($A27<=CB$9,$F27/12)) -> 216.66667 | CC27: =IF(OR($BX27<=0,(CC$9-$A27)>($E27*365)),0,IF($A27<=CC$9,$F27/12)) -> 216.66667 | CD27: =IF(OR($BX27<=0,(CD$9-$A27)>($E27*365)),0,IF($A27<=CD$9,$F27/12)) -> 216.66667 | CE27: =IF(OR($BX27<=0,(CE$9-$A27)>($E27*365)),0,IF($A27<=CE$9,$F27/12)) -> 216.66667 | CF27: =IF(OR($BX27<=0,(CF$9-$A27)>($E27*365)),0,IF($A27<=CF$9,$F27/12)) -> 216.66667 | ... CJ27: =IF(OR($BX27<=0,(CJ$9-$A27)>($E27*365)),0,IF($A27<=CJ$9,$F27/12)) -> 216.66667 | CK27: =SUM(BY27:CJ27) -> 2600 | CL27: =IF(AND($CJ$9>$A27,$CK27<>0),$D27-$S27-$AG27-$AU27-$BI27-$BW27-$CK$10,0) -> 6683.3333 | CM27: =IF(OR($CL27<=0,(CM$9-$A27)>($E27*365)),0,IF($A27<=CM$9,$F27/12)) -> 216.66667 | CN27: =IF(OR($CL27<=0,(CN$9-$A27)>($E27*365)),0,IF($A27<=CN$9,$F27/12)) -> 216.66667 | CO27: =IF(OR($CL27<=0,(CO$9-$A27)>($E27*365)),0,IF($A27<=CO$9,$F27/12)) -> 216.66667 | CP27: =IF(OR($CL27<=0,(CP$9-$A27)>($E27*365)),0,IF($A27<=CP$9,$F27/12)) -> 216.66667 | CQ27: =IF(OR($CL27<=0,(CQ$9-$A27)>($E27*365)),0,IF($A27<=CQ$9,$F27/12)) -> 216.66667 | CR27: =IF(OR($CL27<=0,(CR$9-$A27)>($E27*365)),0,IF($A27<=CR$9,$F27/12)) -> 216.66667 | CS27: =IF(OR($CL27<=0,(CS$9-$A27)>($E27*365)),0,IF($A27<=CS$9,$F27/12)) -> 216.66667 | CT27: =IF(OR($CL27<=0,(CT$9-$A27)>($E27*365)),0,IF($A27<=CT$9,$F27/12)) -> 216.66667 | ... CX27: =IF(OR($CL27<=0,(CX$9-$A27)>($E27*365)),0,IF($A27<=CX$9,$F27/12)) -> 216.66667 | CY27: =SUM(CM27:CX27) -> 2600 | CZ27: =IF(AND($CX$9>$A27,$CY27<>0),$D27-$S27-$AG27-$AU27-$BI27-$BW27-$CK27-$CY27,0) -> 2816.6667 | DA27: =IF(OR($CZ27<=0,(DA$9-$A27)>($E27*365)),0,IF($A27<=DA$9,$F27/12)) -> 216.66667 | DB27: =IF(OR($CZ27<=0,(DB$9-$A27)>($E27*365)),0,IF($A27<=DB$9,$F27/12)) -> 216.66667 | DC27: =IF(OR($CZ27<=0,(DC$9-$A27)>($E27*365)),0,IF($A27<=DC$9,$F27/12)) -> 216.66667 | DD27: =IF(OR($CZ27<=0,(DD$9-$A27)>($E27*365)),0,IF($A27<=DD$9,$F27/12)) -> 216.66667 | DE27: =IF(OR($CZ27<=0,(DE$9-$A27)>($E27*365)),0,IF($A27<=DE$9,$F27/12)) -> 216.66667 | DF27: =IF(OR($CZ27<=0,(DF$9-$A27)>($E27*365)),0,IF($A27<=DF$9,$F27/12)) -> 216.66667 | DG27: =IF(OR($CZ27<=0,(DG$9-$A27)>($E27*365)),0,IF($A27<=DG$9,$F27/12)) -> 216.66667 | DH27: =IF(OR($CZ27<=0,(DH$9-$A27)>($E27*365)),0,IF($A27<=DH$9,$F27/12)) -> 216.66667 | ... DL27: =IF(OR($CZ27<=0,(DL$9-$A27)>($E27*365)),0,IF($A27<=DL$9,$F27/12)) -> 216.66667 | DM27: =SUM(DA27:DL27) -> 2600 | DN27: =IF(AND($DL$9>$A27,$DM27<>0),$D27-$S27-$AG27-$AU27-$BI27-$BW27-$CK$10-$CY27-$DM27,0) -> 1483.3333 | DO27: =IF(OR($DN27<=0,(DO$9-$A27)>($E27*365)),0,IF($A27<=DO$9,$F27/12)) -> 216.66667 | DP27: =IF(OR($DN27<=0,(DP$9-$A27)>($E27*365)),0,IF($A27<=DP$9,$F27/12)) -> 0 | DQ27: =IF(OR($DN27<=0,(DQ$9-$A27)>($E27*365)),0,IF($A27<=DQ$9,$F27/12)) -> 0 | DR27: =IF(OR($DN27<=0,(DR$9-$A27)>($E27*365)),0,IF($A27<=DR$9,$F27/12)) -> 0 | DS27: =IF(OR($DN27<=0,(DS$9-$A27)>($E27*365)),0,IF($A27<=DS$9,$F27/12)) -> 0 | DT27: =IF(OR($DN27<=0,(DT$9-$A27)>($E27*365)),0,IF($A27<=DT$9,$F27/12)) -> 0 | DU27: =IF(OR($DN27<=0,(DU$9-$A27)>($E27*365)),0,IF($A27<=DU$9,$F27/12)) -> 0 | DV27: =IF(OR($DN27<=0,(DV$9-$A27)>($E27*365)),0,IF($A27<=DV$9,$F27/12)) -> 0 | ... DZ27: =IF(OR($DN27<=0,(DZ$9-$A27)>($E27*365)),0,IF($A27<=DZ$9,$F27/12)) -> 0 | EA27: =SUM(DO27:DZ27) -> 216.66667 | EB27: =IF(AND($DZ$9>$A27,$EA27<>0),$D27-$S27-$AG27-$AU27-$BI27-$BW27--CY27-$DM27-$CK27-$EA27,0) -> 5200
A28: 43086 | B28: Matériels | C28: chaises | D28: 1400 | E28: 3
A29: 43088 | B29: Matériels | C29: pence coupente | D29: 380 | E29: 3 | F29: =D29/E29 -> 126.66667 | G29: =IF(OR($F29<=0,(G$9-$A29)>(365*$E29)),0,IF($A29<=G$9,$F29/12,0)) -> 0 | H29: =IF(OR($F29<=0,(H$9-$A29)>(365*$E29)),0,IF($A29<=H$9,$F29/12,0)) -> 0 | I29: =IF(OR($F29<=0,(I$9-$A29)>(365*$E29)),0,IF($A29<=I$9,$F29/12,0)) -> 0 | J29: =IF(OR($F29<=0,(J$9-$A29)>(365*$E29)),0,IF($A29<=J$9,$F29/12,0)) -> 0 | K29: =IF(OR($F29<=0,(K$9-$A29)>(365*$E29)),0,IF($A29<=K$9,$F29/12,0)) -> 0 | L29: =IF(OR($F29<=0,(L$9-$A29)>(365*$E29)),0,IF($A29<=L$9,$F29/12,0)) -> 0 | M29: =IF(OR($F29<=0,(M$9-$A29)>(365*$E29)),0,IF($A29<=M$9,$F29/12,0)) -> 0 | N29: =IF(OR($F29<=0,(N$9-$A29)>(365*$E29)),0,IF($A29<=N$9,$F29/12,0)) -> 0 | ... R29: =IF(OR($F29<=0,(R$9-$A29)>(365*$E29)),0,IF($A29<=R$9,$F29/12,0)) -> 0 | S29: =SUM(G29:R29) -> 0 | T29: =IF(AND($R$9>A29,$S29<>0),$D29-$S29,0) -> 0 | U29: =IF(OR($F29<=0,(U$9-$A29)>(365*$E29)),0,IF($A29<=U$9,$F29/12,0)) -> 0 | V29: =IF(OR($F29<=0,(V$9-$A29)>(365*$E29)),0,IF($A29<=V$9,$F29/12,0)) -> 0 | W29: =IF(OR($F29<=0,(W$9-$A29)>(365*$E29)),0,IF($A29<=W$9,$F29/12,0)) -> 0 | X29: =IF(OR($F29<=0,(X$9-$A29)>(365*$E29)),0,IF($A29<=X$9,$F29/12,0)) -> 0 | Y29: =IF(OR($F29<=0,(Y$9-$A29)>(365*$E29)),0,IF($A29<=Y$9,$F29/12,0)) -> 0 | Z29: =IF(OR($F29<=0,(Z$9-$A29)>(365*$E29)),0,IF($A29<=Z$9,$F29/12,0)) -> 0 | AA29: =IF(OR($F29<=0,(AA$9-$A29)>(365*$E29)),0,IF($A29<=AA$9,$F29/12,0)) -> 0 | AB29: =IF(OR($F29<=0,(AB$9-$A29)>(365*$E29)),0,IF($A29<=AB$9,$F29/12,0)) -> 0 | ... AF29: =IF(OR($F29<=0,(AF$9-$A29)>(365*$E29)),0,IF($A29<=AF$9,$F29/12,0)) -> 0 | AG29: =SUM(U29:AF29) -> 0 | AH29: =IF(AND($AF$9>$A29,$AG29<>0),$D29-$S29-$AG29,0) -> 0 | AI29: =IF(OR($F29<=0,(AI$9-$A29)>(365*$E29)),0,IF($A29<=AI$9,$F29/12,0)) -> 0 | AJ29: =IF(OR($F29<=0,(AJ$9-$A29)>(365*$E29)),0,IF($A29<=AJ$9,$F29/12,0)) -> 0 | AK29: =IF(OR($F29<=0,(AK$9-$A29)>(365*$E29)),0,IF($A29<=AK$9,$F29/12,0)) -> 0 | AL29: =IF(OR($F29<=0,(AL$9-$A29)>(365*$E29)),0,IF($A29<=AL$9,$F29/12,0)) -> 0 | AM29: =IF(OR($F29<=0,(AM$9-$A29)>(365*$E29)),0,IF($A29<=AM$9,$F29/12,0)) -> 0 | AN29: =IF(OR($F29<=0,(AN$9-$A29)>(365*$E29)),0,IF($A29<=AN$9,$F29/12,0)) -> 0 | AO29: =IF(OR($F29<=0,(AO$9-$A29)>(365*$E29)),0,IF($A29<=AO$9,$F29/12,0)) -> 0 | AP29: =IF(OR($F29<=0,(AP$9-$A29)>(365*$E29)),0,IF($A29<=AP$9,$F29/12,0)) -> 0 | ... AT29: =IF(OR($F29<=0,(AT$9-$A29)>(365*$E29)),0,IF($A29<=AT$9,$F29/12,0)) -> 0 | AU29: =SUM(AI29:AT29) -> 0 | AV29: =IF(AND($AT$9>$A29,$AU29<>0),$D29-$S29-$AG29-$AU29,0) -> 0 | AW29: =IF(OR($F29<=0,(AW$9-$A29)>(365*$E29)),0,IF($A29<=AW$9,$F29/12,0)) -> 0 | AX29: =IF(OR($F29<=0,(AX$9-$A29)>(365*$E29)),0,IF($A29<=AX$9,$F29/12,0)) -> 10.555556 | AY29: =IF(OR($F29<=0,(AY$9-$A29)>(365*$E29)),0,IF($A29<=AY$9,$F29/12,0)) -> 10.555556 | AZ29: =IF(OR($F29<=0,(AZ$9-$A29)>(365*$E29)),0,IF($A29<=AZ$9,$F29/12,0)) -> 10.555556 | BA29: =IF(OR($F29<=0,(BA$9-$A29)>(365*$E29)),0,IF($A29<=BA$9,$F29/12,0)) -> 10.555556 | BB29: =IF(OR($F29<=0,(BB$9-$A29)>(365*$E29)),0,IF($A29<=BB$9,$F29/12,0)) -> 10.555556 | BC29: =IF(OR($F29<=0,(BC$9-$A29)>(365*$E29)),0,IF($A29<=BC$9,$F29/12,0)) -> 10.555556 | BD29: =IF(OR($F29<=0,(BD$9-$A29)>(365*$E29)),0,IF($A29<=BD$9,$F29/12,0)) -> 10.555556 | ... BH29: =IF(OR($F29<=0,(BH$9-$A29)>(365*$E29)),0,IF($A29<=BH$9,$F29/12,0)) -> 10.555556 | BI29: =SUM(AW29:BH29) -> 116.11111 | BJ29: =IF(AND($BH$9>$A29,$BI29<>0),$D29-$S29-$AG29-$AU29-$BI29,0) -> 263.88889 | BK29: =IF(OR($BJ29<=0,(BK$9-$A29)>($E29*365)),0,IF($A29<=BK$9,$F29/12)) -> 10.555556 | BL29: =IF(OR($BJ29<=0,(BL$9-$A29)>($E29*365)),0,IF($A29<=BL$9,$F29/12)) -> 10.555556 | BM29: =IF(OR($BJ29<=0,(BM$9-$A29)>($E29*365)),0,IF($A29<=BM$9,$F29/12)) -> 10.555556 | BN29: =IF(OR($BJ29<=0,(BN$9-$A29)>($E29*365)),0,IF($A29<=BN$9,$F29/12)) -> 10.555556 | BO29: =IF(OR($BJ29<=0,(BO$9-$A29)>($E29*365)),0,IF($A29<=BO$9,$F29/12)) -> 10.555556 | BP29: =IF(OR($BJ29<=0,(BP$9-$A29)>($E29*365)),0,IF($A29<=BP$9,$F29/12)) -> 10.555556 | BQ29: =IF(OR($BJ29<=0,(BQ$9-$A29)>($E29*365)),0,IF($A29<=BQ$9,$F29/12)) -> 10.555556 | BR29: =IF(OR($BJ29<=0,(BR$9-$A29)>($E29*365)),0,IF($A29<=BR$9,$F29/12)) -> 10.555556 | ... BV29: =IF(OR($BJ29<=0,(BV$9-$A29)>($E29*365)),0,IF($A29<=BV$9,$F29/12)) -> 10.555556 | BW29: =SUM(BK29:BV29) -> 126.66667 | BX29: =IF(AND($BV$9>$A29,$BW29<>0),$D29-$S29-$AG29-$AU29-$BI29-$BW29,0) -> 137.22222 | BY29: =IF(OR($BX29<=0,(BY$9-$A29)>($E29*365)),0,IF($A29<=BY$9,$F29/12)) -> 10.555556 | BZ29: =IF(OR($BX29<=0,(BZ$9-$A29)>($E29*365)),0,IF($A29<=BZ$9,$F29/12)) -> 10.555556 | CA29: =IF(OR($BX29<=0,(CA$9-$A29)>($E29*365)),0,IF($A29<=CA$9,$F29/12)) -> 10.555556 | CB29: =IF(OR($BX29<=0,(CB$9-$A29)>($E29*365)),0,IF($A29<=CB$9,$F29/12)) -> 10.555556 | CC29: =IF(OR($BX29<=0,(CC$9-$A29)>($E29*365)),0,IF($A29<=CC$9,$F29/12)) -> 10.555556 | CD29: =IF(OR($BX29<=0,(CD$9-$A29)>($E29*365)),0,IF($A29<=CD$9,$F29/12)) -> 10.555556 | CE29: =IF(OR($BX29<=0,(CE$9-$A29)>($E29*365)),0,IF($A29<=CE$9,$F29/12)) -> 10.555556 | CF29: =IF(OR($BX29<=0,(CF$9-$A29)>($E29*365)),0,IF($A29<=CF$9,$F29/12)) -> 10.555556 | ... CJ29: =IF(OR($BX29<=0,(CJ$9-$A29)>($E29*365)),0,IF($A29<=CJ$9,$F29/12)) -> 10.555556 | CK29: =SUM(BY29:CJ29) -> 126.66667 | CL29: =IF(AND($CJ$9>$A29,$CK29<>0),$D29-$S29-$AG29-$AU29-$BI29-$BW29-$CK$10,0) -> -1196.1111 | CM29: =IF(OR($CL29<=0,(CM$9-$A29)>($E29*365)),0,IF($A29<=CM$9,$F29/12)) -> 0 | CN29: =IF(OR($CL29<=0,(CN$9-$A29)>($E29*365)),0,IF($A29<=CN$9,$F29/12)) -> 0 | CO29: =IF(OR($CL29<=0,(CO$9-$A29)>($E29*365)),0,IF($A29<=CO$9,$F29/12)) -> 0 | CP29: =IF(OR($CL29<=0,(CP$9-$A29)>($E29*365)),0,IF($A29<=CP$9,$F29/12)) -> 0 | CQ29: =IF(OR($CL29<=0,(CQ$9-$A29)>($E29*365)),0,IF($A29<=CQ$9,$F29/12)) -> 0 | CR29: =IF(OR($CL29<=0,(CR$9-$A29)>($E29*365)),0,IF($A29<=CR$9,$F29/12)) -> 0 | CS29: =IF(OR($CL29<=0,(CS$9-$A29)>($E29*365)),0,IF($A29<=CS$9,$F29/12)) -> 0 | CT29: =IF(OR($CL29<=0,(CT$9-$A29)>($E29*365)),0,IF($A29<=CT$9,$F29/12)) -> 0 | ... CX29: =IF(OR($CL29<=0,(CX$9-$A29)>($E29*365)),0,IF($A29<=CX$9,$F29/12)) -> 0 | CY29: =SUM(CM29:CX29) -> 0 | CZ29: =IF(AND($CX$9>$A29,$CY29<>0),$D29-$S29-$AG29-$AU29-$BI29-$BW29-$CK29-$CY29,0) -> 0 | DA29: =IF(OR($CZ29<=0,(DA$9-$A29)>($E29*365)),0,IF($A29<=DA$9,$F29/12)) -> 0 | DB29: =IF(OR($CZ29<=0,(DB$9-$A29)>($E29*365)),0,IF($A29<=DB$9,$F29/12)) -> 0 | DC29: =IF(OR($CZ29<=0,(DC$9-$A29)>($E29*365)),0,IF($A29<=DC$9,$F29/12)) -> 0 | DD29: =IF(OR($CZ29<=0,(DD$9-$A29)>($E29*365)),0,IF($A29<=DD$9,$F29/12)) -> 0 | DE29: =IF(OR($CZ29<=0,(DE$9-$A29)>($E29*365)),0,IF($A29<=DE$9,$F29/12)) -> 0 | DF29: =IF(OR($CZ29<=0,(DF$9-$A29)>($E29*365)),0,IF($A29<=DF$9,$F29/12)) -> 0 | DG29: =IF(OR($CZ29<=0,(DG$9-$A29)>($E29*365)),0,IF($A29<=DG$9,$F29/12)) -> 0 | DH29: =IF(OR($CZ29<=0,(DH$9-$A29)>($E29*365)),0,IF($A29<=DH$9,$F29/12)) -> 0 | ... DL29: =IF(OR($CZ29<=0,(DL$9-$A29)>($E29*365)),0,IF($A29<=DL$9,$F29/12)) -> 0 | DM29: =SUM(DA29:DL29) -> 0 | DN29: =IF(AND($DL$9>$A29,$DM29<>0),$D29-$S29-$AG29-$AU29-$BI29-$BW29-$CK$10-$CY29-$DM29,0) -> 0 | DO29: =IF(OR($DN29<=0,(DO$9-$A29)>($E29*365)),0,IF($A29<=DO$9,$F29/12)) -> 0 | DP29: =IF(OR($DN29<=0,(DP$9-$A29)>($E29*365)),0,IF($A29<=DP$9,$F29/12)) -> 0 | DQ29: =IF(OR($DN29<=0,(DQ$9-$A29)>($E29*365)),0,IF($A29<=DQ$9,$F29/12)) -> 0 | DR29: =IF(OR($DN29<=0,(DR$9-$A29)>($E29*365)),0,IF($A29<=DR$9,$F29/12)) -> 0 | DS29: =IF(OR($DN29<=0,(DS$9-$A29)>($E29*365)),0,IF($A29<=DS$9,$F29/12)) -> 0 | DT29: =IF(OR($DN29<=0,(DT$9-$A29)>($E29*365)),0,IF($A29<=DT$9,$F29/12)) -> 0 | DU29: =IF(OR($DN29<=0,(DU$9-$A29)>($E29*365)),0,IF($A29<=DU$9,$F29/12)) -> 0 | DV29: =IF(OR($DN29<=0,(DV$9-$A29)>($E29*365)),0,IF($A29<=DV$9,$F29/12)) -> 0 | ... DZ29: =IF(OR($DN29<=0,(DZ$9-$A29)>($E29*365)),0,IF($A29<=DZ$9,$F29/12)) -> 0 | EA29: =SUM(DO29:DZ29) -> 0 | EB29: =IF(AND($DZ$9>$A29,$EA29<>0),$D29-$S29-$AG29-$AU29-$BI29-$BW29--CY29-$DM29-$CK29-$EA29,0) -> 0
A30: 43088 | B30: Matériels | C30: sésaille | D30: 100 | E30: 3 | F30: =D30/E30 -> 33.333333 | G30: =IF(OR($F30<=0,(G$9-$A30)>(365*$E30)),0,IF($A30<=G$9,$F30/12,0)) -> 0 | H30: =IF(OR($F30<=0,(H$9-$A30)>(365*$E30)),0,IF($A30<=H$9,$F30/12,0)) -> 0 | I30: =IF(OR($F30<=0,(I$9-$A30)>(365*$E30)),0,IF($A30<=I$9,$F30/12,0)) -> 0 | J30: =IF(OR($F30<=0,(J$9-$A30)>(365*$E30)),0,IF($A30<=J$9,$F30/12,0)) -> 0 | K30: =IF(OR($F30<=0,(K$9-$A30)>(365*$E30)),0,IF($A30<=K$9,$F30/12,0)) -> 0 | L30: =IF(OR($F30<=0,(L$9-$A30)>(365*$E30)),0,IF($A30<=L$9,$F30/12,0)) -> 0 | M30: =IF(OR($F30<=0,(M$9-$A30)>(365*$E30)),0,IF($A30<=M$9,$F30/12,0)) -> 0 | N30: =IF(OR($F30<=0,(N$9-$A30)>(365*$E30)),0,IF($A30<=N$9,$F30/12,0)) -> 0 | ... R30: =IF(OR($F30<=0,(R$9-$A30)>(365*$E30)),0,IF($A30<=R$9,$F30/12,0)) -> 0 | S30: =SUM(G30:R30) -> 0 | T30: =IF(AND($R$9>A30,$S30<>0),$D30-$S30,0) -> 0 | U30: =IF(OR($F30<=0,(U$9-$A30)>(365*$E30)),0,IF($A30<=U$9,$F30/12,0)) -> 0 | V30: =IF(OR($F30<=0,(V$9-$A30)>(365*$E30)),0,IF($A30<=V$9,$F30/12,0)) -> 0 | W30: =IF(OR($F30<=0,(W$9-$A30)>(365*$E30)),0,IF($A30<=W$9,$F30/12,0)) -> 0 | X30: =IF(OR($F30<=0,(X$9-$A30)>(365*$E30)),0,IF($A30<=X$9,$F30/12,0)) -> 0 | Y30: =IF(OR($F30<=0,(Y$9-$A30)>(365*$E30)),0,IF($A30<=Y$9,$F30/12,0)) -> 0 | Z30: =IF(OR($F30<=0,(Z$9-$A30)>(365*$E30)),0,IF($A30<=Z$9,$F30/12,0)) -> 0 | AA30: =IF(OR($F30<=0,(AA$9-$A30)>(365*$E30)),0,IF($A30<=AA$9,$F30/12,0)) -> 0 | AB30: =IF(OR($F30<=0,(AB$9-$A30)>(365*$E30)),0,IF($A30<=AB$9,$F30/12,0)) -> 0 | ... AF30: =IF(OR($F30<=0,(AF$9-$A30)>(365*$E30)),0,IF($A30<=AF$9,$F30/12,0)) -> 0 | AG30: =SUM(U30:AF30) -> 0 | AH30: =IF(AND($AF$9>$A30,$AG30<>0),$D30-$S30-$AG30,0) -> 0 | AI30: =IF(OR($F30<=0,(AI$9-$A30)>(365*$E30)),0,IF($A30<=AI$9,$F30/12,0)) -> 0 | AJ30: =IF(OR($F30<=0,(AJ$9-$A30)>(365*$E30)),0,IF($A30<=AJ$9,$F30/12,0)) -> 0 | AK30: =IF(OR($F30<=0,(AK$9-$A30)>(365*$E30)),0,IF($A30<=AK$9,$F30/12,0)) -> 0 | AL30: =IF(OR($F30<=0,(AL$9-$A30)>(365*$E30)),0,IF($A30<=AL$9,$F30/12,0)) -> 0 | AM30: =IF(OR($F30<=0,(AM$9-$A30)>(365*$E30)),0,IF($A30<=AM$9,$F30/12,0)) -> 0 | AN30: =IF(OR($F30<=0,(AN$9-$A30)>(365*$E30)),0,IF($A30<=AN$9,$F30/12,0)) -> 0 | AO30: =IF(OR($F30<=0,(AO$9-$A30)>(365*$E30)),0,IF($A30<=AO$9,$F30/12,0)) -> 0 | AP30: =IF(OR($F30<=0,(AP$9-$A30)>(365*$E30)),0,IF($A30<=AP$9,$F30/12,0)) -> 0 | ... AT30: =IF(OR($F30<=0,(AT$9-$A30)>(365*$E30)),0,IF($A30<=AT$9,$F30/12,0)) -> 0 | AU30: =SUM(AI30:AT30) -> 0 | AV30: =IF(AND($AT$9>$A30,$AU30<>0),$D30-$S30-$AG30-$AU30,0) -> 0 | AW30: =IF(OR($F30<=0,(AW$9-$A30)>(365*$E30)),0,IF($A30<=AW$9,$F30/12,0)) -> 0 | AX30: =IF(OR($F30<=0,(AX$9-$A30)>(365*$E30)),0,IF($A30<=AX$9,$F30/12,0)) -> 2.7777778 | AY30: =IF(OR($F30<=0,(AY$9-$A30)>(365*$E30)),0,IF($A30<=AY$9,$F30/12,0)) -> 2.7777778 | AZ30: =IF(OR($F30<=0,(AZ$9-$A30)>(365*$E30)),0,IF($A30<=AZ$9,$F30/12,0)) -> 2.7777778 | BA30: =IF(OR($F30<=0,(BA$9-$A30)>(365*$E30)),0,IF($A30<=BA$9,$F30/12,0)) -> 2.7777778 | BB30: =IF(OR($F30<=0,(BB$9-$A30)>(365*$E30)),0,IF($A30<=BB$9,$F30/12,0)) -> 2.7777778 | BC30: =IF(OR($F30<=0,(BC$9-$A30)>(365*$E30)),0,IF($A30<=BC$9,$F30/12,0)) -> 2.7777778 | BD30: =IF(OR($F30<=0,(BD$9-$A30)>(365*$E30)),0,IF($A30<=BD$9,$F30/12,0)) -> 2.7777778 | ... BH30: =IF(OR($F30<=0,(BH$9-$A30)>(365*$E30)),0,IF($A30<=BH$9,$F30/12,0)) -> 2.7777778 | BI30: =SUM(AW30:BH30) -> 30.555556 | BJ30: =IF(AND($BH$9>$A30,$BI30<>0),$D30-$S30-$AG30-$AU30-$BI30,0) -> 69.444444 | BK30: =IF(OR($BJ30<=0,(BK$9-$A30)>($E30*365)),0,IF($A30<=BK$9,$F30/12)) -> 2.7777778 | BL30: =IF(OR($BJ30<=0,(BL$9-$A30)>($E30*365)),0,IF($A30<=BL$9,$F30/12)) -> 2.7777778 | BM30: =IF(OR($BJ30<=0,(BM$9-$A30)>($E30*365)),0,IF($A30<=BM$9,$F30/12)) -> 2.7777778 | BN30: =IF(OR($BJ30<=0,(BN$9-$A30)>($E30*365)),0,IF($A30<=BN$9,$F30/12)) -> 2.7777778 | BO30: =IF(OR($BJ30<=0,(BO$9-$A30)>($E30*365)),0,IF($A30<=BO$9,$F30/12)) -> 2.7777778 | BP30: =IF(OR($BJ30<=0,(BP$9-$A30)>($E30*365)),0,IF($A30<=BP$9,$F30/12)) -> 2.7777778 | BQ30: =IF(OR($BJ30<=0,(BQ$9-$A30)>($E30*365)),0,IF($A30<=BQ$9,$F30/12)) -> 2.7777778 | BR30: =IF(OR($BJ30<=0,(BR$9-$A30)>($E30*365)),0,IF($A30<=BR$9,$F30/12)) -> 2.7777778 | ... BV30: =IF(OR($BJ30<=0,(BV$9-$A30)>($E30*365)),0,IF($A30<=BV$9,$F30/12)) -> 2.7777778 | BW30: =SUM(BK30:BV30) -> 33.333333 | BX30: =IF(AND($BV$9>$A30,$BW30<>0),$D30-$S30-$AG30-$AU30-$BI30-$BW30,0) -> 36.111111 | BY30: =IF(OR($BX30<=0,(BY$9-$A30)>($E30*365)),0,IF($A30<=BY$9,$F30/12)) -> 2.7777778 | BZ30: =IF(OR($BX30<=0,(BZ$9-$A30)>($E30*365)),0,IF($A30<=BZ$9,$F30/12)) -> 2.7777778 | CA30: =IF(OR($BX30<=0,(CA$9-$A30)>($E30*365)),0,IF($A30<=CA$9,$F30/12)) -> 2.7777778 | CB30: =IF(OR($BX30<=0,(CB$9-$A30)>($E30*365)),0,IF($A30<=CB$9,$F30/12)) -> 2.7777778 | CC30: =IF(OR($BX30<=0,(CC$9-$A30)>($E30*365)),0,IF($A30<=CC$9,$F30/12)) -> 2.7777778 | CD30: =IF(OR($BX30<=0,(CD$9-$A30)>($E30*365)),0,IF($A30<=CD$9,$F30/12)) -> 2.7777778 | CE30: =IF(OR($BX30<=0,(CE$9-$A30)>($E30*365)),0,IF($A30<=CE$9,$F30/12)) -> 2.7777778 | CF30: =IF(OR($BX30<=0,(CF$9-$A30)>($E30*365)),0,IF($A30<=CF$9,$F30/12)) -> 2.7777778 | ... CJ30: =IF(OR($BX30<=0,(CJ$9-$A30)>($E30*365)),0,IF($A30<=CJ$9,$F30/12)) -> 2.7777778 | CK30: =SUM(BY30:CJ30) -> 33.333333 | CL30: =IF(AND($CJ$9>$A30,$CK30<>0),$D30-$S30-$AG30-$AU30-$BI30-$BW30-$CK$10,0) -> -1297.2222 | CM30: =IF(OR($CL30<=0,(CM$9-$A30)>($E30*365)),0,IF($A30<=CM$9,$F30/12)) -> 0 | CN30: =IF(OR($CL30<=0,(CN$9-$A30)>($E30*365)),0,IF($A30<=CN$9,$F30/12)) -> 0 | CO30: =IF(OR($CL30<=0,(CO$9-$A30)>($E30*365)),0,IF($A30<=CO$9,$F30/12)) -> 0 | CP30: =IF(OR($CL30<=0,(CP$9-$A30)>($E30*365)),0,IF($A30<=CP$9,$F30/12)) -> 0 | CQ30: =IF(OR($CL30<=0,(CQ$9-$A30)>($E30*365)),0,IF($A30<=CQ$9,$F30/12)) -> 0 | CR30: =IF(OR($CL30<=0,(CR$9-$A30)>($E30*365)),0,IF($A30<=CR$9,$F30/12)) -> 0 | CS30: =IF(OR($CL30<=0,(CS$9-$A30)>($E30*365)),0,IF($A30<=CS$9,$F30/12)) -> 0 | CT30: =IF(OR($CL30<=0,(CT$9-$A30)>($E30*365)),0,IF($A30<=CT$9,$F30/12)) -> 0 | ... CX30: =IF(OR($CL30<=0,(CX$9-$A30)>($E30*365)),0,IF($A30<=CX$9,$F30/12)) -> 0 | CY30: =SUM(CM30:CX30) -> 0 | CZ30: =IF(AND($CX$9>$A30,$CY30<>0),$D30-$S30-$AG30-$AU30-$BI30-$BW30-$CK30-$CY30,0) -> 0 | DA30: =IF(OR($CZ30<=0,(DA$9-$A30)>($E30*365)),0,IF($A30<=DA$9,$F30/12)) -> 0 | DB30: =IF(OR($CZ30<=0,(DB$9-$A30)>($E30*365)),0,IF($A30<=DB$9,$F30/12)) -> 0 | DC30: =IF(OR($CZ30<=0,(DC$9-$A30)>($E30*365)),0,IF($A30<=DC$9,$F30/12)) -> 0 | DD30: =IF(OR($CZ30<=0,(DD$9-$A30)>($E30*365)),0,IF($A30<=DD$9,$F30/12)) -> 0 | DE30: =IF(OR($CZ30<=0,(DE$9-$A30)>($E30*365)),0,IF($A30<=DE$9,$F30/12)) -> 0 | DF30: =IF(OR($CZ30<=0,(DF$9-$A30)>($E30*365)),0,IF($A30<=DF$9,$F30/12)) -> 0 | DG30: =IF(OR($CZ30<=0,(DG$9-$A30)>($E30*365)),0,IF($A30<=DG$9,$F30/12)) -> 0 | DH30: =IF(OR($CZ30<=0,(DH$9-$A30)>($E30*365)),0,IF($A30<=DH$9,$F30/12)) -> 0 | ... DL30: =IF(OR($CZ30<=0,(DL$9-$A30)>($E30*365)),0,IF($A30<=DL$9,$F30/12)) -> 0 | DM30: =SUM(DA30:DL30) -> 0 | DN30: =IF(AND($DL$9>$A30,$DM30<>0),$D30-$S30-$AG30-$AU30-$BI30-$BW30-$CK$10-$CY30-$DM30,0) -> 0 | DO30: =IF(OR($DN30<=0,(DO$9-$A30)>($E30*365)),0,IF($A30<=DO$9,$F30/12)) -> 0 | DP30: =IF(OR($DN30<=0,(DP$9-$A30)>($E30*365)),0,IF($A30<=DP$9,$F30/12)) -> 0 | DQ30: =IF(OR($DN30<=0,(DQ$9-$A30)>($E30*365)),0,IF($A30<=DQ$9,$F30/12)) -> 0 | DR30: =IF(OR($DN30<=0,(DR$9-$A30)>($E30*365)),0,IF($A30<=DR$9,$F30/12)) -> 0 | DS30: =IF(OR($DN30<=0,(DS$9-$A30)>($E30*365)),0,IF($A30<=DS$9,$F30/12)) -> 0 | DT30: =IF(OR($DN30<=0,(DT$9-$A30)>($E30*365)),0,IF($A30<=DT$9,$F30/12)) -> 0 | DU30: =IF(OR($DN30<=0,(DU$9-$A30)>($E30*365)),0,IF($A30<=DU$9,$F30/12)) -> 0 | DV30: =IF(OR($DN30<=0,(DV$9-$A30)>($E30*365)),0,IF($A30<=DV$9,$F30/12)) -> 0 | ... DZ30: =IF(OR($DN30<=0,(DZ$9-$A30)>($E30*365)),0,IF($A30<=DZ$9,$F30/12)) -> 0 | EA30: =SUM(DO30:DZ30) -> 0 | EB30: =IF(AND($DZ$9>$A30,$EA30<>0),$D30-$S30-$AG30-$AU30-$BI30-$BW30--CY30-$DM30-$CK30-$EA30,0) -> 0
A31: 43102 | B31: Matériels | C31: sésaille vert | D31: 1000 | E31: 3 | F31: =D31/E31 -> 333.33333 | G31: =IF(OR($F31<=0,(G$9-$A31)>(365*$E31)),0,IF($A31<=G$9,$F31/12,0)) -> 0 | H31: =IF(OR($F31<=0,(H$9-$A31)>(365*$E31)),0,IF($A31<=H$9,$F31/12,0)) -> 0 | I31: =IF(OR($F31<=0,(I$9-$A31)>(365*$E31)),0,IF($A31<=I$9,$F31/12,0)) -> 0 | J31: =IF(OR($F31<=0,(J$9-$A31)>(365*$E31)),0,IF($A31<=J$9,$F31/12,0)) -> 0 | K31: =IF(OR($F31<=0,(K$9-$A31)>(365*$E31)),0,IF($A31<=K$9,$F31/12,0)) -> 0 | L31: =IF(OR($F31<=0,(L$9-$A31)>(365*$E31)),0,IF($A31<=L$9,$F31/12,0)) -> 0 | M31: =IF(OR($F31<=0,(M$9-$A31)>(365*$E31)),0,IF($A31<=M$9,$F31/12,0)) -> 0 | N31: =IF(OR($F31<=0,(N$9-$A31)>(365*$E31)),0,IF($A31<=N$9,$F31/12,0)) -> 0 | ... R31: =IF(OR($F31<=0,(R$9-$A31)>(365*$E31)),0,IF($A31<=R$9,$F31/12,0)) -> 0 | S31: =SUM(G31:R31) -> 0 | T31: =IF(AND($R$9>A31,$S31<>0),$D31-$S31,0) -> 0 | U31: =IF(OR($F31<=0,(U$9-$A31)>(365*$E31)),0,IF($A31<=U$9,$F31/12,0)) -> 0 | V31: =IF(OR($F31<=0,(V$9-$A31)>(365*$E31)),0,IF($A31<=V$9,$F31/12,0)) -> 0 | W31: =IF(OR($F31<=0,(W$9-$A31)>(365*$E31)),0,IF($A31<=W$9,$F31/12,0)) -> 0 | X31: =IF(OR($F31<=0,(X$9-$A31)>(365*$E31)),0,IF($A31<=X$9,$F31/12,0)) -> 0 | Y31: =IF(OR($F31<=0,(Y$9-$A31)>(365*$E31)),0,IF($A31<=Y$9,$F31/12,0)) -> 0 | Z31: =IF(OR($F31<=0,(Z$9-$A31)>(365*$E31)),0,IF($A31<=Z$9,$F31/12,0)) -> 0 | AA31: =IF(OR($F31<=0,(AA$9-$A31)>(365*$E31)),0,IF($A31<=AA$9,$F31/12,0)) -> 0 | AB31: =IF(OR($F31<=0,(AB$9-$A31)>(365*$E31)),0,IF($A31<=AB$9,$F31/12,0)) -> 0 | ... AF31: =IF(OR($F31<=0,(AF$9-$A31)>(365*$E31)),0,IF($A31<=AF$9,$F31/12,0)) -> 0 | AG31: =SUM(U31:AF31) -> 0 | AH31: =IF(AND($AF$9>$A31,$AG31<>0),$D31-$S31-$AG31,0) -> 0 | AI31: =IF(OR($F31<=0,(AI$9-$A31)>(365*$E31)),0,IF($A31<=AI$9,$F31/12,0)) -> 0 | AJ31: =IF(OR($F31<=0,(AJ$9-$A31)>(365*$E31)),0,IF($A31<=AJ$9,$F31/12,0)) -> 0 | AK31: =IF(OR($F31<=0,(AK$9-$A31)>(365*$E31)),0,IF($A31<=AK$9,$F31/12,0)) -> 0 | AL31: =IF(OR($F31<=0,(AL$9-$A31)>(365*$E31)),0,IF($A31<=AL$9,$F31/12,0)) -> 0 | AM31: =IF(OR($F31<=0,(AM$9-$A31)>(365*$E31)),0,IF($A31<=AM$9,$F31/12,0)) -> 0 | AN31: =IF(OR($F31<=0,(AN$9-$A31)>(365*$E31)),0,IF($A31<=AN$9,$F31/12,0)) -> 0 | AO31: =IF(OR($F31<=0,(AO$9-$A31)>(365*$E31)),0,IF($A31<=AO$9,$F31/12,0)) -> 0 | AP31: =IF(OR($F31<=0,(AP$9-$A31)>(365*$E31)),0,IF($A31<=AP$9,$F31/12,0)) -> 0 | ... AT31: =IF(OR($F31<=0,(AT$9-$A31)>(365*$E31)),0,IF($A31<=AT$9,$F31/12,0)) -> 0 | AU31: =SUM(AI31:AT31) -> 0 | AV31: =IF(AND($AT$9>$A31,$AU31<>0),$D31-$S31-$AG31-$AU31,0) -> 0 | AW31: =IF(OR($F31<=0,(AW$9-$A31)>(365*$E31)),0,IF($A31<=AW$9,$F31/12,0)) -> 0 | AX31: =IF(OR($F31<=0,(AX$9-$A31)>(365*$E31)),0,IF($A31<=AX$9,$F31/12,0)) -> 0 | AY31: =IF(OR($F31<=0,(AY$9-$A31)>(365*$E31)),0,IF($A31<=AY$9,$F31/12,0)) -> 27.777778 | AZ31: =IF(OR($F31<=0,(AZ$9-$A31)>(365*$E31)),0,IF($A31<=AZ$9,$F31/12,0)) -> 27.777778 | BA31: =IF(OR($F31<=0,(BA$9-$A31)>(365*$E31)),0,IF($A31<=BA$9,$F31/12,0)) -> 27.777778 | BB31: =IF(OR($F31<=0,(BB$9-$A31)>(365*$E31)),0,IF($A31<=BB$9,$F31/12,0)) -> 27.777778 | BC31: =IF(OR($F31<=0,(BC$9-$A31)>(365*$E31)),0,IF($A31<=BC$9,$F31/12,0)) -> 27.777778 | BD31: =IF(OR($F31<=0,(BD$9-$A31)>(365*$E31)),0,IF($A31<=BD$9,$F31/12,0)) -> 27.777778 | ... BH31: =IF(OR($F31<=0,(BH$9-$A31)>(365*$E31)),0,IF($A31<=BH$9,$F31/12,0)) -> 27.777778 | BI31: =SUM(AW31:BH31) -> 277.77778 | BJ31: =IF(AND($BH$9>$A31,$BI31<>0),$D31-$S31-$AG31-$AU31-$BI31,0) -> 722.22222 | BK31: =IF(OR($BJ31<=0,(BK$9-$A31)>($E31*365)),0,IF($A31<=BK$9,$F31/12)) -> 27.777778 | BL31: =IF(OR($BJ31<=0,(BL$9-$A31)>($E31*365)),0,IF($A31<=BL$9,$F31/12)) -> 27.777778 | BM31: =IF(OR($BJ31<=0,(BM$9-$A31)>($E31*365)),0,IF($A31<=BM$9,$F31/12)) -> 27.777778 | BN31: =IF(OR($BJ31<=0,(BN$9-$A31)>($E31*365)),0,IF($A31<=BN$9,$F31/12)) -> 27.777778 | BO31: =IF(OR($BJ31<=0,(BO$9-$A31)>($E31*365)),0,IF($A31<=BO$9,$F31/12)) -> 27.777778 | BP31: =IF(OR($BJ31<=0,(BP$9-$A31)>($E31*365)),0,IF($A31<=BP$9,$F31/12)) -> 27.777778 | BQ31: =IF(OR($BJ31<=0,(BQ$9-$A31)>($E31*365)),0,IF($A31<=BQ$9,$F31/12)) -> 27.777778 | BR31: =IF(OR($BJ31<=0,(BR$9-$A31)>($E31*365)),0,IF($A31<=BR$9,$F31/12)) -> 27.777778 | ... BV31: =IF(OR($BJ31<=0,(BV$9-$A31)>($E31*365)),0,IF($A31<=BV$9,$F31/12)) -> 27.777778 | BW31: =SUM(BK31:BV31) -> 333.33333 | BX31: =IF(AND($BV$9>$A31,$BW31<>0),$D31-$S31-$AG31-$AU31-$BI31-$BW31,0) -> 388.88889 | BY31: =IF(OR($BX31<=0,(BY$9-$A31)>($E31*365)),0,IF($A31<=BY$9,$F31/12)) -> 27.777778 | BZ31: =IF(OR($BX31<=0,(BZ$9-$A31)>($E31*365)),0,IF($A31<=BZ$9,$F31/12)) -> 27.777778 | CA31: =IF(OR($BX31<=0,(CA$9-$A31)>($E31*365)),0,IF($A31<=CA$9,$F31/12)) -> 27.777778 | CB31: =IF(OR($BX31<=0,(CB$9-$A31)>($E31*365)),0,IF($A31<=CB$9,$F31/12)) -> 27.777778 | CC31: =IF(OR($BX31<=0,(CC$9-$A31)>($E31*365)),0,IF($A31<=CC$9,$F31/12)) -> 27.777778 | CD31: =IF(OR($BX31<=0,(CD$9-$A31)>($E31*365)),0,IF($A31<=CD$9,$F31/12)) -> 27.777778 | CE31: =IF(OR($BX31<=0,(CE$9-$A31)>($E31*365)),0,IF($A31<=CE$9,$F31/12)) -> 27.777778 | CF31: =IF(OR($BX31<=0,(CF$9-$A31)>($E31*365)),0,IF($A31<=CF$9,$F31/12)) -> 27.777778 | ... CJ31: =IF(OR($BX31<=0,(CJ$9-$A31)>($E31*365)),0,IF($A31<=CJ$9,$F31/12)) -> 27.777778 | CK31: =SUM(BY31:CJ31) -> 333.33333 | CL31: =IF(AND($CJ$9>$A31,$CK31<>0),$D31-$S31-$AG31-$AU31-$BI31-$BW31-$CK$10,0) -> -944.44444 | CM31: =IF(OR($CL31<=0,(CM$9-$A31)>($E31*365)),0,IF($A31<=CM$9,$F31/12)) -> 0 | CN31: =IF(OR($CL31<=0,(CN$9-$A31)>($E31*365)),0,IF($A31<=CN$9,$F31/12)) -> 0 | CO31: =IF(OR($CL31<=0,(CO$9-$A31)>($E31*365)),0,IF($A31<=CO$9,$F31/12)) -> 0 | CP31: =IF(OR($CL31<=0,(CP$9-$A31)>($E31*365)),0,IF($A31<=CP$9,$F31/12)) -> 0 | CQ31: =IF(OR($CL31<=0,(CQ$9-$A31)>($E31*365)),0,IF($A31<=CQ$9,$F31/12)) -> 0 | CR31: =IF(OR($CL31<=0,(CR$9-$A31)>($E31*365)),0,IF($A31<=CR$9,$F31/12)) -> 0 | CS31: =IF(OR($CL31<=0,(CS$9-$A31)>($E31*365)),0,IF($A31<=CS$9,$F31/12)) -> 0 | CT31: =IF(OR($CL31<=0,(CT$9-$A31)>($E31*365)),0,IF($A31<=CT$9,$F31/12)) -> 0 | ... CX31: =IF(OR($CL31<=0,(CX$9-$A31)>($E31*365)),0,IF($A31<=CX$9,$F31/12)) -> 0 | CY31: =SUM(CM31:CX31) -> 0 | CZ31: =IF(AND($CX$9>$A31,$CY31<>0),$D31-$S31-$AG31-$AU31-$BI31-$BW31-$CK31-$CY31,0) -> 0 | DA31: =IF(OR($CZ31<=0,(DA$9-$A31)>($E31*365)),0,IF($A31<=DA$9,$F31/12)) -> 0 | DB31: =IF(OR($CZ31<=0,(DB$9-$A31)>($E31*365)),0,IF($A31<=DB$9,$F31/12)) -> 0 | DC31: =IF(OR($CZ31<=0,(DC$9-$A31)>($E31*365)),0,IF($A31<=DC$9,$F31/12)) -> 0 | DD31: =IF(OR($CZ31<=0,(DD$9-$A31)>($E31*365)),0,IF($A31<=DD$9,$F31/12)) -> 0 | DE31: =IF(OR($CZ31<=0,(DE$9-$A31)>($E31*365)),0,IF($A31<=DE$9,$F31/12)) -> 0 | DF31: =IF(OR($CZ31<=0,(DF$9-$A31)>($E31*365)),0,IF($A31<=DF$9,$F31/12)) -> 0 | DG31: =IF(OR($CZ31<=0,(DG$9-$A31)>($E31*365)),0,IF($A31<=DG$9,$F31/12)) -> 0 | DH31: =IF(OR($CZ31<=0,(DH$9-$A31)>($E31*365)),0,IF($A31<=DH$9,$F31/12)) -> 0 | ... DL31: =IF(OR($CZ31<=0,(DL$9-$A31)>($E31*365)),0,IF($A31<=DL$9,$F31/12)) -> 0 | DM31: =SUM(DA31:DL31) -> 0 | DN31: =IF(AND($DL$9>$A31,$DM31<>0),$D31-$S31-$AG31-$AU31-$BI31-$BW31-$CK$10-$CY31-$DM31,0) -> 0 | DO31: =IF(OR($DN31<=0,(DO$9-$A31)>($E31*365)),0,IF($A31<=DO$9,$F31/12)) -> 0 | DP31: =IF(OR($DN31<=0,(DP$9-$A31)>($E31*365)),0,IF($A31<=DP$9,$F31/12)) -> 0 | DQ31: =IF(OR($DN31<=0,(DQ$9-$A31)>($E31*365)),0,IF($A31<=DQ$9,$F31/12)) -> 0 | DR31: =IF(OR($DN31<=0,(DR$9-$A31)>($E31*365)),0,IF($A31<=DR$9,$F31/12)) -> 0 | DS31: =IF(OR($DN31<=0,(DS$9-$A31)>($E31*365)),0,IF($A31<=DS$9,$F31/12)) -> 0 | DT31: =IF(OR($DN31<=0,(DT$9-$A31)>($E31*365)),0,IF($A31<=DT$9,$F31/12)) -> 0 | DU31: =IF(OR($DN31<=0,(DU$9-$A31)>($E31*365)),0,IF($A31<=DU$9,$F31/12)) -> 0 | DV31: =IF(OR($DN31<=0,(DV$9-$A31)>($E31*365)),0,IF($A31<=DV$9,$F31/12)) -> 0 | ... DZ31: =IF(OR($DN31<=0,(DZ$9-$A31)>($E31*365)),0,IF($A31<=DZ$9,$F31/12)) -> 0 | EA31: =SUM(DO31:DZ31) -> 0 | EB31: =IF(AND($DZ$9>$A31,$EA31<>0),$D31-$S31-$AG31-$AU31-$BI31-$BW31--CY31-$DM31-$CK31-$EA31,0) -> 0
A32: 43102 | B32: Matériels | C32: serie craveure | D32: 1500 | E32: 5 | F32: =D32/E32 -> 300 | G32: =IF(OR($F32<=0,(G$9-$A32)>(365*$E32)),0,IF($A32<=G$9,$F32/12,0)) -> 0 | H32: =IF(OR($F32<=0,(H$9-$A32)>(365*$E32)),0,IF($A32<=H$9,$F32/12,0)) -> 0 | I32: =IF(OR($F32<=0,(I$9-$A32)>(365*$E32)),0,IF($A32<=I$9,$F32/12,0)) -> 0 | J32: =IF(OR($F32<=0,(J$9-$A32)>(365*$E32)),0,IF($A32<=J$9,$F32/12,0)) -> 0 | K32: =IF(OR($F32<=0,(K$9-$A32)>(365*$E32)),0,IF($A32<=K$9,$F32/12,0)) -> 0 | L32: =IF(OR($F32<=0,(L$9-$A32)>(365*$E32)),0,IF($A32<=L$9,$F32/12,0)) -> 0 | M32: =IF(OR($F32<=0,(M$9-$A32)>(365*$E32)),0,IF($A32<=M$9,$F32/12,0)) -> 0 | N32: =IF(OR($F32<=0,(N$9-$A32)>(365*$E32)),0,IF($A32<=N$9,$F32/12,0)) -> 0 | ... R32: =IF(OR($F32<=0,(R$9-$A32)>(365*$E32)),0,IF($A32<=R$9,$F32/12,0)) -> 0 | S32: =SUM(G32:R32) -> 0 | T32: =IF(AND($R$9>A32,$S32<>0),$D32-$S32,0) -> 0 | U32: =IF(OR($F32<=0,(U$9-$A32)>(365*$E32)),0,IF($A32<=U$9,$F32/12,0)) -> 0 | V32: =IF(OR($F32<=0,(V$9-$A32)>(365*$E32)),0,IF($A32<=V$9,$F32/12,0)) -> 0 | W32: =IF(OR($F32<=0,(W$9-$A32)>(365*$E32)),0,IF($A32<=W$9,$F32/12,0)) -> 0 | X32: =IF(OR($F32<=0,(X$9-$A32)>(365*$E32)),0,IF($A32<=X$9,$F32/12,0)) -> 0 | Y32: =IF(OR($F32<=0,(Y$9-$A32)>(365*$E32)),0,IF($A32<=Y$9,$F32/12,0)) -> 0 | Z32: =IF(OR($F32<=0,(Z$9-$A32)>(365*$E32)),0,IF($A32<=Z$9,$F32/12,0)) -> 0 | AA32: =IF(OR($F32<=0,(AA$9-$A32)>(365*$E32)),0,IF($A32<=AA$9,$F32/12,0)) -> 0 | AB32: =IF(OR($F32<=0,(AB$9-$A32)>(365*$E32)),0,IF($A32<=AB$9,$F32/12,0)) -> 0 | ... AF32: =IF(OR($F32<=0,(AF$9-$A32)>(365*$E32)),0,IF($A32<=AF$9,$F32/12,0)) -> 0 | AG32: =SUM(U32:AF32) -> 0 | AH32: =IF(AND($AF$9>$A32,$AG32<>0),$D32-$S32-$AG32,0) -> 0 | AI32: =IF(OR($F32<=0,(AI$9-$A32)>(365*$E32)),0,IF($A32<=AI$9,$F32/12,0)) -> 0 | AJ32: =IF(OR($F32<=0,(AJ$9-$A32)>(365*$E32)),0,IF($A32<=AJ$9,$F32/12,0)) -> 0 | AK32: =IF(OR($F32<=0,(AK$9-$A32)>(365*$E32)),0,IF($A32<=AK$9,$F32/12,0)) -> 0 | AL32: =IF(OR($F32<=0,(AL$9-$A32)>(365*$E32)),0,IF($A32<=AL$9,$F32/12,0)) -> 0 | AM32: =IF(OR($F32<=0,(AM$9-$A32)>(365*$E32)),0,IF($A32<=AM$9,$F32/12,0)) -> 0 | AN32: =IF(OR($F32<=0,(AN$9-$A32)>(365*$E32)),0,IF($A32<=AN$9,$F32/12,0)) -> 0 | AO32: =IF(OR($F32<=0,(AO$9-$A32)>(365*$E32)),0,IF($A32<=AO$9,$F32/12,0)) -> 0 | AP32: =IF(OR($F32<=0,(AP$9-$A32)>(365*$E32)),0,IF($A32<=AP$9,$F32/12,0)) -> 0 | ... AT32: =IF(OR($F32<=0,(AT$9-$A32)>(365*$E32)),0,IF($A32<=AT$9,$F32/12,0)) -> 0 | AU32: =SUM(AI32:AT32) -> 0 | AV32: =IF(AND($AT$9>$A32,$AU32<>0),$D32-$S32-$AG32-$AU32,0) -> 0 | AW32: =IF(OR($F32<=0,(AW$9-$A32)>(365*$E32)),0,IF($A32<=AW$9,$F32/12,0)) -> 0 | AX32: =IF(OR($F32<=0,(AX$9-$A32)>(365*$E32)),0,IF($A32<=AX$9,$F32/12,0)) -> 0 | AY32: =IF(OR($F32<=0,(AY$9-$A32)>(365*$E32)),0,IF($A32<=AY$9,$F32/12,0)) -> 25 | AZ32: =IF(OR($F32<=0,(AZ$9-$A32)>(365*$E32)),0,IF($A32<=AZ$9,$F32/12,0)) -> 25 | BA32: =IF(OR($F32<=0,(BA$9-$A32)>(365*$E32)),0,IF($A32<=BA$9,$F32/12,0)) -> 25 | BB32: =IF(OR($F32<=0,(BB$9-$A32)>(365*$E32)),0,IF($A32<=BB$9,$F32/12,0)) -> 25 | BC32: =IF(OR($F32<=0,(BC$9-$A32)>(365*$E32)),0,IF($A32<=BC$9,$F32/12,0)) -> 25 | BD32: =IF(OR($F32<=0,(BD$9-$A32)>(365*$E32)),0,IF($A32<=BD$9,$F32/12,0)) -> 25 | ... BH32: =IF(OR($F32<=0,(BH$9-$A32)>(365*$E32)),0,IF($A32<=BH$9,$F32/12,0)) -> 25 | BI32: =SUM(AW32:BH32) -> 250 | BJ32: =IF(AND($BH$9>$A32,$BI32<>0),$D32-$S32-$AG32-$AU32-$BI32,0) -> 1250 | BK32: =IF(OR($BJ32<=0,(BK$9-$A32)>($E32*365)),0,IF($A32<=BK$9,$F32/12)) -> 25 | BL32: =IF(OR($BJ32<=0,(BL$9-$A32)>($E32*365)),0,IF($A32<=BL$9,$F32/12)) -> 25 | BM32: =IF(OR($BJ32<=0,(BM$9-$A32)>($E32*365)),0,IF($A32<=BM$9,$F32/12)) -> 25 | BN32: =IF(OR($BJ32<=0,(BN$9-$A32)>($E32*365)),0,IF($A32<=BN$9,$F32/12)) -> 25 | BO32: =IF(OR($BJ32<=0,(BO$9-$A32)>($E32*365)),0,IF($A32<=BO$9,$F32/12)) -> 25 | BP32: =IF(OR($BJ32<=0,(BP$9-$A32)>($E32*365)),0,IF($A32<=BP$9,$F32/12)) -> 25 | BQ32: =IF(OR($BJ32<=0,(BQ$9-$A32)>($E32*365)),0,IF($A32<=BQ$9,$F32/12)) -> 25 | BR32: =IF(OR($BJ32<=0,(BR$9-$A32)>($E32*365)),0,IF($A32<=BR$9,$F32/12)) -> 25 | ... BV32: =IF(OR($BJ32<=0,(BV$9-$A32)>($E32*365)),0,IF($A32<=BV$9,$F32/12)) -> 25 | BW32: =SUM(BK32:BV32) -> 300 | BX32: =IF(AND($BV$9>$A32,$BW32<>0),$D32-$S32-$AG32-$AU32-$BI32-$BW32,0) -> 950 | BY32: =IF(OR($BX32<=0,(BY$9-$A32)>($E32*365)),0,IF($A32<=BY$9,$F32/12)) -> 25 | BZ32: =IF(OR($BX32<=0,(BZ$9-$A32)>($E32*365)),0,IF($A32<=BZ$9,$F32/12)) -> 25 | CA32: =IF(OR($BX32<=0,(CA$9-$A32)>($E32*365)),0,IF($A32<=CA$9,$F32/12)) -> 25 | CB32: =IF(OR($BX32<=0,(CB$9-$A32)>($E32*365)),0,IF($A32<=CB$9,$F32/12)) -> 25 | CC32: =IF(OR($BX32<=0,(CC$9-$A32)>($E32*365)),0,IF($A32<=CC$9,$F32/12)) -> 25 | CD32: =IF(OR($BX32<=0,(CD$9-$A32)>($E32*365)),0,IF($A32<=CD$9,$F32/12)) -> 25 | CE32: =IF(OR($BX32<=0,(CE$9-$A32)>($E32*365)),0,IF($A32<=CE$9,$F32/12)) -> 25 | CF32: =IF(OR($BX32<=0,(CF$9-$A32)>($E32*365)),0,IF($A32<=CF$9,$F32/12)) -> 25 | ... CJ32: =IF(OR($BX32<=0,(CJ$9-$A32)>($E32*365)),0,IF($A32<=CJ$9,$F32/12)) -> 25 | CK32: =SUM(BY32:CJ32) -> 300 | CL32: =IF(AND($CJ$9>$A32,$CK32<>0),$D32-$S32-$AG32-$AU32-$BI32-$BW32-$CK$10,0) -> -383.33333 | CM32: =IF(OR($CL32<=0,(CM$9-$A32)>($E32*365)),0,IF($A32<=CM$9,$F32/12)) -> 0 | CN32: =IF(OR($CL32<=0,(CN$9-$A32)>($E32*365)),0,IF($A32<=CN$9,$F32/12)) -> 0 | CO32: =IF(OR($CL32<=0,(CO$9-$A32)>($E32*365)),0,IF($A32<=CO$9,$F32/12)) -> 0 | CP32: =IF(OR($CL32<=0,(CP$9-$A32)>($E32*365)),0,IF($A32<=CP$9,$F32/12)) -> 0 | CQ32: =IF(OR($CL32<=0,(CQ$9-$A32)>($E32*365)),0,IF($A32<=CQ$9,$F32/12)) -> 0 | CR32: =IF(OR($CL32<=0,(CR$9-$A32)>($E32*365)),0,IF($A32<=CR$9,$F32/12)) -> 0 | CS32: =IF(OR($CL32<=0,(CS$9-$A32)>($E32*365)),0,IF($A32<=CS$9,$F32/12)) -> 0 | CT32: =IF(OR($CL32<=0,(CT$9-$A32)>($E32*365)),0,IF($A32<=CT$9,$F32/12)) -> 0 | ... CX32: =IF(OR($CL32<=0,(CX$9-$A32)>($E32*365)),0,IF($A32<=CX$9,$F32/12)) -> 0 | CY32: =SUM(CM32:CX32) -> 0 | CZ32: =IF(AND($CX$9>$A32,$CY32<>0),$D32-$S32-$AG32-$AU32-$BI32-$BW32-$CK32-$CY32,0) -> 0 | DA32: =IF(OR($CZ32<=0,(DA$9-$A32)>($E32*365)),0,IF($A32<=DA$9,$F32/12)) -> 0 | DB32: =IF(OR($CZ32<=0,(DB$9-$A32)>($E32*365)),0,IF($A32<=DB$9,$F32/12)) -> 0 | DC32: =IF(OR($CZ32<=0,(DC$9-$A32)>($E32*365)),0,IF($A32<=DC$9,$F32/12)) -> 0 | DD32: =IF(OR($CZ32<=0,(DD$9-$A32)>($E32*365)),0,IF($A32<=DD$9,$F32/12)) -> 0 | DE32: =IF(OR($CZ32<=0,(DE$9-$A32)>($E32*365)),0,IF($A32<=DE$9,$F32/12)) -> 0 | DF32: =IF(OR($CZ32<=0,(DF$9-$A32)>($E32*365)),0,IF($A32<=DF$9,$F32/12)) -> 0 | DG32: =IF(OR($CZ32<=0,(DG$9-$A32)>($E32*365)),0,IF($A32<=DG$9,$F32/12)) -> 0 | DH32: =IF(OR($CZ32<=0,(DH$9-$A32)>($E32*365)),0,IF($A32<=DH$9,$F32/12)) -> 0 | ... DL32: =IF(OR($CZ32<=0,(DL$9-$A32)>($E32*365)),0,IF($A32<=DL$9,$F32/12)) -> 0 | DM32: =SUM(DA32:DL32) -> 0 | DN32: =IF(AND($DL$9>$A32,$DM32<>0),$D32-$S32-$AG32-$AU32-$BI32-$BW32-$CK$10-$CY32-$DM32,0) -> 0 | DO32: =IF(OR($DN32<=0,(DO$9-$A32)>($E32*365)),0,IF($A32<=DO$9,$F32/12)) -> 0 | DP32: =IF(OR($DN32<=0,(DP$9-$A32)>($E32*365)),0,IF($A32<=DP$9,$F32/12)) -> 0 | DQ32: =IF(OR($DN32<=0,(DQ$9-$A32)>($E32*365)),0,IF($A32<=DQ$9,$F32/12)) -> 0 | DR32: =IF(OR($DN32<=0,(DR$9-$A32)>($E32*365)),0,IF($A32<=DR$9,$F32/12)) -> 0 | DS32: =IF(OR($DN32<=0,(DS$9-$A32)>($E32*365)),0,IF($A32<=DS$9,$F32/12)) -> 0 | DT32: =IF(OR($DN32<=0,(DT$9-$A32)>($E32*365)),0,IF($A32<=DT$9,$F32/12)) -> 0 | DU32: =IF(OR($DN32<=0,(DU$9-$A32)>($E32*365)),0,IF($A32<=DU$9,$F32/12)) -> 0 | DV32: =IF(OR($DN32<=0,(DV$9-$A32)>($E32*365)),0,IF($A32<=DV$9,$F32/12)) -> 0 | ... DZ32: =IF(OR($DN32<=0,(DZ$9-$A32)>($E32*365)),0,IF($A32<=DZ$9,$F32/12)) -> 0 | EA32: =SUM(DO32:DZ32) -> 0 | EB32: =IF(AND($DZ$9>$A32,$EA32<>0),$D32-$S32-$AG32-$AU32-$BI32-$BW32--CY32-$DM32-$CK32-$EA32,0) -> 0
A33: 43178 | B33: Matériels | C33: chaises | D33: 2200 | E33: 3 | F33: =D33/E33 -> 733.33333 | G33: =IF(OR($F33<=0,(G$9-$A33)>(365*$E33)),0,IF($A33<=G$9,$F33/12,0)) -> 0 | H33: =IF(OR($F33<=0,(H$9-$A33)>(365*$E33)),0,IF($A33<=H$9,$F33/12,0)) -> 0 | I33: =IF(OR($F33<=0,(I$9-$A33)>(365*$E33)),0,IF($A33<=I$9,$F33/12,0)) -> 0 | J33: =IF(OR($F33<=0,(J$9-$A33)>(365*$E33)),0,IF($A33<=J$9,$F33/12,0)) -> 0 | K33: =IF(OR($F33<=0,(K$9-$A33)>(365*$E33)),0,IF($A33<=K$9,$F33/12,0)) -> 0 | L33: =IF(OR($F33<=0,(L$9-$A33)>(365*$E33)),0,IF($A33<=L$9,$F33/12,0)) -> 0 | M33: =IF(OR($F33<=0,(M$9-$A33)>(365*$E33)),0,IF($A33<=M$9,$F33/12,0)) -> 0 | N33: =IF(OR($F33<=0,(N$9-$A33)>(365*$E33)),0,IF($A33<=N$9,$F33/12,0)) -> 0 | ... R33: =IF(OR($F33<=0,(R$9-$A33)>(365*$E33)),0,IF($A33<=R$9,$F33/12,0)) -> 0 | S33: =SUM(G33:R33) -> 0 | T33: =IF(AND($R$9>A33,$S33<>0),$D33-$S33,0) -> 0 | U33: =IF(OR($F33<=0,(U$9-$A33)>(365*$E33)),0,IF($A33<=U$9,$F33/12,0)) -> 0 | V33: =IF(OR($F33<=0,(V$9-$A33)>(365*$E33)),0,IF($A33<=V$9,$F33/12,0)) -> 0 | W33: =IF(OR($F33<=0,(W$9-$A33)>(365*$E33)),0,IF($A33<=W$9,$F33/12,0)) -> 0 | X33: =IF(OR($F33<=0,(X$9-$A33)>(365*$E33)),0,IF($A33<=X$9,$F33/12,0)) -> 0 | Y33: =IF(OR($F33<=0,(Y$9-$A33)>(365*$E33)),0,IF($A33<=Y$9,$F33/12,0)) -> 0 | Z33: =IF(OR($F33<=0,(Z$9-$A33)>(365*$E33)),0,IF($A33<=Z$9,$F33/12,0)) -> 0 | AA33: =IF(OR($F33<=0,(AA$9-$A33)>(365*$E33)),0,IF($A33<=AA$9,$F33/12,0)) -> 0 | AB33: =IF(OR($F33<=0,(AB$9-$A33)>(365*$E33)),0,IF($A33<=AB$9,$F33/12,0)) -> 0 | ... AF33: =IF(OR($F33<=0,(AF$9-$A33)>(365*$E33)),0,IF($A33<=AF$9,$F33/12,0)) -> 0 | AG33: =SUM(U33:AF33) -> 0 | AH33: =IF(AND($AF$9>$A33,$AG33<>0),$D33-$S33-$AG33,0) -> 0 | AI33: =IF(OR($F33<=0,(AI$9-$A33)>(365*$E33)),0,IF($A33<=AI$9,$F33/12,0)) -> 0 | AJ33: =IF(OR($F33<=0,(AJ$9-$A33)>(365*$E33)),0,IF($A33<=AJ$9,$F33/12,0)) -> 0 | AK33: =IF(OR($F33<=0,(AK$9-$A33)>(365*$E33)),0,IF($A33<=AK$9,$F33/12,0)) -> 0 | AL33: =IF(OR($F33<=0,(AL$9-$A33)>(365*$E33)),0,IF($A33<=AL$9,$F33/12,0)) -> 0 | AM33: =IF(OR($F33<=0,(AM$9-$A33)>(365*$E33)),0,IF($A33<=AM$9,$F33/12,0)) -> 0 | AN33: =IF(OR($F33<=0,(AN$9-$A33)>(365*$E33)),0,IF($A33<=AN$9,$F33/12,0)) -> 0 | AO33: =IF(OR($F33<=0,(AO$9-$A33)>(365*$E33)),0,IF($A33<=AO$9,$F33/12,0)) -> 0 | AP33: =IF(OR($F33<=0,(AP$9-$A33)>(365*$E33)),0,IF($A33<=AP$9,$F33/12,0)) -> 0 | ... AT33: =IF(OR($F33<=0,(AT$9-$A33)>(365*$E33)),0,IF($A33<=AT$9,$F33/12,0)) -> 0 | AU33: =SUM(AI33:AT33) -> 0 | AV33: =IF(AND($AT$9>$A33,$AU33<>0),$D33-$S33-$AG33-$AU33,0) -> 0 | AW33: =IF(OR($F33<=0,(AW$9-$A33)>(365*$E33)),0,IF($A33<=AW$9,$F33/12,0)) -> 0 | AX33: =IF(OR($F33<=0,(AX$9-$A33)>(365*$E33)),0,IF($A33<=AX$9,$F33/12,0)) -> 0 | AY33: =IF(OR($F33<=0,(AY$9-$A33)>(365*$E33)),0,IF($A33<=AY$9,$F33/12,0)) -> 0 | AZ33: =IF(OR($F33<=0,(AZ$9-$A33)>(365*$E33)),0,IF($A33<=AZ$9,$F33/12,0)) -> 0 | BA33: =IF(OR($F33<=0,(BA$9-$A33)>(365*$E33)),0,IF($A33<=BA$9,$F33/12,0)) -> 61.111111 | BB33: =IF(OR($F33<=0,(BB$9-$A33)>(365*$E33)),0,IF($A33<=BB$9,$F33/12,0)) -> 61.111111 | BC33: =IF(OR($F33<=0,(BC$9-$A33)>(365*$E33)),0,IF($A33<=BC$9,$F33/12,0)) -> 61.111111 | BD33: =IF(OR($F33<=0,(BD$9-$A33)>(365*$E33)),0,IF($A33<=BD$9,$F33/12,0)) -> 61.111111 | ... BH33: =IF(OR($F33<=0,(BH$9-$A33)>(365*$E33)),0,IF($A33<=BH$9,$F33/12,0)) -> 61.111111 | BI33: =SUM(AW33:BH33) -> 488.88889 | BJ33: =IF(AND($BH$9>$A33,$BI33<>0),$D33-$S33-$AG33-$AU33-$BI33,0) -> 1711.1111 | BK33: =IF(OR($BJ33<=0,(BK$9-$A33)>($E33*365)),0,IF($A33<=BK$9,$F33/12)) -> 61.111111 | BL33: =IF(OR($BJ33<=0,(BL$9-$A33)>($E33*365)),0,IF($A33<=BL$9,$F33/12)) -> 61.111111 | BM33: =IF(OR($BJ33<=0,(BM$9-$A33)>($E33*365)),0,IF($A33<=BM$9,$F33/12)) -> 61.111111 | BN33: =IF(OR($BJ33<=0,(BN$9-$A33)>($E33*365)),0,IF($A33<=BN$9,$F33/12)) -> 61.111111 | BO33: =IF(OR($BJ33<=0,(BO$9-$A33)>($E33*365)),0,IF($A33<=BO$9,$F33/12)) -> 61.111111 | BP33: =IF(OR($BJ33<=0,(BP$9-$A33)>($E33*365)),0,IF($A33<=BP$9,$F33/12)) -> 61.111111 | BQ33: =IF(OR($BJ33<=0,(BQ$9-$A33)>($E33*365)),0,IF($A33<=BQ$9,$F33/12)) -> 61.111111 | BR33: =IF(OR($BJ33<=0,(BR$9-$A33)>($E33*365)),0,IF($A33<=BR$9,$F33/12)) -> 61.111111 | ... BV33: =IF(OR($BJ33<=0,(BV$9-$A33)>($E33*365)),0,IF($A33<=BV$9,$F33/12)) -> 61.111111 | BW33: =SUM(BK33:BV33) -> 733.33333 | BX33: =IF(AND($BV$9>$A33,$BW33<>0),$D33-$S33-$AG33-$AU33-$BI33-$BW33,0) -> 977.77778 | BY33: =IF(OR($BX33<=0,(BY$9-$A33)>($E33*365)),0,IF($A33<=BY$9,$F33/12)) -> 61.111111 | BZ33: =IF(OR($BX33<=0,(BZ$9-$A33)>($E33*365)),0,IF($A33<=BZ$9,$F33/12)) -> 61.111111 | CA33: =IF(OR($BX33<=0,(CA$9-$A33)>($E33*365)),0,IF($A33<=CA$9,$F33/12)) -> 61.111111 | CB33: =IF(OR($BX33<=0,(CB$9-$A33)>($E33*365)),0,IF($A33<=CB$9,$F33/12)) -> 61.111111 | CC33: =IF(OR($BX33<=0,(CC$9-$A33)>($E33*365)),0,IF($A33<=CC$9,$F33/12)) -> 61.111111 | CD33: =IF(OR($BX33<=0,(CD$9-$A33)>($E33*365)),0,IF($A33<=CD$9,$F33/12)) -> 61.111111 | CE33: =IF(OR($BX33<=0,(CE$9-$A33)>($E33*365)),0,IF($A33<=CE$9,$F33/12)) -> 61.111111 | CF33: =IF(OR($BX33<=0,(CF$9-$A33)>($E33*365)),0,IF($A33<=CF$9,$F33/12)) -> 61.111111 | ... CJ33: =IF(OR($BX33<=0,(CJ$9-$A33)>($E33*365)),0,IF($A33<=CJ$9,$F33/12)) -> 61.111111 | CK33: =SUM(BY33:CJ33) -> 733.33333 | CL33: =IF(AND($CJ$9>$A33,$CK33<>0),$D33-$S33-$AG33-$AU33-$BI33-$BW33-$CK$10,0) -> -355.55556 | CM33: =IF(OR($CL33<=0,(CM$9-$A33)>($E33*365)),0,IF($A33<=CM$9,$F33/12)) -> 0 | CN33: =IF(OR($CL33<=0,(CN$9-$A33)>($E33*365)),0,IF($A33<=CN$9,$F33/12)) -> 0 | CO33: =IF(OR($CL33<=0,(CO$9-$A33)>($E33*365)),0,IF($A33<=CO$9,$F33/12)) -> 0 | CP33: =IF(OR($CL33<=0,(CP$9-$A33)>($E33*365)),0,IF($A33<=CP$9,$F33/12)) -> 0 | CQ33: =IF(OR($CL33<=0,(CQ$9-$A33)>($E33*365)),0,IF($A33<=CQ$9,$F33/12)) -> 0 | CR33: =IF(OR($CL33<=0,(CR$9-$A33)>($E33*365)),0,IF($A33<=CR$9,$F33/12)) -> 0 | CS33: =IF(OR($CL33<=0,(CS$9-$A33)>($E33*365)),0,IF($A33<=CS$9,$F33/12)) -> 0 | CT33: =IF(OR($CL33<=0,(CT$9-$A33)>($E33*365)),0,IF($A33<=CT$9,$F33/12)) -> 0 | ... CX33: =IF(OR($CL33<=0,(CX$9-$A33)>($E33*365)),0,IF($A33<=CX$9,$F33/12)) -> 0 | CY33: =SUM(CM33:CX33) -> 0 | CZ33: =IF(AND($CX$9>$A33,$CY33<>0),$D33-$S33-$AG33-$AU33-$BI33-$BW33-$CK33-$CY33,0) -> 0 | DA33: =IF(OR($CZ33<=0,(DA$9-$A33)>($E33*365)),0,IF($A33<=DA$9,$F33/12)) -> 0 | DB33: =IF(OR($CZ33<=0,(DB$9-$A33)>($E33*365)),0,IF($A33<=DB$9,$F33/12)) -> 0 | DC33: =IF(OR($CZ33<=0,(DC$9-$A33)>($E33*365)),0,IF($A33<=DC$9,$F33/12)) -> 0 | DD33: =IF(OR($CZ33<=0,(DD$9-$A33)>($E33*365)),0,IF($A33<=DD$9,$F33/12)) -> 0 | DE33: =IF(OR($CZ33<=0,(DE$9-$A33)>($E33*365)),0,IF($A33<=DE$9,$F33/12)) -> 0 | DF33: =IF(OR($CZ33<=0,(DF$9-$A33)>($E33*365)),0,IF($A33<=DF$9,$F33/12)) -> 0 | DG33: =IF(OR($CZ33<=0,(DG$9-$A33)>($E33*365)),0,IF($A33<=DG$9,$F33/12)) -> 0 | DH33: =IF(OR($CZ33<=0,(DH$9-$A33)>($E33*365)),0,IF($A33<=DH$9,$F33/12)) -> 0 | ... DL33: =IF(OR($CZ33<=0,(DL$9-$A33)>($E33*365)),0,IF($A33<=DL$9,$F33/12)) -> 0 | DM33: =SUM(DA33:DL33) -> 0 | DN33: =IF(AND($DL$9>$A33,$DM33<>0),$D33-$S33-$AG33-$AU33-$BI33-$BW33-$CK$10-$CY33-$DM33,0) -> 0 | DO33: =IF(OR($DN33<=0,(DO$9-$A33)>($E33*365)),0,IF($A33<=DO$9,$F33/12)) -> 0 | DP33: =IF(OR($DN33<=0,(DP$9-$A33)>($E33*365)),0,IF($A33<=DP$9,$F33/12)) -> 0 | DQ33: =IF(OR($DN33<=0,(DQ$9-$A33)>($E33*365)),0,IF($A33<=DQ$9,$F33/12)) -> 0 | DR33: =IF(OR($DN33<=0,(DR$9-$A33)>($E33*365)),0,IF($A33<=DR$9,$F33/12)) -> 0 | DS33: =IF(OR($DN33<=0,(DS$9-$A33)>($E33*365)),0,IF($A33<=DS$9,$F33/12)) -> 0 | DT33: =IF(OR($DN33<=0,(DT$9-$A33)>($E33*365)),0,IF($A33<=DT$9,$F33/12)) -> 0 | DU33: =IF(OR($DN33<=0,(DU$9-$A33)>($E33*365)),0,IF($A33<=DU$9,$F33/12)) -> 0 | DV33: =IF(OR($DN33<=0,(DV$9-$A33)>($E33*365)),0,IF($A33<=DV$9,$F33/12)) -> 0 | ... DZ33: =IF(OR($DN33<=0,(DZ$9-$A33)>($E33*365)),0,IF($A33<=DZ$9,$F33/12)) -> 0 | EA33: =SUM(DO33:DZ33) -> 0 | EB33: =IF(AND($DZ$9>$A33,$EA33<>0),$D33-$S33-$AG33-$AU33-$BI33-$BW33--CY33-$DM33-$CK33-$EA33,0) -> 0
A34: 43280 | B34: Matériels | C34: purseuse | D34: 15000 | E34: 5 | F34: =D34/E34 -> 3000 | G34: =IF(OR($F34<=0,(G$9-$A34)>(365*$E34)),0,IF($A34<=G$9,$F34/12,0)) -> 0 | H34: =IF(OR($F34<=0,(H$9-$A34)>(365*$E34)),0,IF($A34<=H$9,$F34/12,0)) -> 0 | I34: =IF(OR($F34<=0,(I$9-$A34)>(365*$E34)),0,IF($A34<=I$9,$F34/12,0)) -> 0 | J34: =IF(OR($F34<=0,(J$9-$A34)>(365*$E34)),0,IF($A34<=J$9,$F34/12,0)) -> 0 | K34: =IF(OR($F34<=0,(K$9-$A34)>(365*$E34)),0,IF($A34<=K$9,$F34/12,0)) -> 0 | L34: =IF(OR($F34<=0,(L$9-$A34)>(365*$E34)),0,IF($A34<=L$9,$F34/12,0)) -> 0 | M34: =IF(OR($F34<=0,(M$9-$A34)>(365*$E34)),0,IF($A34<=M$9,$F34/12,0)) -> 0 | N34: =IF(OR($F34<=0,(N$9-$A34)>(365*$E34)),0,IF($A34<=N$9,$F34/12,0)) -> 0 | ... R34: =IF(OR($F34<=0,(R$9-$A34)>(365*$E34)),0,IF($A34<=R$9,$F34/12,0)) -> 0 | S34: =SUM(G34:R34) -> 0 | T34: =IF(AND($R$9>A34,$S34<>0),$D34-$S34,0) -> 0 | U34: =IF(OR($F34<=0,(U$9-$A34)>(365*$E34)),0,IF($A34<=U$9,$F34/12,0)) -> 0 | V34: =IF(OR($F34<=0,(V$9-$A34)>(365*$E34)),0,IF($A34<=V$9,$F34/12,0)) -> 0 | W34: =IF(OR($F34<=0,(W$9-$A34)>(365*$E34)),0,IF($A34<=W$9,$F34/12,0)) -> 0 | X34: =IF(OR($F34<=0,(X$9-$A34)>(365*$E34)),0,IF($A34<=X$9,$F34/12,0)) -> 0 | Y34: =IF(OR($F34<=0,(Y$9-$A34)>(365*$E34)),0,IF($A34<=Y$9,$F34/12,0)) -> 0 | Z34: =IF(OR($F34<=0,(Z$9-$A34)>(365*$E34)),0,IF($A34<=Z$9,$F34/12,0)) -> 0 | AA34: =IF(OR($F34<=0,(AA$9-$A34)>(365*$E34)),0,IF($A34<=AA$9,$F34/12,0)) -> 0 | AB34: =IF(OR($F34<=0,(AB$9-$A34)>(365*$E34)),0,IF($A34<=AB$9,$F34/12,0)) -> 0 | ... AF34: =IF(OR($F34<=0,(AF$9-$A34)>(365*$E34)),0,IF($A34<=AF$9,$F34/12,0)) -> 0 | AG34: =SUM(U34:AF34) -> 0 | AH34: =IF(AND($AF$9>$A34,$AG34<>0),$D34-$S34-$AG34,0) -> 0 | AI34: =IF(OR($F34<=0,(AI$9-$A34)>(365*$E34)),0,IF($A34<=AI$9,$F34/12,0)) -> 0 | AJ34: =IF(OR($F34<=0,(AJ$9-$A34)>(365*$E34)),0,IF($A34<=AJ$9,$F34/12,0)) -> 0 | AK34: =IF(OR($F34<=0,(AK$9-$A34)>(365*$E34)),0,IF($A34<=AK$9,$F34/12,0)) -> 0 | AL34: =IF(OR($F34<=0,(AL$9-$A34)>(365*$E34)),0,IF($A34<=AL$9,$F34/12,0)) -> 0 | AM34: =IF(OR($F34<=0,(AM$9-$A34)>(365*$E34)),0,IF($A34<=AM$9,$F34/12,0)) -> 0 | AN34: =IF(OR($F34<=0,(AN$9-$A34)>(365*$E34)),0,IF($A34<=AN$9,$F34/12,0)) -> 0 | AO34: =IF(OR($F34<=0,(AO$9-$A34)>(365*$E34)),0,IF($A34<=AO$9,$F34/12,0)) -> 0 | AP34: =IF(OR($F34<=0,(AP$9-$A34)>(365*$E34)),0,IF($A34<=AP$9,$F34/12,0)) -> 0 | ... AT34: =IF(OR($F34<=0,(AT$9-$A34)>(365*$E34)),0,IF($A34<=AT$9,$F34/12,0)) -> 0 | AU34: =SUM(AI34:AT34) -> 0 | AV34: =IF(AND($AT$9>$A34,$AU34<>0),$D34-$S34-$AG34-$AU34,0) -> 0 | AW34: =IF(OR($F34<=0,(AW$9-$A34)>(365*$E34)),0,IF($A34<=AW$9,$F34/12,0)) -> 0 | AX34: =IF(OR($F34<=0,(AX$9-$A34)>(365*$E34)),0,IF($A34<=AX$9,$F34/12,0)) -> 0 | AY34: =IF(OR($F34<=0,(AY$9-$A34)>(365*$E34)),0,IF($A34<=AY$9,$F34/12,0)) -> 0 | AZ34: =IF(OR($F34<=0,(AZ$9-$A34)>(365*$E34)),0,IF($A34<=AZ$9,$F34/12,0)) -> 0 | BA34: =IF(OR($F34<=0,(BA$9-$A34)>(365*$E34)),0,IF($A34<=BA$9,$F34/12,0)) -> 0 | BB34: =IF(OR($F34<=0,(BB$9-$A34)>(365*$E34)),0,IF($A34<=BB$9,$F34/12,0)) -> 0 | BC34: =IF(OR($F34<=0,(BC$9-$A34)>(365*$E34)),0,IF($A34<=BC$9,$F34/12,0)) -> 0 | BD34: =IF(OR($F34<=0,(BD$9-$A34)>(365*$E34)),0,IF($A34<=BD$9,$F34/12,0)) -> 250 | ... BH34: =IF(OR($F34<=0,(BH$9-$A34)>(365*$E34)),0,IF($A34<=BH$9,$F34/12,0)) -> 250 | BI34: =SUM(AW34:BH34) -> 1250 | BJ34: =IF(AND($BH$9>$A34,$BI34<>0),$D34-$S34-$AG34-$AU34-$BI34,0) -> 13750 | BK34: =IF(OR($BJ34<=0,(BK$9-$A34)>($E34*365)),0,IF($A34<=BK$9,$F34/12)) -> 250 | BL34: =IF(OR($BJ34<=0,(BL$9-$A34)>($E34*365)),0,IF($A34<=BL$9,$F34/12)) -> 250 | BM34: =IF(OR($BJ34<=0,(BM$9-$A34)>($E34*365)),0,IF($A34<=BM$9,$F34/12)) -> 250 | BN34: =IF(OR($BJ34<=0,(BN$9-$A34)>($E34*365)),0,IF($A34<=BN$9,$F34/12)) -> 250 | BO34: =IF(OR($BJ34<=0,(BO$9-$A34)>($E34*365)),0,IF($A34<=BO$9,$F34/12)) -> 250 | BP34: =IF(OR($BJ34<=0,(BP$9-$A34)>($E34*365)),0,IF($A34<=BP$9,$F34/12)) -> 250 | BQ34: =IF(OR($BJ34<=0,(BQ$9-$A34)>($E34*365)),0,IF($A34<=BQ$9,$F34/12)) -> 250 | BR34: =IF(OR($BJ34<=0,(BR$9-$A34)>($E34*365)),0,IF($A34<=BR$9,$F34/12)) -> 250 | ... BV34: =IF(OR($BJ34<=0,(BV$9-$A34)>($E34*365)),0,IF($A34<=BV$9,$F34/12)) -> 250 | BW34: =SUM(BK34:BV34) -> 3000 | BX34: =IF(AND($BV$9>$A34,$BW34<>0),$D34-$S34-$AG34-$AU34-$BI34-$BW34,0) -> 10750 | BY34: =IF(OR($BX34<=0,(BY$9-$A34)>($E34*365)),0,IF($A34<=BY$9,$F34/12)) -> 250 | BZ34: =IF(OR($BX34<=0,(BZ$9-$A34)>($E34*365)),0,IF($A34<=BZ$9,$F34/12)) -> 250 | CA34: =IF(OR($BX34<=0,(CA$9-$A34)>($E34*365)),0,IF($A34<=CA$9,$F34/12)) -> 250 | CB34: =IF(OR($BX34<=0,(CB$9-$A34)>($E34*365)),0,IF($A34<=CB$9,$F34/12)) -> 250 | CC34: =IF(OR($BX34<=0,(CC$9-$A34)>($E34*365)),0,IF($A34<=CC$9,$F34/12)) -> 250 | CD34: =IF(OR($BX34<=0,(CD$9-$A34)>($E34*365)),0,IF($A34<=CD$9,$F34/12)) -> 250 | CE34: =IF(OR($BX34<=0,(CE$9-$A34)>($E34*365)),0,IF($A34<=CE$9,$F34/12)) -> 250 | CF34: =IF(OR($BX34<=0,(CF$9-$A34)>($E34*365)),0,IF($A34<=CF$9,$F34/12)) -> 250 | ... CJ34: =IF(OR($BX34<=0,(CJ$9-$A34)>($E34*365)),0,IF($A34<=CJ$9,$F34/12)) -> 250 | CK34: =SUM(BY34:CJ34) -> 3000 | CL34: =IF(AND($CJ$9>$A34,$CK34<>0),$D34-$S34-$AG34-$AU34-$BI34-$BW34-$CK$10,0) -> 9416.6667 | CM34: =IF(OR($CL34<=0,(CM$9-$A34)>($E34*365)),0,IF($A34<=CM$9,$F34/12)) -> 250 | CN34: =IF(OR($CL34<=0,(CN$9-$A34)>($E34*365)),0,IF($A34<=CN$9,$F34/12)) -> 250 | CO34: =IF(OR($CL34<=0,(CO$9-$A34)>($E34*365)),0,IF($A34<=CO$9,$F34/12)) -> 250 | CP34: =IF(OR($CL34<=0,(CP$9-$A34)>($E34*365)),0,IF($A34<=CP$9,$F34/12)) -> 250 | CQ34: =IF(OR($CL34<=0,(CQ$9-$A34)>($E34*365)),0,IF($A34<=CQ$9,$F34/12)) -> 250 | CR34: =IF(OR($CL34<=0,(CR$9-$A34)>($E34*365)),0,IF($A34<=CR$9,$F34/12)) -> 250 | CS34: =IF(OR($CL34<=0,(CS$9-$A34)>($E34*365)),0,IF($A34<=CS$9,$F34/12)) -> 250 | CT34: =IF(OR($CL34<=0,(CT$9-$A34)>($E34*365)),0,IF($A34<=CT$9,$F34/12)) -> 250 | ... CX34: =IF(OR($CL34<=0,(CX$9-$A34)>($E34*365)),0,IF($A34<=CX$9,$F34/12)) -> 250 | CY34: =SUM(CM34:CX34) -> 3000 | CZ34: =IF(AND($CX$9>$A34,$CY34<>0),$D34-$S34-$AG34-$AU34-$BI34-$BW34-$CK34-$CY34,0) -> 4750 | DA34: =IF(OR($CZ34<=0,(DA$9-$A34)>($E34*365)),0,IF($A34<=DA$9,$F34/12)) -> 250 | DB34: =IF(OR($CZ34<=0,(DB$9-$A34)>($E34*365)),0,IF($A34<=DB$9,$F34/12)) -> 250 | DC34: =IF(OR($CZ34<=0,(DC$9-$A34)>($E34*365)),0,IF($A34<=DC$9,$F34/12)) -> 250 | DD34: =IF(OR($CZ34<=0,(DD$9-$A34)>($E34*365)),0,IF($A34<=DD$9,$F34/12)) -> 250 | DE34: =IF(OR($CZ34<=0,(DE$9-$A34)>($E34*365)),0,IF($A34<=DE$9,$F34/12)) -> 250 | DF34: =IF(OR($CZ34<=0,(DF$9-$A34)>($E34*365)),0,IF($A34<=DF$9,$F34/12)) -> 250 | DG34: =IF(OR($CZ34<=0,(DG$9-$A34)>($E34*365)),0,IF($A34<=DG$9,$F34/12)) -> 250 | DH34: =IF(OR($CZ34<=0,(DH$9-$A34)>($E34*365)),0,IF($A34<=DH$9,$F34/12)) -> 250 | ... DL34: =IF(OR($CZ34<=0,(DL$9-$A34)>($E34*365)),0,IF($A34<=DL$9,$F34/12)) -> 250 | DM34: =SUM(DA34:DL34) -> 3000 | DN34: =IF(AND($DL$9>$A34,$DM34<>0),$D34-$S34-$AG34-$AU34-$BI34-$BW34-$CK$10-$CY34-$DM34,0) -> 3416.6667 | DO34: =IF(OR($DN34<=0,(DO$9-$A34)>($E34*365)),0,IF($A34<=DO$9,$F34/12)) -> 250 | DP34: =IF(OR($DN34<=0,(DP$9-$A34)>($E34*365)),0,IF($A34<=DP$9,$F34/12)) -> 250 | DQ34: =IF(OR($DN34<=0,(DQ$9-$A34)>($E34*365)),0,IF($A34<=DQ$9,$F34/12)) -> 250 | DR34: =IF(OR($DN34<=0,(DR$9-$A34)>($E34*365)),0,IF($A34<=DR$9,$F34/12)) -> 250 | DS34: =IF(OR($DN34<=0,(DS$9-$A34)>($E34*365)),0,IF($A34<=DS$9,$F34/12)) -> 250 | DT34: =IF(OR($DN34<=0,(DT$9-$A34)>($E34*365)),0,IF($A34<=DT$9,$F34/12)) -> 250 | DU34: =IF(OR($DN34<=0,(DU$9-$A34)>($E34*365)),0,IF($A34<=DU$9,$F34/12)) -> 250 | DV34: =IF(OR($DN34<=0,(DV$9-$A34)>($E34*365)),0,IF($A34<=DV$9,$F34/12)) -> 0 | ... DZ34: =IF(OR($DN34<=0,(DZ$9-$A34)>($E34*365)),0,IF($A34<=DZ$9,$F34/12)) -> 0 | EA34: =SUM(DO34:DZ34) -> 1750 | EB34: =IF(AND($DZ$9>$A34,$EA34<>0),$D34-$S34-$AG34-$AU34-$BI34-$BW34--CY34-$DM34-$CK34-$EA34,0) -> 6000
